Workbook

Sheet Data Cruda
A1: Año | B1: Fecha | C1: Mes | D1: Cliente | E1: Descripción | F1: PAÍS | G1: ZONA | H1: DEPARTAMENTO | I1: Sector | J1: Refrigerante | K1: Importe total | L1: TIPO DE PROYECTO | M1: CODIGO PROYECTO | N1: Columna1 | O1: Margen Comercial | P1: MARGEN COMERCIAL2 | Q1: Descripción2
A2: 2014 | B2: 41641 | C2: Enero | D2: REFRINDUS EIRL | E2: - BOTELLAS DE REFRIGERANTE | F2: PERÚ | G2: SUR | H2: ICA | I2: OTROS | J2: Glicol | K2: 738.56 | O2: 0 | P2: 0
A3: 2014 | B3: 41642 | C3: Enero | D3: METALMECANICA PAV E.I.R.L. | E3: - DILUYENTE JETPOXY 100, JET 70MP BLANCO HR (A+ B | F3: PERÚ | G3: SUR | H3: ICA | I3: OTROS | J3: Venta directa | K3: 2180.68 | O3: 0 | P3: 0
A4: 2014 | B4: 41642 | C4: Enero | D4: AGRICOLA CHAPI SA | E4: - 2 PARES DE RESISTENCIA ELECTRICA DE BANDEJA DE | F4: PERÚ | G4: SUR | H4: ICA | I4: OTROS | J4: Venta directa | K4: 980 | O4: 0 | P4: 0
A5: 2014 | B5: 41645 | C5: Enero | D5: SUN FRUITS EXPORTS S.A. | E5: - OF 0105PRESOSTATO DE BAJA KP1A, CON RESET AUTOM | F5: PERÚ | G5: SUR | H5: ICA | I5: OTROS | J5: Venta directa | K5: 400 | O5: 0 | P5: 0
A6: 2014 | B6: 41645 | C6: Enero | D6: RVR AGRO E.I.R.L. | E6: - OF 0102RESISTENCIAS PARA EVAPORADOR, DE ACERO I | F6: PERÚ | G6: SUR | H6: ICA | I6: OTROS | J6: Venta directa | K6: 1280 | O6: 0 | P6: 0
A7: 2014 | B7: 41645 | C7: Enero | D7: EMPACADORA Y PROCESADORA HUAMANI SAC | E7: - VENTILADOR EVAPORATIVO DE 48" | F7: PERÚ | G7: SUR | H7: ICA | I7: OTROS | J7: Venta directa | K7: 6600 | O7: 0 | P7: 0
A8: 2014 | B8: 41645 | C8: Enero | D8: CAMPOSOL S.A. | E8: - OF 0471EQUIPOSMATERIALES Y MANO DE OBRA | F8: PERÚ | G8: NORTE | H8: LA LIBERTAD | I8: OTROS | J8: Venta directa | K8: 8650 | O8: 0 | P8: 0
A9: 2014 | B9: 41646 | C9: Enero | D9: CORPORACION AGROLATINA S.A.C. | E9: - SERVICIO DE INSTALACION DE 8 SENSORES DE TEMPERA | F9: PERÚ | G9: SUR | H9: ICA | I9: OTROS | J9: Venta directa | K9: 9120 | O9: 0 | P9: 0
A10: 2014 | B10: 41648 | C10: Enero | D10: RVR AGRO E.I.R.L. | E10: - OF 0109HELICE WINGFAN DE 1035 MM. 6-9 | F10: PERÚ | G10: SUR | H10: ICA | I10: OTROS | J10: Venta directa | K10: 748.93 | O10: 0 | P10: 0
A11: 2014 | B11: 41653 | C11: Enero | D11: I Q F DEL PERU SA | E11: - OF 0101JUEGO DE MANIJAS PARA PUERTA CORREDERAJ | F11: PERÚ | G11: SUR | H11: ICA | I11: OTROS | J11: Venta directa | K11: 810 | O11: 0 | P11: 0
A12: 2014 | B12: 41655 | C12: Enero | D12: DANPER TRUJILLO S.A.C. | E12: - OF 0108INSTALACION DE AIRE ACONDICIONADO EN PLA | F12: PERÚ | G12: NORTE | H12: LA LIBERTAD | I12: OTROS | J12: Venta directa | K12: 450 | O12: 0 | P12: 0
A13: 2014 | B13: 41656 | C13: Enero | D13: TAL S.A. | E13: - EQUIPOS DE REFRIGERACION, PANELES Y PUERTAS, INS | F13: PERÚ | G13: NORTE | H13: LA LIBERTAD | I13: PALTA | J13: Amoniaco | K13: 365000 | O13: 0 | P13: 0
... A610: 2017 | B610: 43098 | C610: Diciembre | D610: DANPER TRUJILLO S.A.C. | E610: MONTAJE DE TUNEL DE PALTA EN ZONA DE MADURACION | F610: PERÚ | G610: NORTE | H610: LA LIBERTAD | I610: OTROS | J610: Venta directa | K610: 1359.9 | O610: 0 | P610: 0
A611: 2018 | B611: 43101 | C611: Enero | D611: PASSION FRESH S.A.C | F611: PERÚ | G611: CENTRO | H611: CHIMBOTE | I611: UVA | J611: Freón | K611: 24447.23 | O611: 0 | P611: 0
A612: 2018 | B612: 43110 | C612: Enero | D612: CAMPOSOL S.A. | F612: PERÚ | G612: NORTE | H612: LA LIBERTAD | I612: ARANDANOS | J612: Amoniaco | K612: 1366897.5 | O612: 0 | P612: 0
A613: 2018 | B613: 43112 | C613: Enero | D613: ECO - ACUICOLA SOCIEDAD ANONIMA CERRADA | F613: PERÚ | G613: NORTE | H613: PIURA | I613: COMEDOR | J613: Otros | K613: 54590.94 | O613: 0 | P613: 0
A614: 2018 | B614: 43118 | C614: Enero | D614: SUN FRUITS EXPORTS S.A. | F614: PERÚ | G614: SUR | H614: ICA | I614: FRUTAS VARIAS | J614: Amoniaco | K614: 5349.2 | O614: 0 | P614: 0
A615: 2018 | B615: 43125 | C615: Enero | D615: T & T FRUITS S.A. | F615: PERÚ | G615: CENTRO | H615: HUARAL | I615: CITRICOS | J615: Freón | K615: 70966.95 | O615: 0 | P615: 0
A616: 2018 | B616: 43138 | C616: Febrero | D616: AGROPIURA S.A.C. | F616: PERÚ | G616: NORTE | H616: PIURA | I616: UVA | J616: Freón | K616: 400754.81 | O616: 0 | P616: 0
A617: 2018 | B617: 43139 | C617: Febrero | D617: INVERSIONES AGRICOLAS OLMOS S.A.C. | F617: PERÚ | G617: NORTE | H617: LAMBAYEQUE | I617: PALTA | J617: Freón | K617: 7462.03 | O617: 0 | P617: 0
A618: 2018 | B618: 43139 | C618: Febrero | D618: AGRICOLA SANTA AZUL S.A.C | F618: PERÚ | G618: CENTRO | H618: LIMA | I618: ARANDANOS | J618: Freón | K618: 415527.5 | O618: 0 | P618: 0
A619: 2018 | B619: 43141 | C619: Febrero | D619: TAL S.A. | F619: PERÚ | G619: NORTE | H619: LA LIBERTAD | I619: PALTA | J619: Amoniaco | K619: 245000.02 | O619: 0 | P619: 0
A620: 2018 | B620: 43143 | C620: Febrero | D620: TAL S.A. | F620: PERÚ | G620: NORTE | H620: LA LIBERTAD | I620: PALTA | J620: Amoniaco | K620: 106000 | O620: 0 | P620: 0
A621: 2018 | B621: 43143 | C621: Febrero | D621: AGROINDUSTRIAS AIB S.A | F621: PERÚ | G621: SUR | H621: ICA | I621: ESPARRAGOS | J621: Freón | K621: 151558.52 | O621: 0 | P621: 0
A622: 2018 | B622: 43147 | C622: Febrero | D622: SUN FRUITS EXPORTS S.A. | F622: PERÚ | G622: SUR | H622: ICA | I622: PALTA | J622: Amoniaco | K622: 53611.91 | O622: 0 | P622: 0
... A663: 2018 | B663: 43269 | C663: Junio | D663: AGROINVERSIONES VALLE Y PAMPA PERU SOCIEDAD ANONIMA | F663: PERÚ | G663: SUR | H663: ICA | I663: ARANDANOS | J663: Freón | K663: 59302.84 | O663: 0 | P663: 0
A664: 2018 | B664: 43270 | C664: Junio | D664: SOCIEDAD AGRICOLA RAPEL S.A.C. | E664: VENTA DE RACKS PARA CAMARAS | F664: PERÚ | G664: NORTE | H664: PIURA | I664: UVA | J664: Otros | K664: 20442 | O664: 0 | P664: 0
A665: 2018 | B665: 43274 | C665: Junio | D665: AGROINDUSTRIAS AIB S.A | F665: PERÚ | G665: SUR | H665: ICA | I665: ESPARRAGOS | J665: Freón | K665: 1280 | O665: 0 | P665: 0
A666: 2018 | B666: 43277 | C666: Junio | D666: HORTIFRUT-TAL S.A.C. | F666: PERÚ | G666: NORTE | H666: LA LIBERTAD | I666: FRUTAS VARIAS | J666: Amoniaco | K666: 23000 | O666: 0 | P666: 0
A667: 2018 | B667: 43284 | C667: Julio | D667: SOCIEDAD AGRICOLA DROKASA S.A. | F667: PERÚ | G667: SUR | H667: ICA | I667: COMEDOR | J667: Freón | K667: 1780.87 | O667: 0 | P667: 0
A668: 2018 | B668: 43286 | C668: Julio | D668: MANUELITA FYH S.A.C. | F668: PERÚ | G668: SUR | H668: ICA | I668: UVA | J668: Freón | K668: 2420 | O668: 0 | P668: 0
A669: 2018 | B669: 43289 | C669: Julio | D669: TAL S.A. | F669: PERÚ | G669: NORTE | H669: LA LIBERTAD | I669: FRUTAS VARIAS | J669: Freón | K669: 2790 | O669: 0 | P669: 0
A670: 2018 | B670: 43293 | C670: Julio | D670: SOCIEDAD AGRICOLA RAPEL S.A.C. | E670: VENTA DE RACKS PARA CAMARAS | F670: PERÚ | G670: NORTE | H670: PIURA | I670: UVA | J670: Otros | K670: 10221.4 | O670: 0 | P670: 0
A671: 2018 | B671: 43293 | C671: Julio | D671: AGRICOLA SAN JOSE S.A. | F671: PERÚ | G671: NORTE | H671: PIURA | I671: OTROS | J671: Otros | K671: 12884.07 | O671: 0 | P671: 0
A672: 2018 | B672: 43305 | C672: Julio | D672: RANSA COMERCIAL S A | F672: PERÚ | G672: CENTRO | H672: LIMA | I672: ARANDANOS | J672: Amoniaco | K672: 84560.77 | O672: 0 | P672: 0
A673: 2018 | B673: 43305 | C673: Julio | D673: AGRICOLA ANDREA S.A.C. | F673: PERÚ | G673: SUR | H673: ICA | I673: FRUTAS VARIAS | J673: Amoniaco | K673: 39268.93 | O673: 0 | P673: 0
A674: 2018 | B674: 43305 | C674: Julio | D674: AGRICOLA ANDREA S.A.C. | F674: PERÚ | G674: SUR | H674: ICA | I674: OTROS | J674: Venta directa | K674: 7000 | O674: 0 | P674: 0
A675: 2018 | B675: 43306 | C675: Julio | D675: MANUELITA FYH S.A.C. | F675: PERÚ | G675: SUR | H675: ICA | I675: UVA | J675: Freón | K675: 5280 | O675: 0 | P675: 0
A676: 2018 | B676: 43306 | C676: Julio | D676: MANUELITA FYH S.A.C. | F676: PERÚ | G676: SUR | H676: ICA | I676: OTROS | J676: Venta directa | K676: 504 | O676: 0 | P676: 0
A677: 2018 | B677: 43307 | C677: Julio | D677: TAL S.A. | F677: PERÚ | G677: NORTE | H677: LA LIBERTAD | I677: OTROS | J677: Venta directa | K677: 1330 | O677: 0 | P677: 0
A678: 2018 | B678: 43309 | C678: Julio | D678: VIRU S.A. | F678: PERÚ | G678: NORTE | H678: LA LIBERTAD | I678: ESPARRAGOS | J678: Freón | K678: 4100 | O678: 0 | P678: 0
A679: 2018 | B679: 43312 | C679: Julio | D679: SOCIEDAD AGRICOLA DROKASA S.A. | F679: PERÚ | G679: SUR | H679: ICA | I679: UVA | J679: Freón | K679: 76367.63 | O679: 0 | P679: 0
A680: 2018 | B680: 43312 | C680: Julio | D680: AGROCASAGRANDE S.A.C. | F680: PERÚ | G680: NORTE | H680: LA LIBERTAD | I680: UVA | J680: Amoniaco | K680: 14264.58 | O680: 0 | P680: 0
A681: 2018 | B681: 43315 | C681: Agosto | D681: SC PACKING S.A.C. | F681: PERÚ | G681: SUR | H681: AREQUIPA | I681: UVA | J681: Freón | K681: 4900 | O681: 0 | P681: 0
A682: 2018 | B682: 43315 | C682: Agosto | D682: BLUEBERRIES PERU S.A.C. | F682: PERÚ | G682: NORTE | H682: LA LIBERTAD | I682: OTROS | J682: Venta directa | K682: 1120 | O682: 0 | P682: 0
... A771: 2019 | B771: 43529 | C771: Marzo | D771: CAMPOSOL S.A. | F771: PERÚ | G771: NORTE | H771: LA LIBERTAD | I771: OTROS | J771: Venta directa | K771: 5700 | O771: 0 | P771: 0
A772: 2019 | B772: 43530 | C772: Marzo | D772: PROCESADORA CAMPO VERDE S.A.C. | E772: AMPLIACIÓN DE PACKING | F772: PERÚ | G772: CENTRO | H772: HUARAL | I772: PALTA | J772: Freón | K772: 133979.59 | O772: 0 | P772: 0
A773: 2019 | B773: 43530 | C773: Marzo | D773: DANPER TRUJILLO S.A.C. | F773: PERÚ | G773: NORTE | H773: LA LIBERTAD | I773: ARANDANOS | J773: Amoniaco | K773: 1274940.2 | O773: 0 | P773: 0
A774: 2019 | B774: 43531 | C774: Marzo | D774: TAL S.A. | F774: PERÚ | G774: NORTE | H774: LA LIBERTAD | I774: OTROS | J774: Venta directa | K774: 1350 | O774: 0 | P774: 0
A775: 2019 | B775: 43531 | C775: Marzo | D775: AGRO PARACAS S.A. | F775: PERÚ | G775: SUR | H775: ICA | I775: OTROS | J775: Venta directa | K775: 4999 | O775: 0 | P775: 0
A776: 2019 | B776: 43532 | C776: Marzo | D776: VIRU S.A. | F776: PERÚ | G776: NORTE | H776: LA LIBERTAD | I776: PALTA | J776: Amoniaco | K776: 27000 | O776: 0 | P776: 0
A777: 2019 | B777: 43533 | C777: Marzo | D777: CONSORCIO CARSOL - JRM S.A.C. | F777: PERÚ | G777: NORTE | H777: PIURA | I777: ARANDANOS | J777: Freón | K777: 1050000 | O777: 0 | P777: 0
A778: 2019 | B778: 43536 | C778: Marzo | D778: VIRU S.A. | F778: PERÚ | G778: NORTE | H778: LA LIBERTAD | I778: OTROS | J778: Venta directa | K778: 1050 | O778: 0 | P778: 0
A779: 2019 | B779: 43536 | C779: Marzo | D779: CAMPOSOL S.A. | F779: PERÚ | G779: NORTE | H779: LA LIBERTAD | I779: OTROS | J779: Venta directa | K779: 6507.35 | O779: 0 | P779: 0
A780: 2019 | B780: 43542 | C780: Marzo | D780: CONSORCIO AGRICOLA MOQUEGUA S.A.C. | F780: PERÚ | G780: SUR | H780: MOQUEGUA | I780: ARANDANOS | J780: Freón | K780: 350000 | O780: 0 | P780: 0
A781: 2019 | B781: 43544 | C781: Marzo | D781: INVERSIONES AGRICOLAS OLMOS S.A.C. | F781: PERÚ | G781: NORTE | H781: LAMBAYEQUE | I781: OTROS | J781: Venta directa | K781: 2445.52 | O781: 0 | P781: 0
A782: 2019 | B782: 43545 | C782: Marzo | D782: CONSORCIO CARSOL - JRM S.A.C. | F782: PERÚ | G782: NORTE | H782: PIURA | I782: OTROS | J782: Venta directa | K782: 5908.75 | O782: 0 | P782: 0
A783: 2019 | B783: 43549 | C783: Marzo | D783: VIRU S.A. | F783: PERÚ | G783: NORTE | H783: LA LIBERTAD | I783: FRUTAS VARIAS | J783: Amoniaco | K783: 150000 | O783: 0 | P783: 0
A784: 2019 | B784: 43549 | C784: Marzo | D784: VIRU S.A. | F784: PERÚ | G784: NORTE | H784: LA LIBERTAD | I784: FRUTAS VARIAS | J784: CO2 | K784: 40000 | O784: 0 | P784: 0
... A786: 2019 | B786: 43550 | C786: Marzo | D786: CORPORACION FRUTICOLA DE CHINCHA S.A.C. | F786: PERÚ | G786: SUR | H786: ICA | I786: OTROS | J786: Venta directa | K786: 1056.58 | O786: 0 | P786: 0
A787: 2019 | B787: 43552 | C787: Marzo | D787: COMPLEJO AGROINDUSTRIAL BETA S.A. | E787: TÚNEL IQF | F787: PERÚ | G787: NORTE | H787: LAMBAYEQUE | I787: ESPARRAGOS | J787: Amoniaco | K787: 341509.44 | O787: 0 | P787: 0
A788: 2019 | B788: 43558 | C788: Abril | D788: CORPORACION FRUTICOLA DE CHINCHA S.A.C. | F788: PERÚ | G788: SUR | H788: ICA | I788: FRUTAS VARIAS | J788: Amoniaco | K788: 26770.73 | O788: 0 | P788: 0
A789: 2019 | B789: 43559 | C789: Abril | D789: RVR AGRO E.I.R.L. | F789: PERÚ | G789: SUR | H789: ICA | I789: UVA | J789: Freón | K789: 465061.29 | O789: 0 | P789: 0
A790: 2019 | B790: 43563 | C790: Abril | D790: VIRU S.A. | F790: PERÚ | G790: NORTE | H790: LA LIBERTAD | I790: ARANDANOS | J790: Venta e instalación | K790: 17085.31 | O790: 0 | P790: 0
A791: 2019 | B791: 43563 | C791: Abril | D791: VIRU S.A. | F791: PERÚ | G791: NORTE | H791: LA LIBERTAD | I791: OTROS | J791: Venta directa | K791: 10656.47 | O791: 0 | P791: 0
A792: 2019 | B792: 43563 | C792: Abril | D792: SUN FRUITS EXPORTS S.A. | F792: PERÚ | G792: SUR | H792: ICA | I792: OTROS | J792: Venta directa | K792: 2686.67 | O792: 0 | P792: 0
A793: 2019 | B793: 43563 | C793: Abril | D793: ICATOM S.A | F793: PERÚ | G793: SUR | H793: ICA | I793: OTROS | J793: Venta directa | K793: 500 | O793: 0 | P793: 0
A794: 2019 | B794: 43563 | C794: Abril | D794: AGROINDUSTRIAS HUARAL SOCIEDAD ANONIMA CERRADA | F794: PERÚ | G794: CENTRO | H794: HUARAL | I794: FRUTAS VARIAS | J794: Freón | K794: 91663.03 | O794: 0 | P794: 0
A795: 2019 | B795: 43565 | C795: Abril | D795: AGROVISION PERU S.A.C. | F795: PERÚ | G795: NORTE | H795: LAMBAYEQUE | I795: ARANDANOS | J795: Amoniaco | K795: 48993.59 | O795: 0 | P795: 0
A796: 2019 | B796: 43566 | C796: Abril | D796: VIRU S.A. | F796: PERÚ | G796: NORTE | H796: LA LIBERTAD | I796: FRUTAS VARIAS | J796: Venta e instalación | K796: 5985 | O796: 0 | P796: 0
A797: 2019 | B797: 43570 | C797: Abril | D797: ARA EXPORT S.A.C. | F797: PERÚ | G797: NORTE | H797: ANCASH | I797: FRUTAS VARIAS | J797: Freón | K797: 384214.27 | O797: 0 | P797: 0
A798: 2019 | B798: 43571 | C798: Abril | D798: DISTRIBUCIONES Y SERVICIOS ROMA S.A.C. | F798: PERÚ | G798: SUR | H798: ICA | I798: OTROS | J798: Venta directa | K798: 445 | O798: 0 | P798: 0
A799: 2019 | B799: 43572 | C799: Abril | D799: HORTIFRUT-TAL S.A.C. | F799: PERÚ | G799: NORTE | H799: LA LIBERTAD | I799: ESPARRAGOS | J799: Freón | K799: 276648.87 | O799: 0 | P799: 0
... A803: 2019 | B803: 43587 | C803: Mayo | D803: AGROINPER FOODS S.A.C. | F803: PERÚ | G803: CENTRO | H803: HUARAL | I803: OTROS | J803: Venta directa | K803: 10742.91 | O803: 0 | P803: 0
A804: 2019 | B804: 43588 | C804: Mayo | D804: CONSORCIO CARSOL - JRM S.A.C. | E804: NORTE | F804: PERÚ | G804: NORTE | H804: PIURA | I804: ARANDANOS | J804: Freón | K804: 14132 | O804: 0 | P804: 0
A805: 2019 | B805: 43592 | C805: Mayo | D805: VIRU S.A. | F805: PERÚ | G805: NORTE | H805: LA LIBERTAD | I805: OTROS | J805: Venta directa | K805: 1650 | O805: 0 | P805: 0
A806: 2019 | B806: 43592 | C806: Mayo | D806: VIRU S.A. | F806: PERÚ | G806: NORTE | H806: LA LIBERTAD | I806: OTROS | J806: Venta directa | K806: 805.3 | O806: 0 | P806: 0
A807: 2019 | B807: 43592 | C807: Mayo | D807: VIRU S.A. | F807: PERÚ | G807: NORTE | H807: LA LIBERTAD | I807: PALTA | J807: Amoniaco | K807: 23500 | O807: 0 | P807: 0
A808: 2019 | B808: 43594 | C808: Mayo | D808: VIRU S.A. | F808: PERÚ | G808: NORTE | H808: LA LIBERTAD | I808: PALTA | J808: Amoniaco | K808: 23835.71 | O808: 0 | P808: 0
A809: 2019 | B809: 43600 | C809: Mayo | D809: HORTIFRUT-TAL S.A.C. | F809: PERÚ | G809: NORTE | H809: LA LIBERTAD | I809: ARANDANOS | J809: Freón | K809: 570158.32 | O809: 0 | P809: 0
A810: 2019 | B810: 43600 | C810: Mayo | D810: CONSORCIO CARSOL - JRM S.A.C. | F810: PERÚ | G810: NORTE | H810: PIURA | I810: ARANDANOS | J810: Freón | K810: 172980.99 | O810: 0 | P810: 0
A811: 2019 | B811: 43600 | C811: Mayo | D811: AGROINDUSTRIAS AIB S.A | F811: PERÚ | G811: NORTE | H811: LAMBAYEQUE | I811: OTROS | J811: Venta directa | K811: 4729.32 | O811: 0 | P811: 0
A812: 2019 | B812: 43600 | C812: Mayo | D812: AGRO PARACAS S.A. | F812: PERÚ | G812: SUR | H812: ICA | I812: FRUTAS VARIAS | J812: Otros | K812: 55000 | O812: 0 | P812: 0
A813: 2019 | B813: 43601 | C813: Mayo | D813: CONSORCIO AGRICOLA MOQUEGUA S.A.C. | F813: PERÚ | G813: SUR | H813: MOQUEGUA | I813: OTROS | J813: Venta directa | K813: 2439.42 | O813: 0 | P813: 0
A814: 2019 | B814: 43601 | C814: Mayo | D814: CONSORCIO AGRICOLA MOQUEGUA S.A.C. | F814: PERÚ | G814: SUR | H814: MOQUEGUA | I814: OTROS | J814: Venta directa | K814: 230 | O814: 0 | P814: 0
A815: 2019 | B815: 43605 | C815: Mayo | D815: CAMPOSOL S.A. | F815: PERÚ | G815: NORTE | H815: LA LIBERTAD | I815: OTROS | J815: Venta directa | K815: 6837.5 | O815: 0 | P815: 0
A816: 2019 | B816: 43606 | C816: Mayo | D816: VIRU S.A. | F816: PERÚ | G816: NORTE | H816: LA LIBERTAD | I816: OTROS | J816: Venta directa | K816: 327.7 | O816: 0 | P816: 0
... A860: 2019 | B860: 43721 | C860: Setiembre | D860: AGROINDUSTRIAS AIB S.A | F860: PERÚ | G860: NORTE | H860: LAMBAYEQUE | I860: OTROS | J860: Venta e instalación | K860: 6436.2 | O860: 0 | P860: 0
A861: 2019 | B861: 43725 | C861: Setiembre | D861: PROCESADORA CAMPO VERDE S.A.C. | E861: AMPLIACIÓN DE PACKING | F861: PERÚ | G861: CENTRO | H861: HUARAL | I861: PALTA | J861: Freón | K861: 133979.57 | O861: 0 | P861: 0
A862: 2019 | B862: 43732 | C862: Setiembre | D862: VIRU S.A. | F862: PERÚ | G862: NORTE | H862: LA LIBERTAD | I862: OTROS | J862: Venta e instalación | K862: 9800 | O862: 0 | P862: 0
A863: 2019 | B863: 43733 | C863: Setiembre | D863: SAVAR AGENTES DE ADUANA S.A. | F863: PERÚ | G863: SUR | H863: ICA | I863: OTROS | J863: Venta directa | K863: 1338.85 | O863: 0 | P863: 0
A864: 2019 | B864: 43733 | C864: Setiembre | D864: BLUEBERRIES PERU S.A.C. | F864: PERÚ | G864: NORTE | H864: LA LIBERTAD | I864: OTROS | J864: Venta directa | K864: 3268 | O864: 0 | P864: 0
A865: 2019 | B865: 43739 | C865: Octubre | D865: HORTIFRUT-TAL S.A.C. | F865: PERÚ | G865: NORTE | H865: LA LIBERTAD | I865: OTROS | J865: Venta e instalación | K865: 5470 | O865: 0 | P865: 0
A866: 2019 | B866: 43745 | C866: Octubre | D866: AGROCASAGRANDE S.A.C. | F866: PERÚ | G866: NORTE | H866: LA LIBERTAD | I866: UVA | J866: Venta e instalación | K866: 3227.67 | O866: 0 | P866: 0
A867: 2019 | B867: 43747 | C867: Octubre | D867: COMPLEJO AGROINDUSTRIAL BETA S.A. | F867: PERÚ | G867: NORTE | H867: LAMBAYEQUE | I867: OTROS | J867: Venta e instalación | K867: 4900 | O867: 0 | P867: 0
A868: 2019 | B868: 43747 | C868: Octubre | D868: AGROVISION PERU S.A.C. | F868: PERÚ | G868: NORTE | H868: LAMBAYEQUE | I868: ARANDANOS | J868: Venta e instalación | K868: 1280 | O868: 0 | P868: 0
A869: 2019 | B869: 43747 | C869: Octubre | D869: AGRICOLA PAMPA BAJA S.A.C. | F869: PERÚ | G869: SUR | H869: AREQUIPA | I869: OTROS | J869: Venta e instalación | K869: 4507.69 | O869: 0 | P869: 0
A870: 2019 | B870: 43747 | C870: Octubre | D870: AGRICOLA PAMPA BAJA S.A.C. | F870: PERÚ | G870: SUR | H870: AREQUIPA | I870: OTROS | J870: Venta e instalación | K870: 181 | O870: 0 | P870: 0
A871: 2019 | B871: 43767 | C871: Octubre | D871: HORTIFRUT-TAL S.A.C. | F871: PERÚ | G871: NORTE | H871: LA LIBERTAD | I871: OTROS | J871: Venta e instalación | K871: 165 | O871: 0 | P871: 0
...

Sheet OO.CC Y EEMM
A1: CODIGO PROYECTO | B1: Fecha | C1: Cliente | D1: venta total | E1: MARGEN DEL PROYECTO % | F1: VENTA DE OO.CC | G1: COSTO DE OO.CC | H1: %oocc | I1: VENTA DE EE.MM | J1: COSTO DE EE.MM | K1: %EEMM | L1: mg frío | M1: MARGEN FRIO AJUSTADO %
A2: PRY 2026-0000030 | B2: 46169 | C2: AGROBERRIES PERU S.A.C. | D2: 9500000 | E2: 0.13783493 | F2: 1610698 | G2: 1417414.3 | H2: 0.12 | I2: 2164509.8 | J2: 1928876.6 | K2: 0.10886214 | L2: 880514.93 | M2: 0.15380732
A3: PRY 2026-0000004 | B3: 46044 | C3: PROCESADORA TORRE BLANCA S.A.C | D3: 718498.3 | E3: 0.19456891 | F3: 99839.601 | G3: 89855.641 | H3: 0.1 | I3: 16663.672 | J3: 14830.668 | K3: 0.11 | L3: 127980.47 | M3: 0.21259389
A4: PRY 2025-0000058 | B4: 45881 | C4: IMBAREX S.A. | D4: 853450 | E4: 0.16949982 | F4: 0 | G4: 0 | H4: 0.1 | I4: 108374.26 | J4: 96453.091 | K4: 0.11 | L4: 132738.45 | M4: 0.17815431
A5: PRY 2025-0000042 | B5: 45838 | C5: EL PARQUE ALAYA PACKING S.A.C. | D5: 1490360.7 | E5: 0.17062136 | F5: 338909.16 | G5: 305018.24 | H5: 0.1 | I5: 384615.14 | J5: 342307.47 | K5: 0.11 | L5: 178088.79 | M5: 0.2322383
A6: PRY 2025-0000023 | B6: 45747 | C6: DANPER TRUJILLO S.A.C. | D6: 4440814 | E6: 0.15065946 | F6: 616879.8 | G6: 555191.82 | H6: 0.1 | I6: 1042789.2 | J6: 928082.41 | K6: 0.11 | L6: 492655.84 | M6: 0.17714137
A7: PRY 2025-0000006 | B7: 45705 | C7: AGROVISION PERU S.A.C. | D7: 815120.48 | E7: 0.14022488 | F7: 109347.88 | G7: 98413.092 | H7: 0.1 | I7: 18900 | J7: 16821 | K7: 0.11 | L7: 101286.38 | M7: 0.14746022
A8: PRY 2024-0000066 | B8: 45594 | C8: FAMILY FARMS PERÚ S.R.L. | D8: 1185464.3 | E8: 0.14071425 | F8: 176880 | G8: 159192 | H8: 0.1 | I8: 50528.8 | J8: 44970.632 | K8: 0.11 | L8: 143565.56 | M8: 0.14985098
A9: PRY 2024-0000027 | B9: 45415 | C9: AQU ANQA S.A.C. | D9: 670271.45 | E9: 0.13870204 | F9: 85639.18 | G9: 77075.262 | H9: 0.1 | I9: 122511.31 | J9: 109035.07 | K9: 0.11 | L9: 70927.858 | M9: 0.15348332
A10: PRY 2024-0000025 | B10: 45411 | C10: AGROVISION PERU S.A.C. | D10: 658743.34 | E10: 0.15300745 | F10: 64219.03 | G10: 57797.127 | H10: 0.1 | I10: 2370 | J10: 2109.3 | K10: 0.11 | L10: 94110.034 | M10: 0.15892823
A11: PRY 2024-0000010 | B11: 45345 | C11: QALI FRUITS S.A.C. | D11: 503000 | E11: 0.15393513 | F11: 103831.66 | G11: 93448.494 | H11: 0.1 | I11: 138791.32 | J11: 123524.27 | K11: 0.11 | L11: 51779.159 | M11: 0.19886225
A12: PRY 2024-0000003 | B12: 45299 | C12: AGROINDUSTRIAL ESTANISLAO DEL CHIMU S.A.C. | D12: 1136822.7 | E12: 0.18679355 | F12: 185668.63 | G12: 167101.77 | H12: 0.1 | I12: 110415.71 | J12: 98269.982 | K12: 0.11 | L12: 181638.56 | M12: 0.21604648
A13: PRY 2023-0000018 | B13: 45027 | C13: AGROFUTURA COMPANY S.A.C. | D13: 1283046.1 | E13: 0.18116751 | F13: 146606.24 | G13: 131945.62 | H13: 0.1 | I13: 44784.94 | J13: 39858.597 | K13: 0.11 | L13: 212859.29 | M13: 0.19498771
... A20: PRY 2021-0000003 | B20: 44208 | C20: CONSORCIO CARSOL - JRM S.A.C. | D20: 984777.26 | E20: 0.13948419 | F20: 142011.98 | G20: 127810.78 | H20: 0.1 | I20: 114196.07 | J20: 101634.5 | K20: 0.11 | L20: 110598.09 | M20: 0.15180177

Sheet 1. Ventas Anuales
A1: TABLA 1 – VENTAS MENSUALES + ACUMULADO POR AÑO (2021-2026)
A3: Año | B3: Ene | C3: Feb | D3: Mar | E3: Abr | F3: May | G3: Jun | H3: Jul | I3: Ago | J3: Sep | K3: Oct | L3: Nov | M3: Dic | N3: TOTAL
A4: 2021 | B4: 1810393 | C4: 1089231.8 | D4: 1116870.3 | E4: 2068493.4 | F4: 2505141.4 | G4: 3589383.9 | H4: 1917227.9 | I4: 1140241 | J4: 1276014.6 | K4: 33998.4 | L4: 1148205.3 | M4: 2615340.2 | N4: =SUM(B4:M4) -> 20310541
A5: Acum. | B5: =B4 -> 1810393 | C5: =B5+C4 -> 2899624.8 | D5: =C5+D4 -> 4016495.1 | E5: =D5+E4 -> 6084988.5 | F5: =E5+F4 -> 8590129.9 | G5: =F5+G4 -> 12179514 | H5: =G5+H4 -> 14096742 | I5: =H5+I4 -> 15236983 | J5: =I5+J4 -> 16512997 | ... M5: =L5+M4 -> 20310541 | N5: =M5 -> 20310541
A7: 2022 | B7: 229756.7 | C7: 3871835.6 | D7: 3602116.1 | E7: 6230558.3 | F7: 5222934.9 | G7: 1427789.9 | H7: 3476461.5 | I7: 1870213.4 | J7: 1212618.8 | K7: 142299.66 | L7: 1305489.6 | M7: 4607690.2 | N7: =SUM(B7:M7) -> 33199765
A8: Acum. | B8: =B7 -> 229756.7 | C8: =B8+C7 -> 4101592.3 | D8: =C8+D7 -> 7703708.4 | E8: =D8+E7 -> 13934267 | F8: =E8+F7 -> 19157202 | G8: =F8+G7 -> 20584991 | H8: =G8+H7 -> 24061453 | I8: =H8+I7 -> 25931666 | J8: =I8+J7 -> 27144285 | ... M8: =L8+M7 -> 33199765 | N8: =M8 -> 33199765
A10: 2023 | B10: 673094.91 | C10: 516516.52 | D10: 2410566.1 | E10: 1729388.8 | F10: 2771062.7 | G10: 993087.41 | H10: 1503733.1 | I10: 1039787.9 | J10: 27777.771 | K10: 594477.09 | L10: 1413141.5 | M10: 1616740.9 | N10: =SUM(B10:M10) -> 15289375
A11: Acum. | B11: =B10 -> 673094.91 | C11: =B11+C10 -> 1189611.4 | D11: =C11+D10 -> 3600177.6 | E11: =D11+E10 -> 5329566.4 | F11: =E11+F10 -> 8100629.1 | G11: =F11+G10 -> 9093716.5 | H11: =G11+H10 -> 10597450 | I11: =H11+I10 -> 11637238 | J11: =I11+J10 -> 11665015 | ... M11: =L11+M10 -> 15289375 | N11: =M11 -> 15289375
A13: 2024 | B13: 77019.72 | C13: 1168612.2 | D13: 3590756.6 | E13: 1626868.8 | F13: 3115787.7 | G13: 1156829.5 | H13: 1562515.9 | I13: 578585.72 | J13: 334648.88 | K13: 1672197.8 | L13: 470764.38 | M13: 96562.07 | N13: =SUM(B13:M13) -> 15451149
A14: Acum. | B14: =B13 -> 77019.72 | C14: =B14+C13 -> 1245632 | D14: =C14+D13 -> 4836388.6 | E14: =D14+E13 -> 6463257.4 | F14: =E14+F13 -> 9579045.1 | G14: =F14+G13 -> 10735875 | H14: =G14+H13 -> 12298390 | I14: =H14+I13 -> 12876976 | J14: =I14+J13 -> 13211625 | ... M14: =L14+M13 -> 15451149 | N14: =M14 -> 15451149
A16: 2025 | B16: 197251.4 | C16: 1096220.8 | D16: 6615418.1 | E16: 4607683.4 | F16: 2423434.7 | G16: 4274625.6 | H16: 888259.06 | I16: 5353130.5 | J16: 4071839.8 | K16: 1992459.2 | L16: 2432241 | M16: 1003760.8 | N16: =SUM(B16:M16) -> 34956324
A17: Acum. | B17: =B16 -> 197251.4 | C17: =B17+C16 -> 1293472.2 | D17: =C17+D16 -> 7908890.3 | E17: =D17+E16 -> 12516574 | F17: =E17+F16 -> 14940008 | G17: =F17+G16 -> 19214634 | H17: =G17+H16 -> 20102893 | I17: =H17+I16 -> 25456024 | J17: =I17+J16 -> 29527863 | ... M17: =L17+M16 -> 34956324 | N17: =M17 -> 34956324
A19: 2026 | B19: 4362015.8 | C19: 3578569.9 | D19: 481538.55 | E19: 4267062.1 | F19: 13044891 | G19: 2526579.3 | H19: 0 | I19: 0 | J19: 0 | K19: 0 | L19: 0 | M19: 0 | N19: =SUM(B19:M19) -> 28260657
A20: Acum. | B20: =B19 -> 4362015.8 | C20: =B20+C19 -> 7940585.7 | D20: =C20+D19 -> 8422124.2 | E20: =D20+E19 -> 12689186 | F20: =E20+F19 -> 25734078 | G20: =F20+G19 -> 28260657 | H20: =G20+H19 -> 28260657 | I20: =H20+I19 -> 28260657 | J20: =I20+J19 -> 28260657 | ... M20: =L20+M19 -> 28260657 | N20: =M20 -> 28260657
A22: TOTAL | B22: =B4+B7+B10+B13+B16+B19 -> 7349531.5 | C22: =C4+C7+C10+C13+C16+C19 -> 11320987 | D22: =D4+D7+D10+D13+D16+D19 -> 17817266 | E22: =E4+E7+E10+E13+E16+E19 -> 20530055 | F22: =F4+F7+F10+F13+F16+F19 -> 29083253 | G22: =G4+G7+G10+G13+G16+G19 -> 13968296 | H22: =H4+H7+H10+H13+H16+H19 -> 9348197.5 | I22: =I4+I7+I10+I13+I16+I19 -> 9981958.5 | ... M22: =M4+M7+M10+M13+M16+M19 -> 9940094.3 | N22: =SUM(B22:M22) -> 1.4746781e+08
A25: TABLA 2 – MARGEN PONDERADO MENSUAL (2021-2026)
A27: Año | B27: Ene | C27: Feb | D27: Mar | E27: Abr | F27: May | G27: Jun | H27: Jul | I27: Ago | J27: Sep | K27: Oct | L27: Nov | M27: Dic | N27: Final Año
A28: 2021 | B28: =IFERROR(SUMIFS('Data Cruda'!$P$2:$P$1801,'Data Cruda'!$A$2:$A$1801,2021,'Data Cruda'!$C$2:$C$1801,"Enero")/SUMIFS('Data Cruda'!$K$2:$K$1801,'Data Cruda'!$A$2:$A$1801,2021,'Data Cruda'!$C$2:$C$1801,"Enero"),0) -> 0.15808456 | C28: =IFERROR(SUMIFS('Data Cruda'!$P$2:$P$1801,'Data Cruda'!$A$2:$A$1801,2021,'Data Cruda'!$C$2:$C$1801,"Febrero")/SUMIFS('Data Cruda'!$K$2:$K$1801,'Data Cruda'!$A$2:$A$1801,2021,'Data Cruda'!$C$2:$C$1801,"Febrero"),0) -> 0.11613769 | D28: =IFERROR(SUMIFS('Data Cruda'!$P$2:$P$1801,'Data Cruda'!$A$2:$A$1801,2021,'Data Cruda'!$C$2:$C$1801,"Marzo")/SUMIFS('Data Cruda'!$K$2:$K$1801,'Data Cruda'!$A$2:$A$1801,2021,'Data Cruda'!$C$2:$C$1801,"Marzo"),0) -> 0.17338259 | E28: =IFERROR(SUMIFS('Data Cruda'!$P$2:$P$1801,'Data Cruda'!$A$2:$A$1801,2021,'Data Cruda'!$C$2:$C$1801,"Abril")/SUMIFS('Data Cruda'!$K$2:$K$1801,'Data Cruda'!$A$2:$A$1801,2021,'Data Cruda'!$C$2:$C$1801,"Abril"),0) -> 0.0038448476 | F28: =IFERROR(SUMIFS('Data Cruda'!$P$2:$P$1801,'Data Cruda'!$A$2:$A$1801,2021,'Data Cruda'!$C$2:$C$1801,"Mayo")/SUMIFS('Data Cruda'!$K$2:$K$1801,'Data Cruda'!$A$2:$A$1801,2021,'Data Cruda'!$C$2:$C$1801,"Mayo"),0) -> 0.15012544 | G28: =IFERROR(SUMIFS('Data Cruda'!$P$2:$P$1801,'Data Cruda'!$A$2:$A$1801,2021,'Data Cruda'!$C$2:$C$1801,"Junio")/SUMIFS('Data Cruda'!$K$2:$K$1801,'Data Cruda'!$A$2:$A$1801,2021,'Data Cruda'!$C$2:$C$1801,"Junio"),0) -> 0.16229559 | H28: =IFERROR(SUMIFS('Data Cruda'!$P$2:$P$1801,'Data Cruda'!$A$2:$A$1801,2021,'Data Cruda'!$C$2:$C$1801,"Julio")/SUMIFS('Data Cruda'!$K$2:$K$1801,'Data Cruda'!$A$2:$A$1801,2021,'Data Cruda'!$C$2:$C$1801,"Julio"),0) -> 0.16966511 | I28: =IFERROR(SUMIFS('Data Cruda'!$P$2:$P$1801,'Data Cruda'!$A$2:$A$1801,2021,'Data Cruda'!$C$2:$C$1801,"Agosto")/SUMIFS('Data Cruda'!$K$2:$K$1801,'Data Cruda'!$A$2:$A$1801,2021,'Data Cruda'!$C$2:$C$1801,"Agosto"),0) -> 0 | J28: =IFERROR(SUMIFS('Data Cruda'!$P$2:$P$1801,'Data Cruda'!$A$2:$A$1801,2021,'Data Cruda'!$C$2:$C$1801,"Setiembre")/SUMIFS('Data Cruda'!$K$2:$K$1801,'Data Cruda'!$A$2:$A$1801,2021,'Data Cruda'!$C$2:$C$1801,"Setiembre"),0) -> 0.15984318 | K28: =IFERROR(SUMIFS('Data Cruda'!$P$2:$P$1801,'Data Cruda'!$A$2:$A$1801,2021,'Data Cruda'!$C$2:$C$1801,"Octubre")/SUMIFS('Data Cruda'!$K$2:$K$1801,'Data Cruda'!$A$2:$A$1801,2021,'Data Cruda'!$C$2:$C$1801,"Octubre"),0) -> 0.15817888 | L28: =IFERROR(SUMIFS('Data Cruda'!$P$2:$P$1801,'Data Cruda'!$A$2:$A$1801,2021,'Data Cruda'!$C$2:$C$1801,"Noviembre")/SUMIFS('Data Cruda'!$K$2:$K$1801,'Data Cruda'!$A$2:$A$1801,2021,'Data Cruda'!$C$2:$C$1801,"Noviembre"),0) -> 0.187156 | M28: =IFERROR(SUMIFS('Data Cruda'!$P$2:$P$1801,'Data Cruda'!$A$2:$A$1801,2021,'Data Cruda'!$C$2:$C$1801,"Diciembre")/SUMIFS('Data Cruda'!$K$2:$K$1801,'Data Cruda'!$A$2:$A$1801,2021,'Data Cruda'!$C$2:$C$1801,"Diciembre"),0) -> 0.155128 | N28: =IFERROR(SUMIFS('Data Cruda'!$P$2:$P$1801,'Data Cruda'!$A$2:$A$1801,2021)/SUMIFS('Data Cruda'!$K$2:$K$1801,'Data Cruda'!$A$2:$A$1801,2021),0) -> 0.13432209
A29: Acum. | B29: =IFERROR(SUMPRODUCT(('Data Cruda'!$A$2:$A$1801=2021)*ISNUMBER(MATCH('Data Cruda'!$C$2:$C$1801,{"Enero"},0))*'Data Cruda'!$P$2:$P$1801)/SUMPRODUCT(('Data Cruda'!$A$2:$A$1801=2021)*ISNUMBER(MATCH('Data Cruda'!$C$2:$C$1801,{"Enero"},0))*'Data Cruda'!$K$2:$K$1801),0) -> 0.15808456 | C29: =IFERROR(SUMPRODUCT(('Data Cruda'!$A$2:$A$1801=2021)*ISNUMBER(MATCH('Data Cruda'!$C$2:$C$1801,{"Enero","Febrero"},0))*'Data Cruda'!$P$2:$P$1801)/SUMPRODUCT(('Data Cruda'!$A$2:$A$1801=2021)*ISNUMBER(MATCH('Data Cruda'!$C$2:$C$1801,{"Enero","Febrero"},0))*'Data Cruda'!$K$2:$K$1801),0) -> 0.1423274 | D29: =IFERROR(SUMPRODUCT(('Data Cruda'!$A$2:$A$1801=2021)*ISNUMBER(MATCH('Data Cruda'!$C$2:$C$1801,{"Enero","Febrero","Marzo"},0))*'Data Cruda'!$P$2:$P$1801)/SUMPRODUCT(('Data Cruda'!$A$2:$A$1801=2021)*ISNUMBER(MATCH('Data Cruda'!$C$2:$C$1801,{"Enero","Febrero","Marzo"},0))*'Data Cruda'!$K$2:$K$1801),0) -> 0.15096294 | E29: =IFERROR(SUMPRODUCT(('Data Cruda'!$A$2:$A$1801=2021)*ISNUMBER(MATCH('Data Cruda'!$C$2:$C$1801,{"Enero","Febrero","Marzo","Abril"},0))*'Data Cruda'!$P$2:$P$1801)/SUMPRODUCT(('Data Cruda'!$A$2:$A$1801=2021)*ISNUMBER(MATCH('Data Cruda'!$C$2:$C$1801,{"Enero","Febrero","Marzo","Abril"},0))*'Data Cruda'!$K$2:$K$1801),0) -> 0.10095252 | F29: =IFERROR(SUMPRODUCT(('Data Cruda'!$A$2:$A$1801=2021)*ISNUMBER(MATCH('Data Cruda'!$C$2:$C$1801,{"Enero","Febrero","Marzo","Abril","Mayo"},0))*'Data Cruda'!$P$2:$P$1801)/SUMPRODUCT(('Data Cruda'!$A$2:$A$1801=2021)*ISNUMBER(MATCH('Data Cruda'!$C$2:$C$1801,{"Enero","Febrero","Marzo","Abril","Mayo"},0))*'Data Cruda'!$K$2:$K$1801),0) -> 0.11529283 | G29: =IFERROR(SUMPRODUCT(('Data Cruda'!$A$2:$A$1801=2021)*ISNUMBER(MATCH('Data Cruda'!$C$2:$C$1801,{"Enero","Febrero","Marzo","Abril","Mayo","Junio"},0))*'Data Cruda'!$P$2:$P$1801)/SUMPRODUCT(('Data Cruda'!$A$2:$A$1801=2021)*ISNUMBER(MATCH('Data Cruda'!$C$2:$C$1801,{"Enero","Febrero","Marzo","Abril","Mayo","Junio"},0))*'Data Cruda'!$K$2:$K$1801),0) -> 0.12914486 | H29: =IFERROR(SUMPRODUCT(('Data Cruda'!$A$2:$A$1801=2021)*ISNUMBER(MATCH('Data Cruda'!$C$2:$C$1801,{"Enero","Febrero","Marzo","Abril","Mayo","Junio","Julio"},0))*'Data Cruda'!$P$2:$P$1801)/SUMPRODUCT(('Data Cruda'!$A$2:$A$1801=2021)*ISNUMBER(MATCH('Data Cruda'!$C$2:$C$1801,{"Enero","Febrero","Marzo","Abril","Mayo","Junio","Julio"},0))*'Data Cruda'!$K$2:$K$1801),0) -> 0.13465582 | I29: =IFERROR(SUMPRODUCT(('Data Cruda'!$A$2:$A$1801=2021)*ISNUMBER(MATCH('Data Cruda'!$C$2:$C$1801,{"Enero","Febrero","Marzo","Abril","Mayo","Junio","Julio","Agosto"},0))*'Data Cruda'!$P$2:$P$1801)/SUMPRODUCT(('Data Cruda'!$A$2:$A$1801=2021)*ISNUMBER(MATCH('Data Cruda'!$C$2:$C$1801,{"Enero","Febrero","Marzo","Abril","Mayo","Junio","Julio","Agosto"},0))*'Data Cruda'!$K$2:$K$1801),0) -> 0.12457901 | J29: =IFERROR(SUMPRODUCT(('Data Cruda'!$A$2:$A$1801=2021)*ISNUMBER(MATCH('Data Cruda'!$C$2:$C$1801,{"Enero","Febrero","Marzo","Abril","Mayo","Junio","Julio","Agosto","Setiembre"},0))*'Data Cruda'!$P$2:$P$1801)/SUMPRODUCT(('Data Cruda'!$A$2:$A$1801=2021)*ISNUMBER(MATCH('Data Cruda'!$C$2:$C$1801,{"Enero","Febrero","Marzo","Abril","Mayo","Junio","Julio","Agosto","Setiembre"},0))*'Data Cruda'!$K$2:$K$1801),0) -> 0.12730399 | K29: =IFERROR(SUMPRODUCT(('Data Cruda'!$A$2:$A$1801=2021)*ISNUMBER(MATCH('Data Cruda'!$C$2:$C$1801,{"Enero","Febrero","Marzo","Abril","Mayo","Junio","Julio","Agosto","Setiembre","Octubre"},0))*'Data Cruda'!$P$2:$P$1801)/SUMPRODUCT(('Data Cruda'!$A$2:$A$1801=2021)*ISNUMBER(MATCH('Data Cruda'!$C$2:$C$1801,{"Enero","Febrero","Marzo","Abril","Mayo","Junio","Julio","Agosto","Setiembre","Octubre"},0))*'Data Cruda'!$K$2:$K$1801),0) -> 0.12736743 | L29: =IFERROR(SUMPRODUCT(('Data Cruda'!$A$2:$A$1801=2021)*ISNUMBER(MATCH('Data Cruda'!$C$2:$C$1801,{"Enero","Febrero","Marzo","Abril","Mayo","Junio","Julio","Agosto","Setiembre","Octubre","Noviembre"},0))*'Data Cruda'!$P$2:$P$1801)/SUMPRODUCT(('Data Cruda'!$A$2:$A$1801=2021)*ISNUMBER(MATCH('Data Cruda'!$C$2:$C$1801,{"Enero","Febrero","Marzo","Abril","Mayo","Junio","Julio","Agosto","Setiembre","Octubre","Noviembre"},0))*'Data Cruda'!$K$2:$K$1801),0) -> 0.13124699 | M29: =IFERROR(SUMPRODUCT(('Data Cruda'!$A$2:$A$1801=2021)*ISNUMBER(MATCH('Data Cruda'!$C$2:$C$1801,{"Enero","Febrero","Marzo","Abril","Mayo","Junio","Julio","Agosto","Setiembre","Octubre","Noviembre","Diciembre"},0))*'Data Cruda'!$P$2:$P$1801)/SUMPRODUCT(('Data Cruda'!$A$2:$A$1801=2021)*ISNUMBER(MATCH('Data Cruda'!$C$2:$C$1801,{"Enero","Febrero","Marzo","Abril","Mayo","Junio","Julio","Agosto","Setiembre","Octubre","Noviembre","Diciembre"},0))*'Data Cruda'!$K$2:$K$1801),0) -> 0.13432209 | N29: =N28 -> 0.13432209
A31: 2022 | B31: =IFERROR(SUMIFS('Data Cruda'!$P$2:$P$1801,'Data Cruda'!$A$2:$A$1801,2022,'Data Cruda'!$C$2:$C$1801,"Enero")/SUMIFS('Data Cruda'!$K$2:$K$1801,'Data Cruda'!$A$2:$A$1801,2022,'Data Cruda'!$C$2:$C$1801,"Enero"),0) -> 0.14979527 | C31: =IFERROR(SUMIFS('Data Cruda'!$P$2:$P$1801,'Data Cruda'!$A$2:$A$1801,2022,'Data Cruda'!$C$2:$C$1801,"Febrero")/SUMIFS('Data Cruda'!$K$2:$K$1801,'Data Cruda'!$A$2:$A$1801,2022,'Data Cruda'!$C$2:$C$1801,"Febrero"),0) -> 0.13670559 | D31: =IFERROR(SUMIFS('Data Cruda'!$P$2:$P$1801,'Data Cruda'!$A$2:$A$1801,2022,'Data Cruda'!$C$2:$C$1801,"Marzo")/SUMIFS('Data Cruda'!$K$2:$K$1801,'Data Cruda'!$A$2:$A$1801,2022,'Data Cruda'!$C$2:$C$1801,"Marzo"),0) -> 0.16291328 | E31: =IFERROR(SUMIFS('Data Cruda'!$P$2:$P$1801,'Data Cruda'!$A$2:$A$1801,2022,'Data Cruda'!$C$2:$C$1801,"Abril")/SUMIFS('Data Cruda'!$K$2:$K$1801,'Data Cruda'!$A$2:$A$1801,2022,'Data Cruda'!$C$2:$C$1801,"Abril"),0) -> 0.053779133 | F31: =IFERROR(SUMIFS('Data Cruda'!$P$2:$P$1801,'Data Cruda'!$A$2:$A$1801,2022,'Data Cruda'!$C$2:$C$1801,"Mayo")/SUMIFS('Data Cruda'!$K$2:$K$1801,'Data Cruda'!$A$2:$A$1801,2022,'Data Cruda'!$C$2:$C$1801,"Mayo"),0) -> 0.17489223 | G31: =IFERROR(SUMIFS('Data Cruda'!$P$2:$P$1801,'Data Cruda'!$A$2:$A$1801,2022,'Data Cruda'!$C$2:$C$1801,"Junio")/SUMIFS('Data Cruda'!$K$2:$K$1801,'Data Cruda'!$A$2:$A$1801,2022,'Data Cruda'!$C$2:$C$1801,"Junio"),0) -> 0.16972186 | H31: =IFERROR(SUMIFS('Data Cruda'!$P$2:$P$1801,'Data Cruda'!$A$2:$A$1801,2022,'Data Cruda'!$C$2:$C$1801,"Julio")/SUMIFS('Data Cruda'!$K$2:$K$1801,'Data Cruda'!$A$2:$A$1801,2022,'Data Cruda'!$C$2:$C$1801,"Julio"),0) -> 0.16683669 | I31: =IFERROR(SUMIFS('Data Cruda'!$P$2:$P$1801,'Data Cruda'!$A$2:$A$1801,2022,'Data Cruda'!$C$2:$C$1801,"Agosto")/SUMIFS('Data Cruda'!$K$2:$K$1801,'Data Cruda'!$A$2:$A$1801,2022,'Data Cruda'!$C$2:$C$1801,"Agosto"),0) -> 0.14879388 | J31: =IFERROR(SUMIFS('Data Cruda'!$P$2:$P$1801,'Data Cruda'!$A$2:$A$1801,2022,'Data Cruda'!$C$2:$C$1801,"Setiembre")/SUMIFS('Data Cruda'!$K$2:$K$1801,'Data Cruda'!$A$2:$A$1801,2022,'Data Cruda'!$C$2:$C$1801,"Setiembre"),0) -> 0.24212895 | K31: =IFERROR(SUMIFS('Data Cruda'!$P$2:$P$1801,'Data Cruda'!$A$2:$A$1801,2022,'Data Cruda'!$C$2:$C$1801,"Octubre")/SUMIFS('Data Cruda'!$K$2:$K$1801,'Data Cruda'!$A$2:$A$1801,2022,'Data Cruda'!$C$2:$C$1801,"Octubre"),0) -> 0.15487694 | L31: =IFERROR(SUMIFS('Data Cruda'!$P$2:$P$1801,'Data Cruda'!$A$2:$A$1801,2022,'Data Cruda'!$C$2:$C$1801,"Noviembre")/SUMIFS('Data Cruda'!$K$2:$K$1801,'Data Cruda'!$A$2:$A$1801,2022,'Data Cruda'!$C$2:$C$1801,"Noviembre"),0) -> 0.15650922 | M31: =IFERROR(SUMIFS('Data Cruda'!$P$2:$P$1801,'Data Cruda'!$A$2:$A$1801,2022,'Data Cruda'!$C$2:$C$1801,"Diciembre")/SUMIFS('Data Cruda'!$K$2:$K$1801,'Data Cruda'!$A$2:$A$1801,2022,'Data Cruda'!$C$2:$C$1801,"Diciembre"),0) -> 0.14372703 | N31: =IFERROR(SUMIFS('Data Cruda'!$P$2:$P$1801,'Data Cruda'!$A$2:$A$1801,2022)/SUMIFS('Data Cruda'!$K$2:$K$1801,'Data Cruda'!$A$2:$A$1801,2022),0) -> 0.14102208
A32: Acum. | B32: =IFERROR(SUMPRODUCT(('Data Cruda'!$A$2:$A$1801=2022)*ISNUMBER(MATCH('Data Cruda'!$C$2:$C$1801,{"Enero"},0))*'Data Cruda'!$P$2:$P$1801)/SUMPRODUCT(('Data Cruda'!$A$2:$A$1801=2022)*ISNUMBER(MATCH('Data Cruda'!$C$2:$C$1801,{"Enero"},0))*'Data Cruda'!$K$2:$K$1801),0) -> 0.14979527 | C32: =IFERROR(SUMPRODUCT(('Data Cruda'!$A$2:$A$1801=2022)*ISNUMBER(MATCH('Data Cruda'!$C$2:$C$1801,{"Enero","Febrero"},0))*'Data Cruda'!$P$2:$P$1801)/SUMPRODUCT(('Data Cruda'!$A$2:$A$1801=2022)*ISNUMBER(MATCH('Data Cruda'!$C$2:$C$1801,{"Enero","Febrero"},0))*'Data Cruda'!$K$2:$K$1801),0) -> 0.13743883 | D32: =IFERROR(SUMPRODUCT(('Data Cruda'!$A$2:$A$1801=2022)*ISNUMBER(MATCH('Data Cruda'!$C$2:$C$1801,{"Enero","Febrero","Marzo"},0))*'Data Cruda'!$P$2:$P$1801)/SUMPRODUCT(('Data Cruda'!$A$2:$A$1801=2022)*ISNUMBER(MATCH('Data Cruda'!$C$2:$C$1801,{"Enero","Febrero","Marzo"},0))*'Data Cruda'!$K$2:$K$1801),0) -> 0.14935023 | E32: =IFERROR(SUMPRODUCT(('Data Cruda'!$A$2:$A$1801=2022)*ISNUMBER(MATCH('Data Cruda'!$C$2:$C$1801,{"Enero","Febrero","Marzo","Abril"},0))*'Data Cruda'!$P$2:$P$1801)/SUMPRODUCT(('Data Cruda'!$A$2:$A$1801=2022)*ISNUMBER(MATCH('Data Cruda'!$C$2:$C$1801,{"Enero","Febrero","Marzo","Abril"},0))*'Data Cruda'!$K$2:$K$1801),0) -> 0.10661663 | F32: =IFERROR(SUMPRODUCT(('Data Cruda'!$A$2:$A$1801=2022)*ISNUMBER(MATCH('Data Cruda'!$C$2:$C$1801,{"Enero","Febrero","Marzo","Abril","Mayo"},0))*'Data Cruda'!$P$2:$P$1801)/SUMPRODUCT(('Data Cruda'!$A$2:$A$1801=2022)*ISNUMBER(MATCH('Data Cruda'!$C$2:$C$1801,{"Enero","Febrero","Marzo","Abril","Mayo"},0))*'Data Cruda'!$K$2:$K$1801),0) -> 0.12523099 | G32: =IFERROR(SUMPRODUCT(('Data Cruda'!$A$2:$A$1801=2022)*ISNUMBER(MATCH('Data Cruda'!$C$2:$C$1801,{"Enero","Febrero","Marzo","Abril","Mayo","Junio"},0))*'Data Cruda'!$P$2:$P$1801)/SUMPRODUCT(('Data Cruda'!$A$2:$A$1801=2022)*ISNUMBER(MATCH('Data Cruda'!$C$2:$C$1801,{"Enero","Febrero","Marzo","Abril","Mayo","Junio"},0))*'Data Cruda'!$K$2:$K$1801),0) -> 0.12831691 | H32: =IFERROR(SUMPRODUCT(('Data Cruda'!$A$2:$A$1801=2022)*ISNUMBER(MATCH('Data Cruda'!$C$2:$C$1801,{"Enero","Febrero","Marzo","Abril","Mayo","Junio","Julio"},0))*'Data Cruda'!$P$2:$P$1801)/SUMPRODUCT(('Data Cruda'!$A$2:$A$1801=2022)*ISNUMBER(MATCH('Data Cruda'!$C$2:$C$1801,{"Enero","Febrero","Marzo","Abril","Mayo","Junio","Julio"},0))*'Data Cruda'!$K$2:$K$1801),0) -> 0.13388235 | I32: =IFERROR(SUMPRODUCT(('Data Cruda'!$A$2:$A$1801=2022)*ISNUMBER(MATCH('Data Cruda'!$C$2:$C$1801,{"Enero","Febrero","Marzo","Abril","Mayo","Junio","Julio","Agosto"},0))*'Data Cruda'!$P$2:$P$1801)/SUMPRODUCT(('Data Cruda'!$A$2:$A$1801=2022)*ISNUMBER(MATCH('Data Cruda'!$C$2:$C$1801,{"Enero","Febrero","Marzo","Abril","Mayo","Junio","Julio","Agosto"},0))*'Data Cruda'!$K$2:$K$1801),0) -> 0.13495778 | J32: =IFERROR(SUMPRODUCT(('Data Cruda'!$A$2:$A$1801=2022)*ISNUMBER(MATCH('Data Cruda'!$C$2:$C$1801,{"Enero","Febrero","Marzo","Abril","Mayo","Junio","Julio","Agosto","Setiembre"},0))*'Data Cruda'!$P$2:$P$1801)/SUMPRODUCT(('Data Cruda'!$A$2:$A$1801=2022)*ISNUMBER(MATCH('Data Cruda'!$C$2:$C$1801,{"Enero","Febrero","Marzo","Abril","Mayo","Junio","Julio","Agosto","Setiembre"},0))*'Data Cruda'!$K$2:$K$1801),0) -> 0.13974545 | K32: =IFERROR(SUMPRODUCT(('Data Cruda'!$A$2:$A$1801=2022)*ISNUMBER(MATCH('Data Cruda'!$C$2:$C$1801,{"Enero","Febrero","Marzo","Abril","Mayo","Junio","Julio","Agosto","Setiembre","Octubre"},0))*'Data Cruda'!$P$2:$P$1801)/SUMPRODUCT(('Data Cruda'!$A$2:$A$1801=2022)*ISNUMBER(MATCH('Data Cruda'!$C$2:$C$1801,{"Enero","Febrero","Marzo","Abril","Mayo","Junio","Julio","Agosto","Setiembre","Octubre"},0))*'Data Cruda'!$K$2:$K$1801),0) -> 0.13982436 | L32: =IFERROR(SUMPRODUCT(('Data Cruda'!$A$2:$A$1801=2022)*ISNUMBER(MATCH('Data Cruda'!$C$2:$C$1801,{"Enero","Febrero","Marzo","Abril","Mayo","Junio","Julio","Agosto","Setiembre","Octubre","Noviembre"},0))*'Data Cruda'!$P$2:$P$1801)/SUMPRODUCT(('Data Cruda'!$A$2:$A$1801=2022)*ISNUMBER(MATCH('Data Cruda'!$C$2:$C$1801,{"Enero","Febrero","Marzo","Abril","Mayo","Junio","Julio","Agosto","Setiembre","Octubre","Noviembre"},0))*'Data Cruda'!$K$2:$K$1801),0) -> 0.14058617 | M32: =IFERROR(SUMPRODUCT(('Data Cruda'!$A$2:$A$1801=2022)*ISNUMBER(MATCH('Data Cruda'!$C$2:$C$1801,{"Enero","Febrero","Marzo","Abril","Mayo","Junio","Julio","Agosto","Setiembre","Octubre","Noviembre","Diciembre"},0))*'Data Cruda'!$P$2:$P$1801)/SUMPRODUCT(('Data Cruda'!$A$2:$A$1801=2022)*ISNUMBER(MATCH('Data Cruda'!$C$2:$C$1801,{"Enero","Febrero","Marzo","Abril","Mayo","Junio","Julio","Agosto","Setiembre","Octubre","Noviembre","Diciembre"},0))*'Data Cruda'!$K$2:$K$1801),0) -> 0.14102208 | N32: =N31 -> 0.14102208
A34: 2023 | B34: =IFERROR(SUMIFS('Data Cruda'!$P$2:$P$1801,'Data Cruda'!$A$2:$A$1801,2023,'Data Cruda'!$C$2:$C$1801,"Enero")/SUMIFS('Data Cruda'!$K$2:$K$1801,'Data Cruda'!$A$2:$A$1801,2023,'Data Cruda'!$C$2:$C$1801,"Enero"),0) -> 0.17726918 | C34: =IFERROR(SUMIFS('Data Cruda'!$P$2:$P$1801,'Data Cruda'!$A$2:$A$1801,2023,'Data Cruda'!$C$2:$C$1801,"Febrero")/SUMIFS('Data Cruda'!$K$2:$K$1801,'Data Cruda'!$A$2:$A$1801,2023,'Data Cruda'!$C$2:$C$1801,"Febrero"),0) -> 0.17837702 | D34: =IFERROR(SUMIFS('Data Cruda'!$P$2:$P$1801,'Data Cruda'!$A$2:$A$1801,2023,'Data Cruda'!$C$2:$C$1801,"Marzo")/SUMIFS('Data Cruda'!$K$2:$K$1801,'Data Cruda'!$A$2:$A$1801,2023,'Data Cruda'!$C$2:$C$1801,"Marzo"),0) -> 0.14069184 | E34: =IFERROR(SUMIFS('Data Cruda'!$P$2:$P$1801,'Data Cruda'!$A$2:$A$1801,2023,'Data Cruda'!$C$2:$C$1801,"Abril")/SUMIFS('Data Cruda'!$K$2:$K$1801,'Data Cruda'!$A$2:$A$1801,2023,'Data Cruda'!$C$2:$C$1801,"Abril"),0) -> 0.19030853 | F34: =IFERROR(SUMIFS('Data Cruda'!$P$2:$P$1801,'Data Cruda'!$A$2:$A$1801,2023,'Data Cruda'!$C$2:$C$1801,"Mayo")/SUMIFS('Data Cruda'!$K$2:$K$1801,'Data Cruda'!$A$2:$A$1801,2023,'Data Cruda'!$C$2:$C$1801,"Mayo"),0) -> 0.19930511 | G34: =IFERROR(SUMIFS('Data Cruda'!$P$2:$P$1801,'Data Cruda'!$A$2:$A$1801,2023,'Data Cruda'!$C$2:$C$1801,"Junio")/SUMIFS('Data Cruda'!$K$2:$K$1801,'Data Cruda'!$A$2:$A$1801,2023,'Data Cruda'!$C$2:$C$1801,"Junio"),0) -> 0.16235663 | H34: =IFERROR(SUMIFS('Data Cruda'!$P$2:$P$1801,'Data Cruda'!$A$2:$A$1801,2023,'Data Cruda'!$C$2:$C$1801,"Julio")/SUMIFS('Data Cruda'!$K$2:$K$1801,'Data Cruda'!$A$2:$A$1801,2023,'Data Cruda'!$C$2:$C$1801,"Julio"),0) -> 0.17336865 | I34: =IFERROR(SUMIFS('Data Cruda'!$P$2:$P$1801,'Data Cruda'!$A$2:$A$1801,2023,'Data Cruda'!$C$2:$C$1801,"Agosto")/SUMIFS('Data Cruda'!$K$2:$K$1801,'Data Cruda'!$A$2:$A$1801,2023,'Data Cruda'!$C$2:$C$1801,"Agosto"),0) -> 0.18420635 | J34: =IFERROR(SUMIFS('Data Cruda'!$P$2:$P$1801,'Data Cruda'!$A$2:$A$1801,2023,'Data Cruda'!$C$2:$C$1801,"Setiembre")/SUMIFS('Data Cruda'!$K$2:$K$1801,'Data Cruda'!$A$2:$A$1801,2023,'Data Cruda'!$C$2:$C$1801,"Setiembre"),0) -> 0.10725931 | K34: =IFERROR(SUMIFS('Data Cruda'!$P$2:$P$1801,'Data Cruda'!$A$2:$A$1801,2023,'Data Cruda'!$C$2:$C$1801,"Octubre")/SUMIFS('Data Cruda'!$K$2:$K$1801,'Data Cruda'!$A$2:$A$1801,2023,'Data Cruda'!$C$2:$C$1801,"Octubre"),0) -> 0.15440088 | L34: =IFERROR(SUMIFS('Data Cruda'!$P$2:$P$1801,'Data Cruda'!$A$2:$A$1801,2023,'Data Cruda'!$C$2:$C$1801,"Noviembre")/SUMIFS('Data Cruda'!$K$2:$K$1801,'Data Cruda'!$A$2:$A$1801,2023,'Data Cruda'!$C$2:$C$1801,"Noviembre"),0) -> 0.1202607 | M34: =IFERROR(SUMIFS('Data Cruda'!$P$2:$P$1801,'Data Cruda'!$A$2:$A$1801,2023,'Data Cruda'!$C$2:$C$1801,"Diciembre")/SUMIFS('Data Cruda'!$K$2:$K$1801,'Data Cruda'!$A$2:$A$1801,2023,'Data Cruda'!$C$2:$C$1801,"Diciembre"),0) -> 0.18743318 | N34: =IFERROR(SUMIFS('Data Cruda'!$P$2:$P$1801,'Data Cruda'!$A$2:$A$1801,2023)/SUMIFS('Data Cruda'!$K$2:$K$1801,'Data Cruda'!$A$2:$A$1801,2023),0) -> 0.17091729
A35: Acum. | B35: =IFERROR(SUMPRODUCT(('Data Cruda'!$A$2:$A$1801=2023)*ISNUMBER(MATCH('Data Cruda'!$C$2:$C$1801,{"Enero"},0))*'Data Cruda'!$P$2:$P$1801)/SUMPRODUCT(('Data Cruda'!$A$2:$A$1801=2023)*ISNUMBER(MATCH('Data Cruda'!$C$2:$C$1801,{"Enero"},0))*'Data Cruda'!$K$2:$K$1801),0) -> 0.17726918 | C35: =IFERROR(SUMPRODUCT(('Data Cruda'!$A$2:$A$1801=2023)*ISNUMBER(MATCH('Data Cruda'!$C$2:$C$1801,{"Enero","Febrero"},0))*'Data Cruda'!$P$2:$P$1801)/SUMPRODUCT(('Data Cruda'!$A$2:$A$1801=2023)*ISNUMBER(MATCH('Data Cruda'!$C$2:$C$1801,{"Enero","Febrero"},0))*'Data Cruda'!$K$2:$K$1801),0) -> 0.17775019 | D35: =IFERROR(SUMPRODUCT(('Data Cruda'!$A$2:$A$1801=2023)*ISNUMBER(MATCH('Data Cruda'!$C$2:$C$1801,{"Enero","Febrero","Marzo"},0))*'Data Cruda'!$P$2:$P$1801)/SUMPRODUCT(('Data Cruda'!$A$2:$A$1801=2023)*ISNUMBER(MATCH('Data Cruda'!$C$2:$C$1801,{"Enero","Febrero","Marzo"},0))*'Data Cruda'!$K$2:$K$1801),0) -> 0.15293708 | E35: =IFERROR(SUMPRODUCT(('Data Cruda'!$A$2:$A$1801=2023)*ISNUMBER(MATCH('Data Cruda'!$C$2:$C$1801,{"Enero","Febrero","Marzo","Abril"},0))*'Data Cruda'!$P$2:$P$1801)/SUMPRODUCT(('Data Cruda'!$A$2:$A$1801=2023)*ISNUMBER(MATCH('Data Cruda'!$C$2:$C$1801,{"Enero","Febrero","Marzo","Abril"},0))*'Data Cruda'!$K$2:$K$1801),0) -> 0.16506373 | F35: =IFERROR(SUMPRODUCT(('Data Cruda'!$A$2:$A$1801=2023)*ISNUMBER(MATCH('Data Cruda'!$C$2:$C$1801,{"Enero","Febrero","Marzo","Abril","Mayo"},0))*'Data Cruda'!$P$2:$P$1801)/SUMPRODUCT(('Data Cruda'!$A$2:$A$1801=2023)*ISNUMBER(MATCH('Data Cruda'!$C$2:$C$1801,{"Enero","Febrero","Marzo","Abril","Mayo"},0))*'Data Cruda'!$K$2:$K$1801),0) -> 0.17677702 | G35: =IFERROR(SUMPRODUCT(('Data Cruda'!$A$2:$A$1801=2023)*ISNUMBER(MATCH('Data Cruda'!$C$2:$C$1801,{"Enero","Febrero","Marzo","Abril","Mayo","Junio"},0))*'Data Cruda'!$P$2:$P$1801)/SUMPRODUCT(('Data Cruda'!$A$2:$A$1801=2023)*ISNUMBER(MATCH('Data Cruda'!$C$2:$C$1801,{"Enero","Febrero","Marzo","Abril","Mayo","Junio"},0))*'Data Cruda'!$K$2:$K$1801),0) -> 0.17520222 | H35: =IFERROR(SUMPRODUCT(('Data Cruda'!$A$2:$A$1801=2023)*ISNUMBER(MATCH('Data Cruda'!$C$2:$C$1801,{"Enero","Febrero","Marzo","Abril","Mayo","Junio","Julio"},0))*'Data Cruda'!$P$2:$P$1801)/SUMPRODUCT(('Data Cruda'!$A$2:$A$1801=2023)*ISNUMBER(MATCH('Data Cruda'!$C$2:$C$1801,{"Enero","Febrero","Marzo","Abril","Mayo","Junio","Julio"},0))*'Data Cruda'!$K$2:$K$1801),0) -> 0.17494205 | I35: =IFERROR(SUMPRODUCT(('Data Cruda'!$A$2:$A$1801=2023)*ISNUMBER(MATCH('Data Cruda'!$C$2:$C$1801,{"Enero","Febrero","Marzo","Abril","Mayo","Junio","Julio","Agosto"},0))*'Data Cruda'!$P$2:$P$1801)/SUMPRODUCT(('Data Cruda'!$A$2:$A$1801=2023)*ISNUMBER(MATCH('Data Cruda'!$C$2:$C$1801,{"Enero","Febrero","Marzo","Abril","Mayo","Junio","Julio","Agosto"},0))*'Data Cruda'!$K$2:$K$1801),0) -> 0.17576981 | J35: =IFERROR(SUMPRODUCT(('Data Cruda'!$A$2:$A$1801=2023)*ISNUMBER(MATCH('Data Cruda'!$C$2:$C$1801,{"Enero","Febrero","Marzo","Abril","Mayo","Junio","Julio","Agosto","Setiembre"},0))*'Data Cruda'!$P$2:$P$1801)/SUMPRODUCT(('Data Cruda'!$A$2:$A$1801=2023)*ISNUMBER(MATCH('Data Cruda'!$C$2:$C$1801,{"Enero","Febrero","Marzo","Abril","Mayo","Junio","Julio","Agosto","Setiembre"},0))*'Data Cruda'!$K$2:$K$1801),0) -> 0.17560667 | K35: =IFERROR(SUMPRODUCT(('Data Cruda'!$A$2:$A$1801=2023)*ISNUMBER(MATCH('Data Cruda'!$C$2:$C$1801,{"Enero","Febrero","Marzo","Abril","Mayo","Junio","Julio","Agosto","Setiembre","Octubre"},0))*'Data Cruda'!$P$2:$P$1801)/SUMPRODUCT(('Data Cruda'!$A$2:$A$1801=2023)*ISNUMBER(MATCH('Data Cruda'!$C$2:$C$1801,{"Enero","Febrero","Marzo","Abril","Mayo","Junio","Julio","Agosto","Setiembre","Octubre"},0))*'Data Cruda'!$K$2:$K$1801),0) -> 0.17457838 | L35: =IFERROR(SUMPRODUCT(('Data Cruda'!$A$2:$A$1801=2023)*ISNUMBER(MATCH('Data Cruda'!$C$2:$C$1801,{"Enero","Febrero","Marzo","Abril","Mayo","Junio","Julio","Agosto","Setiembre","Octubre","Noviembre"},0))*'Data Cruda'!$P$2:$P$1801)/SUMPRODUCT(('Data Cruda'!$A$2:$A$1801=2023)*ISNUMBER(MATCH('Data Cruda'!$C$2:$C$1801,{"Enero","Febrero","Marzo","Abril","Mayo","Junio","Julio","Agosto","Setiembre","Octubre","Noviembre"},0))*'Data Cruda'!$K$2:$K$1801),0) -> 0.16896435 | M35: =IFERROR(SUMPRODUCT(('Data Cruda'!$A$2:$A$1801=2023)*ISNUMBER(MATCH('Data Cruda'!$C$2:$C$1801,{"Enero","Febrero","Marzo","Abril","Mayo","Junio","Julio","Agosto","Setiembre","Octubre","Noviembre","Diciembre"},0))*'Data Cruda'!$P$2:$P$1801)/SUMPRODUCT(('Data Cruda'!$A$2:$A$1801=2023)*ISNUMBER(MATCH('Data Cruda'!$C$2:$C$1801,{"Enero","Febrero","Marzo","Abril","Mayo","Junio","Julio","Agosto","Setiembre","Octubre","Noviembre","Diciembre"},0))*'Data Cruda'!$K$2:$K$1801),0) -> 0.17091729 | N35: =N34 -> 0.17091729
A37: 2024 | B37: =IFERROR(SUMIFS('Data Cruda'!$P$2:$P$1801,'Data Cruda'!$A$2:$A$1801,2024,'Data Cruda'!$C$2:$C$1801,"Enero")/SUMIFS('Data Cruda'!$K$2:$K$1801,'Data Cruda'!$A$2:$A$1801,2024,'Data Cruda'!$C$2:$C$1801,"Enero"),0) -> 0.16666737 | C37: =IFERROR(SUMIFS('Data Cruda'!$P$2:$P$1801,'Data Cruda'!$A$2:$A$1801,2024,'Data Cruda'!$C$2:$C$1801,"Febrero")/SUMIFS('Data Cruda'!$K$2:$K$1801,'Data Cruda'!$A$2:$A$1801,2024,'Data Cruda'!$C$2:$C$1801,"Febrero"),0) -> 0.16398718 | D37: =IFERROR(SUMIFS('Data Cruda'!$P$2:$P$1801,'Data Cruda'!$A$2:$A$1801,2024,'Data Cruda'!$C$2:$C$1801,"Marzo")/SUMIFS('Data Cruda'!$K$2:$K$1801,'Data Cruda'!$A$2:$A$1801,2024,'Data Cruda'!$C$2:$C$1801,"Marzo"),0) -> 0.14997408 | E37: =IFERROR(SUMIFS('Data Cruda'!$P$2:$P$1801,'Data Cruda'!$A$2:$A$1801,2024,'Data Cruda'!$C$2:$C$1801,"Abril")/SUMIFS('Data Cruda'!$K$2:$K$1801,'Data Cruda'!$A$2:$A$1801,2024,'Data Cruda'!$C$2:$C$1801,"Abril"),0) -> 0.14766614 | F37: =IFERROR(SUMIFS('Data Cruda'!$P$2:$P$1801,'Data Cruda'!$A$2:$A$1801,2024,'Data Cruda'!$C$2:$C$1801,"Mayo")/SUMIFS('Data Cruda'!$K$2:$K$1801,'Data Cruda'!$A$2:$A$1801,2024,'Data Cruda'!$C$2:$C$1801,"Mayo"),0) -> 0.16246946 | G37: =IFERROR(SUMIFS('Data Cruda'!$P$2:$P$1801,'Data Cruda'!$A$2:$A$1801,2024,'Data Cruda'!$C$2:$C$1801,"Junio")/SUMIFS('Data Cruda'!$K$2:$K$1801,'Data Cruda'!$A$2:$A$1801,2024,'Data Cruda'!$C$2:$C$1801,"Junio"),0) -> 0.18121366 | H37: =IFERROR(SUMIFS('Data Cruda'!$P$2:$P$1801,'Data Cruda'!$A$2:$A$1801,2024,'Data Cruda'!$C$2:$C$1801,"Julio")/SUMIFS('Data Cruda'!$K$2:$K$1801,'Data Cruda'!$A$2:$A$1801,2024,'Data Cruda'!$C$2:$C$1801,"Julio"),0) -> 0.1166396 | I37: =IFERROR(SUMIFS('Data Cruda'!$P$2:$P$1801,'Data Cruda'!$A$2:$A$1801,2024,'Data Cruda'!$C$2:$C$1801,"Agosto")/SUMIFS('Data Cruda'!$K$2:$K$1801,'Data Cruda'!$A$2:$A$1801,2024,'Data Cruda'!$C$2:$C$1801,"Agosto"),0) -> 0.14271307 | J37: =IFERROR(SUMIFS('Data Cruda'!$P$2:$P$1801,'Data Cruda'!$A$2:$A$1801,2024,'Data Cruda'!$C$2:$C$1801,"Setiembre")/SUMIFS('Data Cruda'!$K$2:$K$1801,'Data Cruda'!$A$2:$A$1801,2024,'Data Cruda'!$C$2:$C$1801,"Setiembre"),0) -> 0.15664275 | K37: =IFERROR(SUMIFS('Data Cruda'!$P$2:$P$1801,'Data Cruda'!$A$2:$A$1801,2024,'Data Cruda'!$C$2:$C$1801,"Octubre")/SUMIFS('Data Cruda'!$K$2:$K$1801,'Data Cruda'!$A$2:$A$1801,2024,'Data Cruda'!$C$2:$C$1801,"Octubre"),0) -> 0.14778752 | L37: =IFERROR(SUMIFS('Data Cruda'!$P$2:$P$1801,'Data Cruda'!$A$2:$A$1801,2024,'Data Cruda'!$C$2:$C$1801,"Noviembre")/SUMIFS('Data Cruda'!$K$2:$K$1801,'Data Cruda'!$A$2:$A$1801,2024,'Data Cruda'!$C$2:$C$1801,"Noviembre"),0) -> 0.18297841 | M37: =IFERROR(SUMIFS('Data Cruda'!$P$2:$P$1801,'Data Cruda'!$A$2:$A$1801,2024,'Data Cruda'!$C$2:$C$1801,"Diciembre")/SUMIFS('Data Cruda'!$K$2:$K$1801,'Data Cruda'!$A$2:$A$1801,2024,'Data Cruda'!$C$2:$C$1801,"Diciembre"),0) -> 0.14949483 | N37: =IFERROR(SUMIFS('Data Cruda'!$P$2:$P$1801,'Data Cruda'!$A$2:$A$1801,2024)/SUMIFS('Data Cruda'!$K$2:$K$1801,'Data Cruda'!$A$2:$A$1801,2024),0) -> 0.15300028
A38: Acum. | B38: =IFERROR(SUMPRODUCT(('Data Cruda'!$A$2:$A$1801=2024)*ISNUMBER(MATCH('Data Cruda'!$C$2:$C$1801,{"Enero"},0))*'Data Cruda'!$P$2:$P$1801)/SUMPRODUCT(('Data Cruda'!$A$2:$A$1801=2024)*ISNUMBER(MATCH('Data Cruda'!$C$2:$C$1801,{"Enero"},0))*'Data Cruda'!$K$2:$K$1801),0) -> 0.16666737 | C38: =IFERROR(SUMPRODUCT(('Data Cruda'!$A$2:$A$1801=2024)*ISNUMBER(MATCH('Data Cruda'!$C$2:$C$1801,{"Enero","Febrero"},0))*'Data Cruda'!$P$2:$P$1801)/SUMPRODUCT(('Data Cruda'!$A$2:$A$1801=2024)*ISNUMBER(MATCH('Data Cruda'!$C$2:$C$1801,{"Enero","Febrero"},0))*'Data Cruda'!$K$2:$K$1801),0) -> 0.1641529 | D38: =IFERROR(SUMPRODUCT(('Data Cruda'!$A$2:$A$1801=2024)*ISNUMBER(MATCH('Data Cruda'!$C$2:$C$1801,{"Enero","Febrero","Marzo"},0))*'Data Cruda'!$P$2:$P$1801)/SUMPRODUCT(('Data Cruda'!$A$2:$A$1801=2024)*ISNUMBER(MATCH('Data Cruda'!$C$2:$C$1801,{"Enero","Febrero","Marzo"},0))*'Data Cruda'!$K$2:$K$1801),0) -> 0.15362589 | E38: =IFERROR(SUMPRODUCT(('Data Cruda'!$A$2:$A$1801=2024)*ISNUMBER(MATCH('Data Cruda'!$C$2:$C$1801,{"Enero","Febrero","Marzo","Abril"},0))*'Data Cruda'!$P$2:$P$1801)/SUMPRODUCT(('Data Cruda'!$A$2:$A$1801=2024)*ISNUMBER(MATCH('Data Cruda'!$C$2:$C$1801,{"Enero","Febrero","Marzo","Abril"},0))*'Data Cruda'!$K$2:$K$1801),0) -> 0.15212576 | F38: =IFERROR(SUMPRODUCT(('Data Cruda'!$A$2:$A$1801=2024)*ISNUMBER(MATCH('Data Cruda'!$C$2:$C$1801,{"Enero","Febrero","Marzo","Abril","Mayo"},0))*'Data Cruda'!$P$2:$P$1801)/SUMPRODUCT(('Data Cruda'!$A$2:$A$1801=2024)*ISNUMBER(MATCH('Data Cruda'!$C$2:$C$1801,{"Enero","Febrero","Marzo","Abril","Mayo"},0))*'Data Cruda'!$K$2:$K$1801),0) -> 0.15549027 | G38: =IFERROR(SUMPRODUCT(('Data Cruda'!$A$2:$A$1801=2024)*ISNUMBER(MATCH('Data Cruda'!$C$2:$C$1801,{"Enero","Febrero","Marzo","Abril","Mayo","Junio"},0))*'Data Cruda'!$P$2:$P$1801)/SUMPRODUCT(('Data Cruda'!$A$2:$A$1801=2024)*ISNUMBER(MATCH('Data Cruda'!$C$2:$C$1801,{"Enero","Febrero","Marzo","Abril","Mayo","Junio"},0))*'Data Cruda'!$K$2:$K$1801),0) -> 0.15826206 | H38: =IFERROR(SUMPRODUCT(('Data Cruda'!$A$2:$A$1801=2024)*ISNUMBER(MATCH('Data Cruda'!$C$2:$C$1801,{"Enero","Febrero","Marzo","Abril","Mayo","Junio","Julio"},0))*'Data Cruda'!$P$2:$P$1801)/SUMPRODUCT(('Data Cruda'!$A$2:$A$1801=2024)*ISNUMBER(MATCH('Data Cruda'!$C$2:$C$1801,{"Enero","Febrero","Marzo","Abril","Mayo","Junio","Julio"},0))*'Data Cruda'!$K$2:$K$1801),0) -> 0.15297391 | I38: =IFERROR(SUMPRODUCT(('Data Cruda'!$A$2:$A$1801=2024)*ISNUMBER(MATCH('Data Cruda'!$C$2:$C$1801,{"Enero","Febrero","Marzo","Abril","Mayo","Junio","Julio","Agosto"},0))*'Data Cruda'!$P$2:$P$1801)/SUMPRODUCT(('Data Cruda'!$A$2:$A$1801=2024)*ISNUMBER(MATCH('Data Cruda'!$C$2:$C$1801,{"Enero","Febrero","Marzo","Abril","Mayo","Junio","Julio","Agosto"},0))*'Data Cruda'!$K$2:$K$1801),0) -> 0.15251287 | J38: =IFERROR(SUMPRODUCT(('Data Cruda'!$A$2:$A$1801=2024)*ISNUMBER(MATCH('Data Cruda'!$C$2:$C$1801,{"Enero","Febrero","Marzo","Abril","Mayo","Junio","Julio","Agosto","Setiembre"},0))*'Data Cruda'!$P$2:$P$1801)/SUMPRODUCT(('Data Cruda'!$A$2:$A$1801=2024)*ISNUMBER(MATCH('Data Cruda'!$C$2:$C$1801,{"Enero","Febrero","Marzo","Abril","Mayo","Junio","Julio","Agosto","Setiembre"},0))*'Data Cruda'!$K$2:$K$1801),0) -> 0.15261748 | K38: =IFERROR(SUMPRODUCT(('Data Cruda'!$A$2:$A$1801=2024)*ISNUMBER(MATCH('Data Cruda'!$C$2:$C$1801,{"Enero","Febrero","Marzo","Abril","Mayo","Junio","Julio","Agosto","Setiembre","Octubre"},0))*'Data Cruda'!$P$2:$P$1801)/SUMPRODUCT(('Data Cruda'!$A$2:$A$1801=2024)*ISNUMBER(MATCH('Data Cruda'!$C$2:$C$1801,{"Enero","Febrero","Marzo","Abril","Mayo","Junio","Julio","Agosto","Setiembre","Octubre"},0))*'Data Cruda'!$K$2:$K$1801),0) -> 0.15207483 | L38: =IFERROR(SUMPRODUCT(('Data Cruda'!$A$2:$A$1801=2024)*ISNUMBER(MATCH('Data Cruda'!$C$2:$C$1801,{"Enero","Febrero","Marzo","Abril","Mayo","Junio","Julio","Agosto","Setiembre","Octubre","Noviembre"},0))*'Data Cruda'!$P$2:$P$1801)/SUMPRODUCT(('Data Cruda'!$A$2:$A$1801=2024)*ISNUMBER(MATCH('Data Cruda'!$C$2:$C$1801,{"Enero","Febrero","Marzo","Abril","Mayo","Junio","Julio","Agosto","Setiembre","Octubre","Noviembre"},0))*'Data Cruda'!$K$2:$K$1801),0) -> 0.15302232 | M38: =IFERROR(SUMPRODUCT(('Data Cruda'!$A$2:$A$1801=2024)*ISNUMBER(MATCH('Data Cruda'!$C$2:$C$1801,{"Enero","Febrero","Marzo","Abril","Mayo","Junio","Julio","Agosto","Setiembre","Octubre","Noviembre","Diciembre"},0))*'Data Cruda'!$P$2:$P$1801)/SUMPRODUCT(('Data Cruda'!$A$2:$A$1801=2024)*ISNUMBER(MATCH('Data Cruda'!$C$2:$C$1801,{"Enero","Febrero","Marzo","Abril","Mayo","Junio","Julio","Agosto","Setiembre","Octubre","Noviembre","Diciembre"},0))*'Data Cruda'!$K$2:$K$1801),0) -> 0.15300028 | N38: =N37 -> 0.15300028
A40: 2025 | B40: =IFERROR(SUMIFS('Data Cruda'!$P$2:$P$1801,'Data Cruda'!$A$2:$A$1801,2025,'Data Cruda'!$C$2:$C$1801,"Enero")/SUMIFS('Data Cruda'!$K$2:$K$1801,'Data Cruda'!$A$2:$A$1801,2025,'Data Cruda'!$C$2:$C$1801,"Enero"),0) -> 0.15202929 | C40: =IFERROR(SUMIFS('Data Cruda'!$P$2:$P$1801,'Data Cruda'!$A$2:$A$1801,2025,'Data Cruda'!$C$2:$C$1801,"Febrero")/SUMIFS('Data Cruda'!$K$2:$K$1801,'Data Cruda'!$A$2:$A$1801,2025,'Data Cruda'!$C$2:$C$1801,"Febrero"),0) -> 0.15524631 | D40: =IFERROR(SUMIFS('Data Cruda'!$P$2:$P$1801,'Data Cruda'!$A$2:$A$1801,2025,'Data Cruda'!$C$2:$C$1801,"Marzo")/SUMIFS('Data Cruda'!$K$2:$K$1801,'Data Cruda'!$A$2:$A$1801,2025,'Data Cruda'!$C$2:$C$1801,"Marzo"),0) -> 0.15093029 | E40: =IFERROR(SUMIFS('Data Cruda'!$P$2:$P$1801,'Data Cruda'!$A$2:$A$1801,2025,'Data Cruda'!$C$2:$C$1801,"Abril")/SUMIFS('Data Cruda'!$K$2:$K$1801,'Data Cruda'!$A$2:$A$1801,2025,'Data Cruda'!$C$2:$C$1801,"Abril"),0) -> 0.17130529 | F40: =IFERROR(SUMIFS('Data Cruda'!$P$2:$P$1801,'Data Cruda'!$A$2:$A$1801,2025,'Data Cruda'!$C$2:$C$1801,"Mayo")/SUMIFS('Data Cruda'!$K$2:$K$1801,'Data Cruda'!$A$2:$A$1801,2025,'Data Cruda'!$C$2:$C$1801,"Mayo"),0) -> 0.16447295 | G40: =IFERROR(SUMIFS('Data Cruda'!$P$2:$P$1801,'Data Cruda'!$A$2:$A$1801,2025,'Data Cruda'!$C$2:$C$1801,"Junio")/SUMIFS('Data Cruda'!$K$2:$K$1801,'Data Cruda'!$A$2:$A$1801,2025,'Data Cruda'!$C$2:$C$1801,"Junio"),0) -> 0.14042711 | H40: =IFERROR(SUMIFS('Data Cruda'!$P$2:$P$1801,'Data Cruda'!$A$2:$A$1801,2025,'Data Cruda'!$C$2:$C$1801,"Julio")/SUMIFS('Data Cruda'!$K$2:$K$1801,'Data Cruda'!$A$2:$A$1801,2025,'Data Cruda'!$C$2:$C$1801,"Julio"),0) -> 0.14352754 | I40: =IFERROR(SUMIFS('Data Cruda'!$P$2:$P$1801,'Data Cruda'!$A$2:$A$1801,2025,'Data Cruda'!$C$2:$C$1801,"Agosto")/SUMIFS('Data Cruda'!$K$2:$K$1801,'Data Cruda'!$A$2:$A$1801,2025,'Data Cruda'!$C$2:$C$1801,"Agosto"),0) -> 0.17581193 | J40: =IFERROR(SUMIFS('Data Cruda'!$P$2:$P$1801,'Data Cruda'!$A$2:$A$1801,2025,'Data Cruda'!$C$2:$C$1801,"Setiembre")/SUMIFS('Data Cruda'!$K$2:$K$1801,'Data Cruda'!$A$2:$A$1801,2025,'Data Cruda'!$C$2:$C$1801,"Setiembre"),0) -> 0.16315694 | K40: =IFERROR(SUMIFS('Data Cruda'!$P$2:$P$1801,'Data Cruda'!$A$2:$A$1801,2025,'Data Cruda'!$C$2:$C$1801,"Octubre")/SUMIFS('Data Cruda'!$K$2:$K$1801,'Data Cruda'!$A$2:$A$1801,2025,'Data Cruda'!$C$2:$C$1801,"Octubre"),0) -> 0.1750591 | L40: =IFERROR(SUMIFS('Data Cruda'!$P$2:$P$1801,'Data Cruda'!$A$2:$A$1801,2025,'Data Cruda'!$C$2:$C$1801,"Noviembre")/SUMIFS('Data Cruda'!$K$2:$K$1801,'Data Cruda'!$A$2:$A$1801,2025,'Data Cruda'!$C$2:$C$1801,"Noviembre"),0) -> 0.17220737 | M40: =IFERROR(SUMIFS('Data Cruda'!$P$2:$P$1801,'Data Cruda'!$A$2:$A$1801,2025,'Data Cruda'!$C$2:$C$1801,"Diciembre")/SUMIFS('Data Cruda'!$K$2:$K$1801,'Data Cruda'!$A$2:$A$1801,2025,'Data Cruda'!$C$2:$C$1801,"Diciembre"),0) -> 0.14195359 | N40: =IFERROR(SUMIFS('Data Cruda'!$P$2:$P$1801,'Data Cruda'!$A$2:$A$1801,2025)/SUMIFS('Data Cruda'!$K$2:$K$1801,'Data Cruda'!$A$2:$A$1801,2025),0) -> 0.16103777
A41: Acum. | B41: =IFERROR(SUMPRODUCT(('Data Cruda'!$A$2:$A$1801=2025)*ISNUMBER(MATCH('Data Cruda'!$C$2:$C$1801,{"Enero"},0))*'Data Cruda'!$P$2:$P$1801)/SUMPRODUCT(('Data Cruda'!$A$2:$A$1801=2025)*ISNUMBER(MATCH('Data Cruda'!$C$2:$C$1801,{"Enero"},0))*'Data Cruda'!$K$2:$K$1801),0) -> 0.15202929 | C41: =IFERROR(SUMPRODUCT(('Data Cruda'!$A$2:$A$1801=2025)*ISNUMBER(MATCH('Data Cruda'!$C$2:$C$1801,{"Enero","Febrero"},0))*'Data Cruda'!$P$2:$P$1801)/SUMPRODUCT(('Data Cruda'!$A$2:$A$1801=2025)*ISNUMBER(MATCH('Data Cruda'!$C$2:$C$1801,{"Enero","Febrero"},0))*'Data Cruda'!$K$2:$K$1801),0) -> 0.15475572 | D41: =IFERROR(SUMPRODUCT(('Data Cruda'!$A$2:$A$1801=2025)*ISNUMBER(MATCH('Data Cruda'!$C$2:$C$1801,{"Enero","Febrero","Marzo"},0))*'Data Cruda'!$P$2:$P$1801)/SUMPRODUCT(('Data Cruda'!$A$2:$A$1801=2025)*ISNUMBER(MATCH('Data Cruda'!$C$2:$C$1801,{"Enero","Febrero","Marzo"},0))*'Data Cruda'!$K$2:$K$1801),0) -> 0.15155593 | E41: =IFERROR(SUMPRODUCT(('Data Cruda'!$A$2:$A$1801=2025)*ISNUMBER(MATCH('Data Cruda'!$C$2:$C$1801,{"Enero","Febrero","Marzo","Abril"},0))*'Data Cruda'!$P$2:$P$1801)/SUMPRODUCT(('Data Cruda'!$A$2:$A$1801=2025)*ISNUMBER(MATCH('Data Cruda'!$C$2:$C$1801,{"Enero","Febrero","Marzo","Abril"},0))*'Data Cruda'!$K$2:$K$1801),0) -> 0.15882619 | F41: =IFERROR(SUMPRODUCT(('Data Cruda'!$A$2:$A$1801=2025)*ISNUMBER(MATCH('Data Cruda'!$C$2:$C$1801,{"Enero","Febrero","Marzo","Abril","Mayo"},0))*'Data Cruda'!$P$2:$P$1801)/SUMPRODUCT(('Data Cruda'!$A$2:$A$1801=2025)*ISNUMBER(MATCH('Data Cruda'!$C$2:$C$1801,{"Enero","Febrero","Marzo","Abril","Mayo"},0))*'Data Cruda'!$K$2:$K$1801),0) -> 0.15968127 | G41: =IFERROR(SUMPRODUCT(('Data Cruda'!$A$2:$A$1801=2025)*ISNUMBER(MATCH('Data Cruda'!$C$2:$C$1801,{"Enero","Febrero","Marzo","Abril","Mayo","Junio"},0))*'Data Cruda'!$P$2:$P$1801)/SUMPRODUCT(('Data Cruda'!$A$2:$A$1801=2025)*ISNUMBER(MATCH('Data Cruda'!$C$2:$C$1801,{"Enero","Febrero","Marzo","Abril","Mayo","Junio"},0))*'Data Cruda'!$K$2:$K$1801),0) -> 0.15535511 | H41: =IFERROR(SUMPRODUCT(('Data Cruda'!$A$2:$A$1801=2025)*ISNUMBER(MATCH('Data Cruda'!$C$2:$C$1801,{"Enero","Febrero","Marzo","Abril","Mayo","Junio","Julio"},0))*'Data Cruda'!$P$2:$P$1801)/SUMPRODUCT(('Data Cruda'!$A$2:$A$1801=2025)*ISNUMBER(MATCH('Data Cruda'!$C$2:$C$1801,{"Enero","Febrero","Marzo","Abril","Mayo","Junio","Julio"},0))*'Data Cruda'!$K$2:$K$1801),0) -> 0.15482751 | I41: =IFERROR(SUMPRODUCT(('Data Cruda'!$A$2:$A$1801=2025)*ISNUMBER(MATCH('Data Cruda'!$C$2:$C$1801,{"Enero","Febrero","Marzo","Abril","Mayo","Junio","Julio","Agosto"},0))*'Data Cruda'!$P$2:$P$1801)/SUMPRODUCT(('Data Cruda'!$A$2:$A$1801=2025)*ISNUMBER(MATCH('Data Cruda'!$C$2:$C$1801,{"Enero","Febrero","Marzo","Abril","Mayo","Junio","Julio","Agosto"},0))*'Data Cruda'!$K$2:$K$1801),0) -> 0.15927347 | J41: =IFERROR(SUMPRODUCT(('Data Cruda'!$A$2:$A$1801=2025)*ISNUMBER(MATCH('Data Cruda'!$C$2:$C$1801,{"Enero","Febrero","Marzo","Abril","Mayo","Junio","Julio","Agosto","Setiembre"},0))*'Data Cruda'!$P$2:$P$1801)/SUMPRODUCT(('Data Cruda'!$A$2:$A$1801=2025)*ISNUMBER(MATCH('Data Cruda'!$C$2:$C$1801,{"Enero","Febrero","Marzo","Abril","Mayo","Junio","Julio","Agosto","Setiembre"},0))*'Data Cruda'!$K$2:$K$1801),0) -> 0.15981246 | K41: =IFERROR(SUMPRODUCT(('Data Cruda'!$A$2:$A$1801=2025)*ISNUMBER(MATCH('Data Cruda'!$C$2:$C$1801,{"Enero","Febrero","Marzo","Abril","Mayo","Junio","Julio","Agosto","Setiembre","Octubre"},0))*'Data Cruda'!$P$2:$P$1801)/SUMPRODUCT(('Data Cruda'!$A$2:$A$1801=2025)*ISNUMBER(MATCH('Data Cruda'!$C$2:$C$1801,{"Enero","Febrero","Marzo","Abril","Mayo","Junio","Julio","Agosto","Setiembre","Octubre"},0))*'Data Cruda'!$K$2:$K$1801),0) -> 0.16078207 | L41: =IFERROR(SUMPRODUCT(('Data Cruda'!$A$2:$A$1801=2025)*ISNUMBER(MATCH('Data Cruda'!$C$2:$C$1801,{"Enero","Febrero","Marzo","Abril","Mayo","Junio","Julio","Agosto","Setiembre","Octubre","Noviembre"},0))*'Data Cruda'!$P$2:$P$1801)/SUMPRODUCT(('Data Cruda'!$A$2:$A$1801=2025)*ISNUMBER(MATCH('Data Cruda'!$C$2:$C$1801,{"Enero","Febrero","Marzo","Abril","Mayo","Junio","Julio","Agosto","Setiembre","Octubre","Noviembre"},0))*'Data Cruda'!$K$2:$K$1801),0) -> 0.16160514 | M41: =IFERROR(SUMPRODUCT(('Data Cruda'!$A$2:$A$1801=2025)*ISNUMBER(MATCH('Data Cruda'!$C$2:$C$1801,{"Enero","Febrero","Marzo","Abril","Mayo","Junio","Julio","Agosto","Setiembre","Octubre","Noviembre","Diciembre"},0))*'Data Cruda'!$P$2:$P$1801)/SUMPRODUCT(('Data Cruda'!$A$2:$A$1801=2025)*ISNUMBER(MATCH('Data Cruda'!$C$2:$C$1801,{"Enero","Febrero","Marzo","Abril","Mayo","Junio","Julio","Agosto","Setiembre","Octubre","Noviembre","Diciembre"},0))*'Data Cruda'!$K$2:$K$1801),0) -> 0.16103777 | N41: =N40 -> 0.16103777
A43: 2026 | B43: =IFERROR(SUMIFS('Data Cruda'!$P$2:$P$1801,'Data Cruda'!$A$2:$A$1801,2026,'Data Cruda'!$C$2:$C$1801,"Enero")/SUMIFS('Data Cruda'!$K$2:$K$1801,'Data Cruda'!$A$2:$A$1801,2026,'Data Cruda'!$C$2:$C$1801,"Enero"),0) -> 0.15097763 | C43: =IFERROR(SUMIFS('Data Cruda'!$P$2:$P$1801,'Data Cruda'!$A$2:$A$1801,2026,'Data Cruda'!$C$2:$C$1801,"Febrero")/SUMIFS('Data Cruda'!$K$2:$K$1801,'Data Cruda'!$A$2:$A$1801,2026,'Data Cruda'!$C$2:$C$1801,"Febrero"),0) -> 0.16585125 | D43: =IFERROR(SUMIFS('Data Cruda'!$P$2:$P$1801,'Data Cruda'!$A$2:$A$1801,2026,'Data Cruda'!$C$2:$C$1801,"Marzo")/SUMIFS('Data Cruda'!$K$2:$K$1801,'Data Cruda'!$A$2:$A$1801,2026,'Data Cruda'!$C$2:$C$1801,"Marzo"),0) -> 0.18087268 | E43: =IFERROR(SUMIFS('Data Cruda'!$P$2:$P$1801,'Data Cruda'!$A$2:$A$1801,2026,'Data Cruda'!$C$2:$C$1801,"Abril")/SUMIFS('Data Cruda'!$K$2:$K$1801,'Data Cruda'!$A$2:$A$1801,2026,'Data Cruda'!$C$2:$C$1801,"Abril"),0) -> 0.18255141 | F43: =IFERROR(SUMIFS('Data Cruda'!$P$2:$P$1801,'Data Cruda'!$A$2:$A$1801,2026,'Data Cruda'!$C$2:$C$1801,"Mayo")/SUMIFS('Data Cruda'!$K$2:$K$1801,'Data Cruda'!$A$2:$A$1801,2026,'Data Cruda'!$C$2:$C$1801,"Mayo"),0) -> 0.14024809 | G43: =IFERROR(SUMIFS('Data Cruda'!$P$2:$P$1801,'Data Cruda'!$A$2:$A$1801,2026,'Data Cruda'!$C$2:$C$1801,"Junio")/SUMIFS('Data Cruda'!$K$2:$K$1801,'Data Cruda'!$A$2:$A$1801,2026,'Data Cruda'!$C$2:$C$1801,"Junio"),0) -> 0.15065386 | H43: =IFERROR(SUMIFS('Data Cruda'!$P$2:$P$1801,'Data Cruda'!$A$2:$A$1801,2026,'Data Cruda'!$C$2:$C$1801,"Julio")/SUMIFS('Data Cruda'!$K$2:$K$1801,'Data Cruda'!$A$2:$A$1801,2026,'Data Cruda'!$C$2:$C$1801,"Julio"),0) -> 0 | I43: =IFERROR(SUMIFS('Data Cruda'!$P$2:$P$1801,'Data Cruda'!$A$2:$A$1801,2026,'Data Cruda'!$C$2:$C$1801,"Agosto")/SUMIFS('Data Cruda'!$K$2:$K$1801,'Data Cruda'!$A$2:$A$1801,2026,'Data Cruda'!$C$2:$C$1801,"Agosto"),0) -> 0 | J43: =IFERROR(SUMIFS('Data Cruda'!$P$2:$P$1801,'Data Cruda'!$A$2:$A$1801,2026,'Data Cruda'!$C$2:$C$1801,"Setiembre")/SUMIFS('Data Cruda'!$K$2:$K$1801,'Data Cruda'!$A$2:$A$1801,2026,'Data Cruda'!$C$2:$C$1801,"Setiembre"),0) -> 0 | K43: =IFERROR(SUMIFS('Data Cruda'!$P$2:$P$1801,'Data Cruda'!$A$2:$A$1801,2026,'Data Cruda'!$C$2:$C$1801,"Octubre")/SUMIFS('Data Cruda'!$K$2:$K$1801,'Data Cruda'!$A$2:$A$1801,2026,'Data Cruda'!$C$2:$C$1801,"Octubre"),0) -> 0 | L43: =IFERROR(SUMIFS('Data Cruda'!$P$2:$P$1801,'Data Cruda'!$A$2:$A$1801,2026,'Data Cruda'!$C$2:$C$1801,"Noviembre")/SUMIFS('Data Cruda'!$K$2:$K$1801,'Data Cruda'!$A$2:$A$1801,2026,'Data Cruda'!$C$2:$C$1801,"Noviembre"),0) -> 0 | M43: =IFERROR(SUMIFS('Data Cruda'!$P$2:$P$1801,'Data Cruda'!$A$2:$A$1801,2026,'Data Cruda'!$C$2:$C$1801,"Diciembre")/SUMIFS('Data Cruda'!$K$2:$K$1801,'Data Cruda'!$A$2:$A$1801,2026,'Data Cruda'!$C$2:$C$1801,"Diciembre"),0) -> 0 | N43: =IFERROR(SUMIFS('Data Cruda'!$P$2:$P$1801,'Data Cruda'!$A$2:$A$1801,2026)/SUMIFS('Data Cruda'!$K$2:$K$1801,'Data Cruda'!$A$2:$A$1801,2026),0) -> 0.15315612
A44: Acum. | B44: =IFERROR(SUMPRODUCT(('Data Cruda'!$A$2:$A$1801=2026)*ISNUMBER(MATCH('Data Cruda'!$C$2:$C$1801,{"Enero"},0))*'Data Cruda'!$P$2:$P$1801)/SUMPRODUCT(('Data Cruda'!$A$2:$A$1801=2026)*ISNUMBER(MATCH('Data Cruda'!$C$2:$C$1801,{"Enero"},0))*'Data Cruda'!$K$2:$K$1801),0) -> 0.15097763 | C44: =IFERROR(SUMPRODUCT(('Data Cruda'!$A$2:$A$1801=2026)*ISNUMBER(MATCH('Data Cruda'!$C$2:$C$1801,{"Enero","Febrero"},0))*'Data Cruda'!$P$2:$P$1801)/SUMPRODUCT(('Data Cruda'!$A$2:$A$1801=2026)*ISNUMBER(MATCH('Data Cruda'!$C$2:$C$1801,{"Enero","Febrero"},0))*'Data Cruda'!$K$2:$K$1801),0) -> 0.1576807 | D44: =IFERROR(SUMPRODUCT(('Data Cruda'!$A$2:$A$1801=2026)*ISNUMBER(MATCH('Data Cruda'!$C$2:$C$1801,{"Enero","Febrero","Marzo"},0))*'Data Cruda'!$P$2:$P$1801)/SUMPRODUCT(('Data Cruda'!$A$2:$A$1801=2026)*ISNUMBER(MATCH('Data Cruda'!$C$2:$C$1801,{"Enero","Febrero","Marzo"},0))*'Data Cruda'!$K$2:$K$1801),0) -> 0.15900671 | E44: =IFERROR(SUMPRODUCT(('Data Cruda'!$A$2:$A$1801=2026)*ISNUMBER(MATCH('Data Cruda'!$C$2:$C$1801,{"Enero","Febrero","Marzo","Abril"},0))*'Data Cruda'!$P$2:$P$1801)/SUMPRODUCT(('Data Cruda'!$A$2:$A$1801=2026)*ISNUMBER(MATCH('Data Cruda'!$C$2:$C$1801,{"Enero","Febrero","Marzo","Abril"},0))*'Data Cruda'!$K$2:$K$1801),0) -> 0.16692422 | F44: =IFERROR(SUMPRODUCT(('Data Cruda'!$A$2:$A$1801=2026)*ISNUMBER(MATCH('Data Cruda'!$C$2:$C$1801,{"Enero","Febrero","Marzo","Abril","Mayo"},0))*'Data Cruda'!$P$2:$P$1801)/SUMPRODUCT(('Data Cruda'!$A$2:$A$1801=2026)*ISNUMBER(MATCH('Data Cruda'!$C$2:$C$1801,{"Enero","Febrero","Marzo","Abril","Mayo"},0))*'Data Cruda'!$K$2:$K$1801),0) -> 0.15340179 | G44: =IFERROR(SUMPRODUCT(('Data Cruda'!$A$2:$A$1801=2026)*ISNUMBER(MATCH('Data Cruda'!$C$2:$C$1801,{"Enero","Febrero","Marzo","Abril","Mayo","Junio"},0))*'Data Cruda'!$P$2:$P$1801)/SUMPRODUCT(('Data Cruda'!$A$2:$A$1801=2026)*ISNUMBER(MATCH('Data Cruda'!$C$2:$C$1801,{"Enero","Febrero","Marzo","Abril","Mayo","Junio"},0))*'Data Cruda'!$K$2:$K$1801),0) -> 0.15315612 | N44: =N43 -> 0.15315612

Sheet 2. Análisis Anual
A1: TABLA 1 – REFRIGERANTE: FREÓN VS OTROS
A3: Año | B3: Monto Freón | C3: % Freón | D3: Monto Otros | E3: % Otros | F3: Total Año
A4: 2021 | B4: 9717808.6 | C4: =B4/F4 -> 0.47846133 | D4: =F4-B4 -> 10592733 | E4: =D4/F4 -> 0.52153867 | F4: 20310541
A5: 2022 | B5: 11783033 | C5: =B5/F5 -> 0.35491316 | D5: =F5-B5 -> 21416731 | E5: =D5/F5 -> 0.64508684 | F5: 33199765
A6: 2023 | B6: 10023577 | C6: =B6/F6 -> 0.65559102 | D6: =F6-B6 -> 5265798.1 | E6: =D6/F6 -> 0.34440898 | F6: 15289375
A7: 2024 | B7: 6480103.8 | C7: =B7/F7 -> 0.41939299 | D7: =F7-B7 -> 8971045.5 | E7: =D7/F7 -> 0.58060701 | F7: 15451149
A8: 2025 | B8: 6662323.2 | C8: =B8/F8 -> 0.19058992 | D8: =F8-B8 -> 28294001 | E8: =D8/F8 -> 0.80941008 | F8: 34956324
A9: 2026 | B9: 4913328.2 | C9: =B9/F9 -> 0.17385753 | D9: =F9-B9 -> 23347329 | E9: =D9/F9 -> 0.82614247 | F9: 28260657
A10: TOTAL | B10: 49580174 | C10: 0.33621014 | D10: 97887637 | E10: 0.66378986 | F10: 1.4746781e+08
A13: TABLA 2 – MARGEN POR REFRIGERANTE (FREÓN / AMONIACO / OTROS)
A15: Año | B15: Freón Monto | C15: Freón Mg% | D15: Freón %Part | E15: Amon. Monto | F15: Amon. Mg% | G15: Amon. %Part | H15: Otros Monto | I15: Otros Mg% | J15: Otros %Part | K15: Total
A16: 2021 | B16: 9717808.6 | C16: =IFERROR(SUMIFS('Data Cruda'!$P$2:$P$1801,'Data Cruda'!$A$2:$A$1801,2021,'Data Cruda'!$J$2:$J$1801,"Freón")/SUMIFS('Data Cruda'!$K$2:$K$1801,'Data Cruda'!$A$2:$A$1801,2021,'Data Cruda'!$J$2:$J$1801,"Freón"),0) -> 0.13931059 | D16: 0.47846133 | E16: 9840110.5 | F16: =IFERROR(SUMIFS('Data Cruda'!$P$2:$P$1801,'Data Cruda'!$A$2:$A$1801,2021,'Data Cruda'!$J$2:$J$1801,"Amoniaco")/SUMIFS('Data Cruda'!$K$2:$K$1801,'Data Cruda'!$A$2:$A$1801,2021,'Data Cruda'!$J$2:$J$1801,"Amoniaco"),0) -> 0.1299521 | G16: 0.48448293 | H16: 752622.1 | I16: =IFERROR((SUMIFS('Data Cruda'!$P$2:$P$1801,'Data Cruda'!$A$2:$A$1801,2021)-SUMIFS('Data Cruda'!$P$2:$P$1801,'Data Cruda'!$A$2:$A$1801,2021,'Data Cruda'!$J$2:$J$1801,"Freón")-SUMIFS('Data Cruda'!$P$2:$P$1801,'Data Cruda'!$A$2:$A$1801,2021,'Data Cruda'!$J$2:$J$1801,"Amoniaco"))/(SUMIFS('Data Cruda'!$K$2:$K$1801,'Data Cruda'!$A$2:$A$1801,2021)-SUMIFS('Data Cruda'!$K$2:$K$1801,'Data Cruda'!$A$2:$A$1801,2021,'Data Cruda'!$J$2:$J$1801,"Freón")-SUMIFS('Data Cruda'!$K$2:$K$1801,'Data Cruda'!$A$2:$A$1801,2021,'Data Cruda'!$J$2:$J$1801,"Amoniaco")),0) -> 0.12704607 | J16: 0.037055738 | K16: 20310541
A17: 2022 | B17: 11783033 | C17: =IFERROR(SUMIFS('Data Cruda'!$P$2:$P$1801,'Data Cruda'!$A$2:$A$1801,2022,'Data Cruda'!$J$2:$J$1801,"Freón")/SUMIFS('Data Cruda'!$K$2:$K$1801,'Data Cruda'!$A$2:$A$1801,2022,'Data Cruda'!$J$2:$J$1801,"Freón"),0) -> 0.13491101 | D17: 0.35491316 | E17: 20442114 | F17: =IFERROR(SUMIFS('Data Cruda'!$P$2:$P$1801,'Data Cruda'!$A$2:$A$1801,2022,'Data Cruda'!$J$2:$J$1801,"Amoniaco")/SUMIFS('Data Cruda'!$K$2:$K$1801,'Data Cruda'!$A$2:$A$1801,2022,'Data Cruda'!$J$2:$J$1801,"Amoniaco"),0) -> 0.14296732 | G17: 0.61573071 | H17: 974616.81 | I17: =IFERROR((SUMIFS('Data Cruda'!$P$2:$P$1801,'Data Cruda'!$A$2:$A$1801,2022)-SUMIFS('Data Cruda'!$P$2:$P$1801,'Data Cruda'!$A$2:$A$1801,2022,'Data Cruda'!$J$2:$J$1801,"Freón")-SUMIFS('Data Cruda'!$P$2:$P$1801,'Data Cruda'!$A$2:$A$1801,2022,'Data Cruda'!$J$2:$J$1801,"Amoniaco"))/(SUMIFS('Data Cruda'!$K$2:$K$1801,'Data Cruda'!$A$2:$A$1801,2022)-SUMIFS('Data Cruda'!$K$2:$K$1801,'Data Cruda'!$A$2:$A$1801,2022,'Data Cruda'!$J$2:$J$1801,"Freón")-SUMIFS('Data Cruda'!$K$2:$K$1801,'Data Cruda'!$A$2:$A$1801,2022,'Data Cruda'!$J$2:$J$1801,"Amoniaco")),0) -> 0.17410403 | J17: 0.029356136 | K17: 33199765
A18: 2023 | B18: 10023577 | C18: =IFERROR(SUMIFS('Data Cruda'!$P$2:$P$1801,'Data Cruda'!$A$2:$A$1801,2023,'Data Cruda'!$J$2:$J$1801,"Freón")/SUMIFS('Data Cruda'!$K$2:$K$1801,'Data Cruda'!$A$2:$A$1801,2023,'Data Cruda'!$J$2:$J$1801,"Freón"),0) -> 0.15819948 | D18: 0.65559102 | E18: 4060599.4 | F18: =IFERROR(SUMIFS('Data Cruda'!$P$2:$P$1801,'Data Cruda'!$A$2:$A$1801,2023,'Data Cruda'!$J$2:$J$1801,"Amoniaco")/SUMIFS('Data Cruda'!$K$2:$K$1801,'Data Cruda'!$A$2:$A$1801,2023,'Data Cruda'!$J$2:$J$1801,"Amoniaco"),0) -> 0.19810948 | G18: 0.26558309 | H18: 1205198.7 | I18: =IFERROR((SUMIFS('Data Cruda'!$P$2:$P$1801,'Data Cruda'!$A$2:$A$1801,2023)-SUMIFS('Data Cruda'!$P$2:$P$1801,'Data Cruda'!$A$2:$A$1801,2023,'Data Cruda'!$J$2:$J$1801,"Freón")-SUMIFS('Data Cruda'!$P$2:$P$1801,'Data Cruda'!$A$2:$A$1801,2023,'Data Cruda'!$J$2:$J$1801,"Amoniaco"))/(SUMIFS('Data Cruda'!$K$2:$K$1801,'Data Cruda'!$A$2:$A$1801,2023)-SUMIFS('Data Cruda'!$K$2:$K$1801,'Data Cruda'!$A$2:$A$1801,2023,'Data Cruda'!$J$2:$J$1801,"Freón")-SUMIFS('Data Cruda'!$K$2:$K$1801,'Data Cruda'!$A$2:$A$1801,2023,'Data Cruda'!$J$2:$J$1801,"Amoniaco")),0) -> 0.1850738 | J18: 0.078825895 | K18: 15289375
A19: 2024 | B19: 6480103.8 | C19: =IFERROR(SUMIFS('Data Cruda'!$P$2:$P$1801,'Data Cruda'!$A$2:$A$1801,2024,'Data Cruda'!$J$2:$J$1801,"Freón")/SUMIFS('Data Cruda'!$K$2:$K$1801,'Data Cruda'!$A$2:$A$1801,2024,'Data Cruda'!$J$2:$J$1801,"Freón"),0) -> 0.14581802 | D19: 0.41939299 | E19: 7445782.2 | F19: =IFERROR(SUMIFS('Data Cruda'!$P$2:$P$1801,'Data Cruda'!$A$2:$A$1801,2024,'Data Cruda'!$J$2:$J$1801,"Amoniaco")/SUMIFS('Data Cruda'!$K$2:$K$1801,'Data Cruda'!$A$2:$A$1801,2024,'Data Cruda'!$J$2:$J$1801,"Amoniaco"),0) -> 0.16032871 | G19: 0.4818918 | H19: 1525263.4 | I19: =IFERROR((SUMIFS('Data Cruda'!$P$2:$P$1801,'Data Cruda'!$A$2:$A$1801,2024)-SUMIFS('Data Cruda'!$P$2:$P$1801,'Data Cruda'!$A$2:$A$1801,2024,'Data Cruda'!$J$2:$J$1801,"Freón")-SUMIFS('Data Cruda'!$P$2:$P$1801,'Data Cruda'!$A$2:$A$1801,2024,'Data Cruda'!$J$2:$J$1801,"Amoniaco"))/(SUMIFS('Data Cruda'!$K$2:$K$1801,'Data Cruda'!$A$2:$A$1801,2024)-SUMIFS('Data Cruda'!$K$2:$K$1801,'Data Cruda'!$A$2:$A$1801,2024,'Data Cruda'!$J$2:$J$1801,"Freón")-SUMIFS('Data Cruda'!$K$2:$K$1801,'Data Cruda'!$A$2:$A$1801,2024,'Data Cruda'!$J$2:$J$1801,"Amoniaco")),0) -> 0.14773948 | J19: 0.098715206 | K19: 15451149
A20: 2025 | B20: 6662323.2 | C20: =IFERROR(SUMIFS('Data Cruda'!$P$2:$P$1801,'Data Cruda'!$A$2:$A$1801,2025,'Data Cruda'!$J$2:$J$1801,"Freón")/SUMIFS('Data Cruda'!$K$2:$K$1801,'Data Cruda'!$A$2:$A$1801,2025,'Data Cruda'!$J$2:$J$1801,"Freón"),0) -> 0.15384681 | D20: 0.19058992 | E20: 21030719 | F20: =IFERROR(SUMIFS('Data Cruda'!$P$2:$P$1801,'Data Cruda'!$A$2:$A$1801,2025,'Data Cruda'!$J$2:$J$1801,"Amoniaco")/SUMIFS('Data Cruda'!$K$2:$K$1801,'Data Cruda'!$A$2:$A$1801,2025,'Data Cruda'!$J$2:$J$1801,"Amoniaco"),0) -> 0.1599399 | G20: 0.60162845 | H20: 7263281.9 | I20: =IFERROR((SUMIFS('Data Cruda'!$P$2:$P$1801,'Data Cruda'!$A$2:$A$1801,2025)-SUMIFS('Data Cruda'!$P$2:$P$1801,'Data Cruda'!$A$2:$A$1801,2025,'Data Cruda'!$J$2:$J$1801,"Freón")-SUMIFS('Data Cruda'!$P$2:$P$1801,'Data Cruda'!$A$2:$A$1801,2025,'Data Cruda'!$J$2:$J$1801,"Amoniaco"))/(SUMIFS('Data Cruda'!$K$2:$K$1801,'Data Cruda'!$A$2:$A$1801,2025)-SUMIFS('Data Cruda'!$K$2:$K$1801,'Data Cruda'!$A$2:$A$1801,2025,'Data Cruda'!$J$2:$J$1801,"Freón")-SUMIFS('Data Cruda'!$K$2:$K$1801,'Data Cruda'!$A$2:$A$1801,2025,'Data Cruda'!$J$2:$J$1801,"Amoniaco")),0) -> 0.17062466 | J20: 0.20778163 | K20: 34956324
A21: 2026 | B21: 4913328.2 | C21: =IFERROR(SUMIFS('Data Cruda'!$P$2:$P$1801,'Data Cruda'!$A$2:$A$1801,2026,'Data Cruda'!$J$2:$J$1801,"Freón")/SUMIFS('Data Cruda'!$K$2:$K$1801,'Data Cruda'!$A$2:$A$1801,2026,'Data Cruda'!$J$2:$J$1801,"Freón"),0) -> 0.16485593 | D21: 0.17385753 | E21: 21821650 | F21: =IFERROR(SUMIFS('Data Cruda'!$P$2:$P$1801,'Data Cruda'!$A$2:$A$1801,2026,'Data Cruda'!$J$2:$J$1801,"Amoniaco")/SUMIFS('Data Cruda'!$K$2:$K$1801,'Data Cruda'!$A$2:$A$1801,2026,'Data Cruda'!$J$2:$J$1801,"Amoniaco"),0) -> 0.14940768 | G21: 0.77215651 | H21: 1525678.4 | I21: =IFERROR((SUMIFS('Data Cruda'!$P$2:$P$1801,'Data Cruda'!$A$2:$A$1801,2026)-SUMIFS('Data Cruda'!$P$2:$P$1801,'Data Cruda'!$A$2:$A$1801,2026,'Data Cruda'!$J$2:$J$1801,"Freón")-SUMIFS('Data Cruda'!$P$2:$P$1801,'Data Cruda'!$A$2:$A$1801,2026,'Data Cruda'!$J$2:$J$1801,"Amoniaco"))/(SUMIFS('Data Cruda'!$K$2:$K$1801,'Data Cruda'!$A$2:$A$1801,2026)-SUMIFS('Data Cruda'!$K$2:$K$1801,'Data Cruda'!$A$2:$A$1801,2026,'Data Cruda'!$J$2:$J$1801,"Freón")-SUMIFS('Data Cruda'!$K$2:$K$1801,'Data Cruda'!$A$2:$A$1801,2026,'Data Cruda'!$J$2:$J$1801,"Amoniaco")),0) -> 0.1690913 | J21: 0.05398595 | K21: 28260657
A22: TOTAL | B22: 49580174 | C22: =IFERROR(SUMPRODUCT(ISNUMBER(MATCH('Data Cruda'!$A$2:$A$1801,{2021,2022,2023,2024,2025,2026},0))*('Data Cruda'!$J$2:$J$1801="Freón")*'Data Cruda'!$P$2:$P$1801)/SUMPRODUCT(ISNUMBER(MATCH('Data Cruda'!$A$2:$A$1801,{2021,2022,2023,2024,2025,2026},0))*('Data Cruda'!$J$2:$J$1801="Freón")*'Data Cruda'!$K$2:$K$1801),0) -> 0.14739437 | D22: 0.33621014 | E22: 84640976 | F22: =IFERROR(SUMPRODUCT(ISNUMBER(MATCH('Data Cruda'!$A$2:$A$1801,{2021,2022,2023,2024,2025,2026},0))*('Data Cruda'!$J$2:$J$1801="Amoniaco")*'Data Cruda'!$P$2:$P$1801)/SUMPRODUCT(ISNUMBER(MATCH('Data Cruda'!$A$2:$A$1801,{2021,2022,2023,2024,2025,2026},0))*('Data Cruda'!$J$2:$J$1801="Amoniaco")*'Data Cruda'!$K$2:$K$1801),0) -> 0.15150447 | G22: 0.57396238 | H22: 13246661 | I22: =IFERROR((SUMPRODUCT(ISNUMBER(MATCH('Data Cruda'!$A$2:$A$1801,{2021,2022,2023,2024,2025,2026},0))*'Data Cruda'!$P$2:$P$1801)-SUMIFS('Data Cruda'!$P$2:$P$1801,'Data Cruda'!$J$2:$J$1801,"Freón")-SUMIFS('Data Cruda'!$P$2:$P$1801,'Data Cruda'!$J$2:$J$1801,"Amoniaco"))/(SUMPRODUCT(ISNUMBER(MATCH('Data Cruda'!$A$2:$A$1801,{2021,2022,2023,2024,2025,2026},0))*'Data Cruda'!$K$2:$K$1801)-SUMIFS('Data Cruda'!$K$2:$K$1801,'Data Cruda'!$J$2:$J$1801,"Freón")-SUMIFS('Data Cruda'!$K$2:$K$1801,'Data Cruda'!$J$2:$J$1801,"Amoniaco")),0) -> -0.024593864 | J22: 0.089827476 | K22: 1.4746781e+08
A25: TABLA 3 – TIPO DE VENTA (PR / AD / VS / VSI)
A26: PR=Proyecto · AD=Adicional · VS=Servicio arquitectura · VSI=Servicio arquitectura (variación). 2014-2020 sin clasificar (S/C).
A28: Año | B28: PR Monto | C28: PR % | D28: AD Monto | E28: AD % | F28: VS Monto | G28: VS % | H28: VSI Monto | I28: VSI % | J28: Total Año
A29: 2021 | B29: 19355389 | C29: 0.95297259 | D29: 832200.23 | E29: 0.040973809 | F29: 52000 | G29: 0.0025602469 | H29: 69252 | I29: 0.003409658 | J29: =B29+D29+F29+H29 -> 20308841
A30: 2022 | B30: 28303498 | C30: 0.85252105 | D30: 1109471.6 | E30: 0.033418056 | F30: 0 | G30: 0 | H30: 0 | I30: 0 | J30: =B30+D30+F30+H30 -> 29412970
A31: 2023 | B31: 14249025 | C31: 0.93195606 | D31: 1040349.4 | E31: 0.068043944 | F31: 0 | G31: 0 | H31: 0 | I31: 0 | J31: =B31+D31+F31+H31 -> 15289375
A32: 2024 | B32: 14024848 | C32: 0.90768962 | D32: 1426301.5 | E32: 0.092310381 | F32: 0 | G32: 0 | H32: 0 | I32: 0 | J32: =B32+D32+F32+H32 -> 15451149
A33: 2025 | B33: 33216546 | C33: 0.95022994 | D33: 1219228.8 | E33: 0.034878633 | F33: 496549.4 | G33: 0.014204852 | H33: 24000 | I33: 0.00068657104 | J33: =B33+D33+F33+H33 -> 34956324
A34: 2026 | B34: 26963097 | C34: 0.95408599 | D34: 1193765.1 | E34: 0.042241236 | F34: 95325 | G34: 0.0033730638 | H34: 8470 | I34: 0.00029970995 | J34: =B34+D34+F34+H34 -> 28260657
A35: TOTAL | B35: 1.361124e+08 | C35: 0.92299738 | D35: 6821316.6 | E35: 0.046256308 | F35: 643874.4 | G35: 0.004366203 | H35: 101722 | I35: 0.00068979121 | J35: 1.4746781e+08

Sheet 3. Clientes 2025-2026
A1: TABLA 1 – CLIENTES ACTIVOS 2025-2026
A3: # | B3: Cliente | C3: Monto 2025 | D3: Monto 2026 | E3: Total 25-26 | F3: % Total | G3: Margen %
A4: 1 | B4: AGROBERRIES PERU S.A.C. | C4: 0 | D4: 10141560 | E4: 10141560 | F4: 0.16042462 | G4: =IFERROR((SUMIFS('Data Cruda'!$P$2:$P$1801,'Data Cruda'!$D$2:$D$1801,"AGROBERRIES PERU S.A.C.",'Data Cruda'!$A$2:$A$1801,2025)+SUMIFS('Data Cruda'!$P$2:$P$1801,'Data Cruda'!$D$2:$D$1801,"AGROBERRIES PERU S.A.C.",'Data Cruda'!$A$2:$A$1801,2026))/(SUMIFS('Data Cruda'!$K$2:$K$1801,'Data Cruda'!$D$2:$D$1801,"AGROBERRIES PERU S.A.C.",'Data Cruda'!$A$2:$A$1801,2025)+SUMIFS('Data Cruda'!$K$2:$K$1801,'Data Cruda'!$D$2:$D$1801,"AGROBERRIES PERU S.A.C.",'Data Cruda'!$A$2:$A$1801,2026)),0) -> 0.1393832
A5: 2 | B5: DANPER TRUJILLO S.A.C. | C5: 4480901 | D5: 5000 | E5: 4485901 | F5: 0.07096038 | G5: =IFERROR((SUMIFS('Data Cruda'!$P$2:$P$1801,'Data Cruda'!$D$2:$D$1801,"DANPER TRUJILLO S.A.C.",'Data Cruda'!$A$2:$A$1801,2025)+SUMIFS('Data Cruda'!$P$2:$P$1801,'Data Cruda'!$D$2:$D$1801,"DANPER TRUJILLO S.A.C.",'Data Cruda'!$A$2:$A$1801,2026))/(SUMIFS('Data Cruda'!$K$2:$K$1801,'Data Cruda'!$D$2:$D$1801,"DANPER TRUJILLO S.A.C.",'Data Cruda'!$A$2:$A$1801,2025)+SUMIFS('Data Cruda'!$K$2:$K$1801,'Data Cruda'!$D$2:$D$1801,"DANPER TRUJILLO S.A.C.",'Data Cruda'!$A$2:$A$1801,2026)),0) -> 0.15082002
A6: 3 | B6: CORPORACION AGROLATINA S.A.C. | C6: 2130000 | D6: 2320000 | E6: 4450000 | F6: 0.070392478 | G6: =IFERROR((SUMIFS('Data Cruda'!$P$2:$P$1801,'Data Cruda'!$D$2:$D$1801,"CORPORACION AGROLATINA S.A.C.",'Data Cruda'!$A$2:$A$1801,2025)+SUMIFS('Data Cruda'!$P$2:$P$1801,'Data Cruda'!$D$2:$D$1801,"CORPORACION AGROLATINA S.A.C.",'Data Cruda'!$A$2:$A$1801,2026))/(SUMIFS('Data Cruda'!$K$2:$K$1801,'Data Cruda'!$D$2:$D$1801,"CORPORACION AGROLATINA S.A.C.",'Data Cruda'!$A$2:$A$1801,2025)+SUMIFS('Data Cruda'!$K$2:$K$1801,'Data Cruda'!$D$2:$D$1801,"CORPORACION AGROLATINA S.A.C.",'Data Cruda'!$A$2:$A$1801,2026)),0) -> 0.14905433
A7: 4 | B7: AGRICOLA HUARMEY S.A. | C7: 3839343.4 | D7: 169653.6 | E7: 4008997 | F7: 0.063416458 | G7: =IFERROR((SUMIFS('Data Cruda'!$P$2:$P$1801,'Data Cruda'!$D$2:$D$1801,"AGRICOLA HUARMEY S.A.",'Data Cruda'!$A$2:$A$1801,2025)+SUMIFS('Data Cruda'!$P$2:$P$1801,'Data Cruda'!$D$2:$D$1801,"AGRICOLA HUARMEY S.A.",'Data Cruda'!$A$2:$A$1801,2026))/(SUMIFS('Data Cruda'!$K$2:$K$1801,'Data Cruda'!$D$2:$D$1801,"AGRICOLA HUARMEY S.A.",'Data Cruda'!$A$2:$A$1801,2025)+SUMIFS('Data Cruda'!$K$2:$K$1801,'Data Cruda'!$D$2:$D$1801,"AGRICOLA HUARMEY S.A.",'Data Cruda'!$A$2:$A$1801,2026)),0) -> 0.16069571
A8: 5 | B8: PROSEMBRA SOCIEDAD ANONIMA CERRADA | C8: 3374482.5 | D8: 257759.74 | E8: 3632242.2 | F8: 0.057456749 | G8: =IFERROR((SUMIFS('Data Cruda'!$P$2:$P$1801,'Data Cruda'!$D$2:$D$1801,"PROSEMBRA SOCIEDAD ANONIMA CERRADA",'Data Cruda'!$A$2:$A$1801,2025)+SUMIFS('Data Cruda'!$P$2:$P$1801,'Data Cruda'!$D$2:$D$1801,"PROSEMBRA SOCIEDAD ANONIMA CERRADA",'Data Cruda'!$A$2:$A$1801,2026))/(SUMIFS('Data Cruda'!$K$2:$K$1801,'Data Cruda'!$D$2:$D$1801,"PROSEMBRA SOCIEDAD ANONIMA CERRADA",'Data Cruda'!$A$2:$A$1801,2025)+SUMIFS('Data Cruda'!$K$2:$K$1801,'Data Cruda'!$D$2:$D$1801,"PROSEMBRA SOCIEDAD ANONIMA CERRADA",'Data Cruda'!$A$2:$A$1801,2026)),0) -> 0.17386194
A9: 6 | B9: AQU ANQA S.A.C. | C9: 3325088.7 | D9: 30911.99 | E9: 3356000.7 | F9: 0.053087013 | G9: =IFERROR((SUMIFS('Data Cruda'!$P$2:$P$1801,'Data Cruda'!$D$2:$D$1801,"AQU ANQA S.A.C.",'Data Cruda'!$A$2:$A$1801,2025)+SUMIFS('Data Cruda'!$P$2:$P$1801,'Data Cruda'!$D$2:$D$1801,"AQU ANQA S.A.C.",'Data Cruda'!$A$2:$A$1801,2026))/(SUMIFS('Data Cruda'!$K$2:$K$1801,'Data Cruda'!$D$2:$D$1801,"AQU ANQA S.A.C.",'Data Cruda'!$A$2:$A$1801,2025)+SUMIFS('Data Cruda'!$K$2:$K$1801,'Data Cruda'!$D$2:$D$1801,"AQU ANQA S.A.C.",'Data Cruda'!$A$2:$A$1801,2026)),0) -> 0.18232047
A10: 7 | B10: BOMAREA S.R.L. | C10: 0 | D10: 3162368.8 | E10: 3162368.8 | F10: 0.050024039 | G10: =IFERROR((SUMIFS('Data Cruda'!$P$2:$P$1801,'Data Cruda'!$D$2:$D$1801,"BOMAREA S.R.L.",'Data Cruda'!$A$2:$A$1801,2025)+SUMIFS('Data Cruda'!$P$2:$P$1801,'Data Cruda'!$D$2:$D$1801,"BOMAREA S.R.L.",'Data Cruda'!$A$2:$A$1801,2026))/(SUMIFS('Data Cruda'!$K$2:$K$1801,'Data Cruda'!$D$2:$D$1801,"BOMAREA S.R.L.",'Data Cruda'!$A$2:$A$1801,2025)+SUMIFS('Data Cruda'!$K$2:$K$1801,'Data Cruda'!$D$2:$D$1801,"BOMAREA S.R.L.",'Data Cruda'!$A$2:$A$1801,2026)),0) -> 0.14773245
A11: 8 | B11: Q PACK S.A.C. | C11: 2825478.5 | D11: 123657.16 | E11: 2949135.6 | F11: 0.046651004 | G11: =IFERROR((SUMIFS('Data Cruda'!$P$2:$P$1801,'Data Cruda'!$D$2:$D$1801,"Q PACK S.A.C.",'Data Cruda'!$A$2:$A$1801,2025)+SUMIFS('Data Cruda'!$P$2:$P$1801,'Data Cruda'!$D$2:$D$1801,"Q PACK S.A.C.",'Data Cruda'!$A$2:$A$1801,2026))/(SUMIFS('Data Cruda'!$K$2:$K$1801,'Data Cruda'!$D$2:$D$1801,"Q PACK S.A.C.",'Data Cruda'!$A$2:$A$1801,2025)+SUMIFS('Data Cruda'!$K$2:$K$1801,'Data Cruda'!$D$2:$D$1801,"Q PACK S.A.C.",'Data Cruda'!$A$2:$A$1801,2026)),0) -> 0.17957819
A12: 9 | B12: TAL S.A. | C12: 20145 | D12: 2052587.8 | E12: 2072732.8 | F12: 0.032787595 | G12: =IFERROR((SUMIFS('Data Cruda'!$P$2:$P$1801,'Data Cruda'!$D$2:$D$1801,"TAL S.A.",'Data Cruda'!$A$2:$A$1801,2025)+SUMIFS('Data Cruda'!$P$2:$P$1801,'Data Cruda'!$D$2:$D$1801,"TAL S.A.",'Data Cruda'!$A$2:$A$1801,2026))/(SUMIFS('Data Cruda'!$K$2:$K$1801,'Data Cruda'!$D$2:$D$1801,"TAL S.A.",'Data Cruda'!$A$2:$A$1801,2025)+SUMIFS('Data Cruda'!$K$2:$K$1801,'Data Cruda'!$D$2:$D$1801,"TAL S.A.",'Data Cruda'!$A$2:$A$1801,2026)),0) -> 0.13883549
A13: 10 | B13: PROCESOS AGROINDUSTRIALES SOCIEDAD ANONIMA | C13: 0 | D13: 2034100.6 | E13: 2034100.6 | F13: 0.03217649 | G13: =IFERROR((SUMIFS('Data Cruda'!$P$2:$P$1801,'Data Cruda'!$D$2:$D$1801,"PROCESOS AGROINDUSTRIALES SOCIEDAD ANONIMA",'Data Cruda'!$A$2:$A$1801,2025)+SUMIFS('Data Cruda'!$P$2:$P$1801,'Data Cruda'!$D$2:$D$1801,"PROCESOS AGROINDUSTRIALES SOCIEDAD ANONIMA",'Data Cruda'!$A$2:$A$1801,2026))/(SUMIFS('Data Cruda'!$K$2:$K$1801,'Data Cruda'!$D$2:$D$1801,"PROCESOS AGROINDUSTRIALES SOCIEDAD ANONIMA",'Data Cruda'!$A$2:$A$1801,2025)+SUMIFS('Data Cruda'!$K$2:$K$1801,'Data Cruda'!$D$2:$D$1801,"PROCESOS AGROINDUSTRIALES SOCIEDAD ANONIMA",'Data Cruda'!$A$2:$A$1801,2026)),0) -> 0.14012856
A14: 11 | B14: SOCIEDAD AGRICOLA DROKASA S.A. | C14: 1421017.1 | D14: 208585.21 | E14: 1629602.3 | F14: 0.025777921 | G14: =IFERROR((SUMIFS('Data Cruda'!$P$2:$P$1801,'Data Cruda'!$D$2:$D$1801,"SOCIEDAD AGRICOLA DROKASA S.A.",'Data Cruda'!$A$2:$A$1801,2025)+SUMIFS('Data Cruda'!$P$2:$P$1801,'Data Cruda'!$D$2:$D$1801,"SOCIEDAD AGRICOLA DROKASA S.A.",'Data Cruda'!$A$2:$A$1801,2026))/(SUMIFS('Data Cruda'!$K$2:$K$1801,'Data Cruda'!$D$2:$D$1801,"SOCIEDAD AGRICOLA DROKASA S.A.",'Data Cruda'!$A$2:$A$1801,2025)+SUMIFS('Data Cruda'!$K$2:$K$1801,'Data Cruda'!$D$2:$D$1801,"SOCIEDAD AGRICOLA DROKASA S.A.",'Data Cruda'!$A$2:$A$1801,2026)),0) -> 0.14932792
A15: 12 | B15: AGRICOLA ALAYA SOCIEDAD ANONIMA CERRADA | C15: 1490360.7 | D15: 0 | E15: 1490360.7 | F15: 0.023575322 | G15: =IFERROR((SUMIFS('Data Cruda'!$P$2:$P$1801,'Data Cruda'!$D$2:$D$1801,"AGRICOLA ALAYA SOCIEDAD ANONIMA CERRADA",'Data Cruda'!$A$2:$A$1801,2025)+SUMIFS('Data Cruda'!$P$2:$P$1801,'Data Cruda'!$D$2:$D$1801,"AGRICOLA ALAYA SOCIEDAD ANONIMA CERRADA",'Data Cruda'!$A$2:$A$1801,2026))/(SUMIFS('Data Cruda'!$K$2:$K$1801,'Data Cruda'!$D$2:$D$1801,"AGRICOLA ALAYA SOCIEDAD ANONIMA CERRADA",'Data Cruda'!$A$2:$A$1801,2025)+SUMIFS('Data Cruda'!$K$2:$K$1801,'Data Cruda'!$D$2:$D$1801,"AGRICOLA ALAYA SOCIEDAD ANONIMA CERRADA",'Data Cruda'!$A$2:$A$1801,2026)),0) -> 0.17062136
A16: 13 | B16: TA EXPORT S.A.C. | C16: 0 | D16: 1460000 | E16: 1460000 | F16: 0.02309506 | G16: =IFERROR((SUMIFS('Data Cruda'!$P$2:$P$1801,'Data Cruda'!$D$2:$D$1801,"TA EXPORT S.A.C.",'Data Cruda'!$A$2:$A$1801,2025)+SUMIFS('Data Cruda'!$P$2:$P$1801,'Data Cruda'!$D$2:$D$1801,"TA EXPORT S.A.C.",'Data Cruda'!$A$2:$A$1801,2026))/(SUMIFS('Data Cruda'!$K$2:$K$1801,'Data Cruda'!$D$2:$D$1801,"TA EXPORT S.A.C.",'Data Cruda'!$A$2:$A$1801,2025)+SUMIFS('Data Cruda'!$K$2:$K$1801,'Data Cruda'!$D$2:$D$1801,"TA EXPORT S.A.C.",'Data Cruda'!$A$2:$A$1801,2026)),0) -> 0.1634769
A17: 14 | B17: AGRICOLA PAMPA BAJA S.A.C. | C17: 596173.6 | D17: 628712.2 | E17: 1224885.8 | F17: 0.019375898 | G17: =IFERROR((SUMIFS('Data Cruda'!$P$2:$P$1801,'Data Cruda'!$D$2:$D$1801,"AGRICOLA PAMPA BAJA S.A.C.",'Data Cruda'!$A$2:$A$1801,2025)+SUMIFS('Data Cruda'!$P$2:$P$1801,'Data Cruda'!$D$2:$D$1801,"AGRICOLA PAMPA BAJA S.A.C.",'Data Cruda'!$A$2:$A$1801,2026))/(SUMIFS('Data Cruda'!$K$2:$K$1801,'Data Cruda'!$D$2:$D$1801,"AGRICOLA PAMPA BAJA S.A.C.",'Data Cruda'!$A$2:$A$1801,2025)+SUMIFS('Data Cruda'!$K$2:$K$1801,'Data Cruda'!$D$2:$D$1801,"AGRICOLA PAMPA BAJA S.A.C.",'Data Cruda'!$A$2:$A$1801,2026)),0) -> 0.15406422
A18: 15 | B18: AGROINDUSTRIAS AIB S.A | C18: 693362.39 | D18: 394694.81 | E18: 1088057.2 | F18: 0.01721147 | G18: =IFERROR((SUMIFS('Data Cruda'!$P$2:$P$1801,'Data Cruda'!$D$2:$D$1801,"AGROINDUSTRIAS AIB S.A",'Data Cruda'!$A$2:$A$1801,2025)+SUMIFS('Data Cruda'!$P$2:$P$1801,'Data Cruda'!$D$2:$D$1801,"AGROINDUSTRIAS AIB S.A",'Data Cruda'!$A$2:$A$1801,2026))/(SUMIFS('Data Cruda'!$K$2:$K$1801,'Data Cruda'!$D$2:$D$1801,"AGROINDUSTRIAS AIB S.A",'Data Cruda'!$A$2:$A$1801,2025)+SUMIFS('Data Cruda'!$K$2:$K$1801,'Data Cruda'!$D$2:$D$1801,"AGROINDUSTRIAS AIB S.A",'Data Cruda'!$A$2:$A$1801,2026)),0) -> 0.15289941
A19: 16 | B19: EL PEDREGAL S.A. | C19: 954731.07 | D19: 0 | E19: 954731.07 | F19: 0.015102446 | G19: =IFERROR((SUMIFS('Data Cruda'!$P$2:$P$1801,'Data Cruda'!$D$2:$D$1801,"EL PEDREGAL S.A.",'Data Cruda'!$A$2:$A$1801,2025)+SUMIFS('Data Cruda'!$P$2:$P$1801,'Data Cruda'!$D$2:$D$1801,"EL PEDREGAL S.A.",'Data Cruda'!$A$2:$A$1801,2026))/(SUMIFS('Data Cruda'!$K$2:$K$1801,'Data Cruda'!$D$2:$D$1801,"EL PEDREGAL S.A.",'Data Cruda'!$A$2:$A$1801,2025)+SUMIFS('Data Cruda'!$K$2:$K$1801,'Data Cruda'!$D$2:$D$1801,"EL PEDREGAL S.A.",'Data Cruda'!$A$2:$A$1801,2026)),0) -> 0.14383219
A20: 17 | B20: PROCESADORA LARAN SAC | C20: 195018.42 | D20: 715885.05 | E20: 910903.47 | F20: 0.014409158 | G20: =IFERROR((SUMIFS('Data Cruda'!$P$2:$P$1801,'Data Cruda'!$D$2:$D$1801,"PROCESADORA LARAN SAC",'Data Cruda'!$A$2:$A$1801,2025)+SUMIFS('Data Cruda'!$P$2:$P$1801,'Data Cruda'!$D$2:$D$1801,"PROCESADORA LARAN SAC",'Data Cruda'!$A$2:$A$1801,2026))/(SUMIFS('Data Cruda'!$K$2:$K$1801,'Data Cruda'!$D$2:$D$1801,"PROCESADORA LARAN SAC",'Data Cruda'!$A$2:$A$1801,2025)+SUMIFS('Data Cruda'!$K$2:$K$1801,'Data Cruda'!$D$2:$D$1801,"PROCESADORA LARAN SAC",'Data Cruda'!$A$2:$A$1801,2026)),0) -> 0.13679221
A21: 18 | B21: ARA FOODS INDUSTRY S.A.C. | C21: 805597.47 | D21: 100000 | E21: 905597.47 | F21: 0.014325225 | G21: =IFERROR((SUMIFS('Data Cruda'!$P$2:$P$1801,'Data Cruda'!$D$2:$D$1801,"ARA FOODS INDUSTRY S.A.C.",'Data Cruda'!$A$2:$A$1801,2025)+SUMIFS('Data Cruda'!$P$2:$P$1801,'Data Cruda'!$D$2:$D$1801,"ARA FOODS INDUSTRY S.A.C.",'Data Cruda'!$A$2:$A$1801,2026))/(SUMIFS('Data Cruda'!$K$2:$K$1801,'Data Cruda'!$D$2:$D$1801,"ARA FOODS INDUSTRY S.A.C.",'Data Cruda'!$A$2:$A$1801,2025)+SUMIFS('Data Cruda'!$K$2:$K$1801,'Data Cruda'!$D$2:$D$1801,"ARA FOODS INDUSTRY S.A.C.",'Data Cruda'!$A$2:$A$1801,2026)),0) -> 0.17152947
A22: 19 | B22: IMBAREX S.A. | C22: 584350 | D22: 269100 | E22: 853450 | F22: 0.013500328 | G22: =IFERROR((SUMIFS('Data Cruda'!$P$2:$P$1801,'Data Cruda'!$D$2:$D$1801,"IMBAREX S.A.",'Data Cruda'!$A$2:$A$1801,2025)+SUMIFS('Data Cruda'!$P$2:$P$1801,'Data Cruda'!$D$2:$D$1801,"IMBAREX S.A.",'Data Cruda'!$A$2:$A$1801,2026))/(SUMIFS('Data Cruda'!$K$2:$K$1801,'Data Cruda'!$D$2:$D$1801,"IMBAREX S.A.",'Data Cruda'!$A$2:$A$1801,2025)+SUMIFS('Data Cruda'!$K$2:$K$1801,'Data Cruda'!$D$2:$D$1801,"IMBAREX S.A.",'Data Cruda'!$A$2:$A$1801,2026)),0) -> 0.16949982
A23: 20 | B23: AGROVISION PERU S.A.C. | C23: 817031.34 | D23: 0 | E23: 817031.34 | F23: 0.012924238 | G23: =IFERROR((SUMIFS('Data Cruda'!$P$2:$P$1801,'Data Cruda'!$D$2:$D$1801,"AGROVISION PERU S.A.C.",'Data Cruda'!$A$2:$A$1801,2025)+SUMIFS('Data Cruda'!$P$2:$P$1801,'Data Cruda'!$D$2:$D$1801,"AGROVISION PERU S.A.C.",'Data Cruda'!$A$2:$A$1801,2026))/(SUMIFS('Data Cruda'!$K$2:$K$1801,'Data Cruda'!$D$2:$D$1801,"AGROVISION PERU S.A.C.",'Data Cruda'!$A$2:$A$1801,2025)+SUMIFS('Data Cruda'!$K$2:$K$1801,'Data Cruda'!$D$2:$D$1801,"AGROVISION PERU S.A.C.",'Data Cruda'!$A$2:$A$1801,2026)),0) -> 0.14029453
A24: 21 | B24: AGROCASAGRANDE S.A.C. | C24: 785287.51 | D24: 0 | E24: 785287.51 | F24: 0.012422098 | G24: =IFERROR((SUMIFS('Data Cruda'!$P$2:$P$1801,'Data Cruda'!$D$2:$D$1801,"AGROCASAGRANDE S.A.C.",'Data Cruda'!$A$2:$A$1801,2025)+SUMIFS('Data Cruda'!$P$2:$P$1801,'Data Cruda'!$D$2:$D$1801,"AGROCASAGRANDE S.A.C.",'Data Cruda'!$A$2:$A$1801,2026))/(SUMIFS('Data Cruda'!$K$2:$K$1801,'Data Cruda'!$D$2:$D$1801,"AGROCASAGRANDE S.A.C.",'Data Cruda'!$A$2:$A$1801,2025)+SUMIFS('Data Cruda'!$K$2:$K$1801,'Data Cruda'!$D$2:$D$1801,"AGROCASAGRANDE S.A.C.",'Data Cruda'!$A$2:$A$1801,2026)),0) -> 0.18165273
A25: 22 | B25: PROCESADORA TORRE BLANCA S.A.C | C25: 0 | D25: 721156.89 | E25: 721156.89 | F25: 0.011407645 | G25: =IFERROR((SUMIFS('Data Cruda'!$P$2:$P$1801,'Data Cruda'!$D$2:$D$1801,"PROCESADORA TORRE BLANCA S.A.C",'Data Cruda'!$A$2:$A$1801,2025)+SUMIFS('Data Cruda'!$P$2:$P$1801,'Data Cruda'!$D$2:$D$1801,"PROCESADORA TORRE BLANCA S.A.C",'Data Cruda'!$A$2:$A$1801,2026))/(SUMIFS('Data Cruda'!$K$2:$K$1801,'Data Cruda'!$D$2:$D$1801,"PROCESADORA TORRE BLANCA S.A.C",'Data Cruda'!$A$2:$A$1801,2025)+SUMIFS('Data Cruda'!$K$2:$K$1801,'Data Cruda'!$D$2:$D$1801,"PROCESADORA TORRE BLANCA S.A.C",'Data Cruda'!$A$2:$A$1801,2026)),0) -> 0.19493805
A26: 23 | B26: AGROBUSINESS INTERNATIONAL PERU S.A.C. | C26: 602333.49 | D26: 0 | E26: 602333.49 | F26: 0.0095280331 | G26: =IFERROR((SUMIFS('Data Cruda'!$P$2:$P$1801,'Data Cruda'!$D$2:$D$1801,"AGROBUSINESS INTERNATIONAL PERU S.A.C.",'Data Cruda'!$A$2:$A$1801,2025)+SUMIFS('Data Cruda'!$P$2:$P$1801,'Data Cruda'!$D$2:$D$1801,"AGROBUSINESS INTERNATIONAL PERU S.A.C.",'Data Cruda'!$A$2:$A$1801,2026))/(SUMIFS('Data Cruda'!$K$2:$K$1801,'Data Cruda'!$D$2:$D$1801,"AGROBUSINESS INTERNATIONAL PERU S.A.C.",'Data Cruda'!$A$2:$A$1801,2025)+SUMIFS('Data Cruda'!$K$2:$K$1801,'Data Cruda'!$D$2:$D$1801,"AGROBUSINESS INTERNATIONAL PERU S.A.C.",'Data Cruda'!$A$2:$A$1801,2026)),0) -> 0.17460278
A27: 24 | B27: SANTA SOFIA DEL SUR S.A.C. | C27: 545000 | D27: 5187.52 | E27: 550187.52 | F27: 0.0087031602 | G27: =IFERROR((SUMIFS('Data Cruda'!$P$2:$P$1801,'Data Cruda'!$D$2:$D$1801,"SANTA SOFIA DEL SUR S.A.C.",'Data Cruda'!$A$2:$A$1801,2025)+SUMIFS('Data Cruda'!$P$2:$P$1801,'Data Cruda'!$D$2:$D$1801,"SANTA SOFIA DEL SUR S.A.C.",'Data Cruda'!$A$2:$A$1801,2026))/(SUMIFS('Data Cruda'!$K$2:$K$1801,'Data Cruda'!$D$2:$D$1801,"SANTA SOFIA DEL SUR S.A.C.",'Data Cruda'!$A$2:$A$1801,2025)+SUMIFS('Data Cruda'!$K$2:$K$1801,'Data Cruda'!$D$2:$D$1801,"SANTA SOFIA DEL SUR S.A.C.",'Data Cruda'!$A$2:$A$1801,2026)),0) -> 0.13309998
A28: 25 | B28: AGRO FLORAL PERU S.A.C. | C28: 506966.62 | D28: 31962.8 | E28: 538929.42 | F28: 0.0085250736 | G28: =IFERROR((SUMIFS('Data Cruda'!$P$2:$P$1801,'Data Cruda'!$D$2:$D$1801,"AGRO FLORAL PERU S.A.C.",'Data Cruda'!$A$2:$A$1801,2025)+SUMIFS('Data Cruda'!$P$2:$P$1801,'Data Cruda'!$D$2:$D$1801,"AGRO FLORAL PERU S.A.C.",'Data Cruda'!$A$2:$A$1801,2026))/(SUMIFS('Data Cruda'!$K$2:$K$1801,'Data Cruda'!$D$2:$D$1801,"AGRO FLORAL PERU S.A.C.",'Data Cruda'!$A$2:$A$1801,2025)+SUMIFS('Data Cruda'!$K$2:$K$1801,'Data Cruda'!$D$2:$D$1801,"AGRO FLORAL PERU S.A.C.",'Data Cruda'!$A$2:$A$1801,2026)),0) -> 0.17036528
A29: 26 | B29: AGROINDUSTRIA FRUTOS DE ORO S.A.C. | C29: 507312.36 | D29: 760 | E29: 508072.36 | F29: 0.0080369601 | G29: =IFERROR((SUMIFS('Data Cruda'!$P$2:$P$1801,'Data Cruda'!$D$2:$D$1801,"AGROINDUSTRIA FRUTOS DE ORO S.A.C.",'Data Cruda'!$A$2:$A$1801,2025)+SUMIFS('Data Cruda'!$P$2:$P$1801,'Data Cruda'!$D$2:$D$1801,"AGROINDUSTRIA FRUTOS DE ORO S.A.C.",'Data Cruda'!$A$2:$A$1801,2026))/(SUMIFS('Data Cruda'!$K$2:$K$1801,'Data Cruda'!$D$2:$D$1801,"AGROINDUSTRIA FRUTOS DE ORO S.A.C.",'Data Cruda'!$A$2:$A$1801,2025)+SUMIFS('Data Cruda'!$K$2:$K$1801,'Data Cruda'!$D$2:$D$1801,"AGROINDUSTRIA FRUTOS DE ORO S.A.C.",'Data Cruda'!$A$2:$A$1801,2026)),0) -> 0.16892888
A30: 27 | B30: CAMPOSOL S.A. | C30: 0 | D30: 497385.27 | E30: 497385.27 | F30: 0.007867906 | G30: =IFERROR((SUMIFS('Data Cruda'!$P$2:$P$1801,'Data Cruda'!$D$2:$D$1801,"CAMPOSOL S.A.",'Data Cruda'!$A$2:$A$1801,2025)+SUMIFS('Data Cruda'!$P$2:$P$1801,'Data Cruda'!$D$2:$D$1801,"CAMPOSOL S.A.",'Data Cruda'!$A$2:$A$1801,2026))/(SUMIFS('Data Cruda'!$K$2:$K$1801,'Data Cruda'!$D$2:$D$1801,"CAMPOSOL S.A.",'Data Cruda'!$A$2:$A$1801,2025)+SUMIFS('Data Cruda'!$K$2:$K$1801,'Data Cruda'!$D$2:$D$1801,"CAMPOSOL S.A.",'Data Cruda'!$A$2:$A$1801,2026)),0) -> 0.1509673
A31: 28 | B31: SUN FRUITS EXPORTS S.A. | C31: 0 | D31: 460117.04 | E31: 460117.04 | F31: 0.0072783773 | G31: =IFERROR((SUMIFS('Data Cruda'!$P$2:$P$1801,'Data Cruda'!$D$2:$D$1801,"SUN FRUITS EXPORTS S.A.",'Data Cruda'!$A$2:$A$1801,2025)+SUMIFS('Data Cruda'!$P$2:$P$1801,'Data Cruda'!$D$2:$D$1801,"SUN FRUITS EXPORTS S.A.",'Data Cruda'!$A$2:$A$1801,2026))/(SUMIFS('Data Cruda'!$K$2:$K$1801,'Data Cruda'!$D$2:$D$1801,"SUN FRUITS EXPORTS S.A.",'Data Cruda'!$A$2:$A$1801,2025)+SUMIFS('Data Cruda'!$K$2:$K$1801,'Data Cruda'!$D$2:$D$1801,"SUN FRUITS EXPORTS S.A.",'Data Cruda'!$A$2:$A$1801,2026)),0) -> 0.20032218
A32: 29 | B32: ESTANTERIAS METALICAS J.R.M. S.A.C | C32: 0 | D32: 455000 | E32: 455000 | F32: 0.0071974332 | G32: =IFERROR((SUMIFS('Data Cruda'!$P$2:$P$1801,'Data Cruda'!$D$2:$D$1801,"ESTANTERIAS METALICAS J.R.M. S.A.C",'Data Cruda'!$A$2:$A$1801,2025)+SUMIFS('Data Cruda'!$P$2:$P$1801,'Data Cruda'!$D$2:$D$1801,"ESTANTERIAS METALICAS J.R.M. S.A.C",'Data Cruda'!$A$2:$A$1801,2026))/(SUMIFS('Data Cruda'!$K$2:$K$1801,'Data Cruda'!$D$2:$D$1801,"ESTANTERIAS METALICAS J.R.M. S.A.C",'Data Cruda'!$A$2:$A$1801,2025)+SUMIFS('Data Cruda'!$K$2:$K$1801,'Data Cruda'!$D$2:$D$1801,"ESTANTERIAS METALICAS J.R.M. S.A.C",'Data Cruda'!$A$2:$A$1801,2026)),0) -> 0.14243422
A33: 30 | B33: DELICE S.A.C | C33: 384886.11 | D33: 42583.21 | E33: 427469.32 | F33: 0.0067619382 | G33: =IFERROR((SUMIFS('Data Cruda'!$P$2:$P$1801,'Data Cruda'!$D$2:$D$1801,"DELICE S.A.C",'Data Cruda'!$A$2:$A$1801,2025)+SUMIFS('Data Cruda'!$P$2:$P$1801,'Data Cruda'!$D$2:$D$1801,"DELICE S.A.C",'Data Cruda'!$A$2:$A$1801,2026))/(SUMIFS('Data Cruda'!$K$2:$K$1801,'Data Cruda'!$D$2:$D$1801,"DELICE S.A.C",'Data Cruda'!$A$2:$A$1801,2025)+SUMIFS('Data Cruda'!$K$2:$K$1801,'Data Cruda'!$D$2:$D$1801,"DELICE S.A.C",'Data Cruda'!$A$2:$A$1801,2026)),0) -> 0.14045859
A34: 31 | B34: VIRU S.A. | C34: 407039.67 | D34: 0 | E34: 407039.67 | F34: 0.006438771 | G34: =IFERROR((SUMIFS('Data Cruda'!$P$2:$P$1801,'Data Cruda'!$D$2:$D$1801,"VIRU S.A.",'Data Cruda'!$A$2:$A$1801,2025)+SUMIFS('Data Cruda'!$P$2:$P$1801,'Data Cruda'!$D$2:$D$1801,"VIRU S.A.",'Data Cruda'!$A$2:$A$1801,2026))/(SUMIFS('Data Cruda'!$K$2:$K$1801,'Data Cruda'!$D$2:$D$1801,"VIRU S.A.",'Data Cruda'!$A$2:$A$1801,2025)+SUMIFS('Data Cruda'!$K$2:$K$1801,'Data Cruda'!$D$2:$D$1801,"VIRU S.A.",'Data Cruda'!$A$2:$A$1801,2026)),0) -> 0.16478352
A35: 32 | B35: BERRY HARVEST S.A. | C35: 256080.11 | D35: 146670.61 | E35: 402750.72 | F35: 0.0063709261 | G35: =IFERROR((SUMIFS('Data Cruda'!$P$2:$P$1801,'Data Cruda'!$D$2:$D$1801,"BERRY HARVEST S.A.",'Data Cruda'!$A$2:$A$1801,2025)+SUMIFS('Data Cruda'!$P$2:$P$1801,'Data Cruda'!$D$2:$D$1801,"BERRY HARVEST S.A.",'Data Cruda'!$A$2:$A$1801,2026))/(SUMIFS('Data Cruda'!$K$2:$K$1801,'Data Cruda'!$D$2:$D$1801,"BERRY HARVEST S.A.",'Data Cruda'!$A$2:$A$1801,2025)+SUMIFS('Data Cruda'!$K$2:$K$1801,'Data Cruda'!$D$2:$D$1801,"BERRY HARVEST S.A.",'Data Cruda'!$A$2:$A$1801,2026)),0) -> 0.18555774
A36: 33 | B36: AGRICOLA 2M S.A.C. | C36: 390950.55 | D36: 0 | E36: 390950.55 | F36: 0.0061842648 | G36: =IFERROR((SUMIFS('Data Cruda'!$P$2:$P$1801,'Data Cruda'!$D$2:$D$1801,"AGRICOLA 2M S.A.C.",'Data Cruda'!$A$2:$A$1801,2025)+SUMIFS('Data Cruda'!$P$2:$P$1801,'Data Cruda'!$D$2:$D$1801,"AGRICOLA 2M S.A.C.",'Data Cruda'!$A$2:$A$1801,2026))/(SUMIFS('Data Cruda'!$K$2:$K$1801,'Data Cruda'!$D$2:$D$1801,"AGRICOLA 2M S.A.C.",'Data Cruda'!$A$2:$A$1801,2025)+SUMIFS('Data Cruda'!$K$2:$K$1801,'Data Cruda'!$D$2:$D$1801,"AGRICOLA 2M S.A.C.",'Data Cruda'!$A$2:$A$1801,2026)),0) -> 0.16107096
A37: 34 | B37: QALI FRUITS S.A.C. | C37: 0 | D37: 379901.83 | E37: 379901.83 | F37: 0.0060094902 | G37: =IFERROR((SUMIFS('Data Cruda'!$P$2:$P$1801,'Data Cruda'!$D$2:$D$1801,"QALI FRUITS S.A.C.",'Data Cruda'!$A$2:$A$1801,2025)+SUMIFS('Data Cruda'!$P$2:$P$1801,'Data Cruda'!$D$2:$D$1801,"QALI FRUITS S.A.C.",'Data Cruda'!$A$2:$A$1801,2026))/(SUMIFS('Data Cruda'!$K$2:$K$1801,'Data Cruda'!$D$2:$D$1801,"QALI FRUITS S.A.C.",'Data Cruda'!$A$2:$A$1801,2025)+SUMIFS('Data Cruda'!$K$2:$K$1801,'Data Cruda'!$D$2:$D$1801,"QALI FRUITS S.A.C.",'Data Cruda'!$A$2:$A$1801,2026)),0) -> 0.15382442
A38: 35 | B38: DIAMOND BRIDGE SAC | C38: 321860.28 | D38: 0 | E38: 321860.28 | F38: 0.0050913579 | G38: =IFERROR((SUMIFS('Data Cruda'!$P$2:$P$1801,'Data Cruda'!$D$2:$D$1801,"DIAMOND BRIDGE SAC",'Data Cruda'!$A$2:$A$1801,2025)+SUMIFS('Data Cruda'!$P$2:$P$1801,'Data Cruda'!$D$2:$D$1801,"DIAMOND BRIDGE SAC",'Data Cruda'!$A$2:$A$1801,2026))/(SUMIFS('Data Cruda'!$K$2:$K$1801,'Data Cruda'!$D$2:$D$1801,"DIAMOND BRIDGE SAC",'Data Cruda'!$A$2:$A$1801,2025)+SUMIFS('Data Cruda'!$K$2:$K$1801,'Data Cruda'!$D$2:$D$1801,"DIAMOND BRIDGE SAC",'Data Cruda'!$A$2:$A$1801,2026)),0) -> 0.16518315
A39: 36 | B39: LIMONES PIURANOS SOCIEDAD ANONIMA CERRADA | C39: 317796.61 | D39: 0 | E39: 317796.61 | F39: 0.0050270766 | G39: =IFERROR((SUMIFS('Data Cruda'!$P$2:$P$1801,'Data Cruda'!$D$2:$D$1801,"LIMONES PIURANOS SOCIEDAD ANONIMA CERRADA",'Data Cruda'!$A$2:$A$1801,2025)+SUMIFS('Data Cruda'!$P$2:$P$1801,'Data Cruda'!$D$2:$D$1801,"LIMONES PIURANOS SOCIEDAD ANONIMA CERRADA",'Data Cruda'!$A$2:$A$1801,2026))/(SUMIFS('Data Cruda'!$K$2:$K$1801,'Data Cruda'!$D$2:$D$1801,"LIMONES PIURANOS SOCIEDAD ANONIMA CERRADA",'Data Cruda'!$A$2:$A$1801,2025)+SUMIFS('Data Cruda'!$K$2:$K$1801,'Data Cruda'!$D$2:$D$1801,"LIMONES PIURANOS SOCIEDAD ANONIMA CERRADA",'Data Cruda'!$A$2:$A$1801,2026)),0) -> 0.17076041
A40: 37 | B40: SOCIEDAD AGRICOLA 3P S.A.C. | C40: 281500.85 | D40: 500 | E40: 282000.85 | F40: 0.0044608402 | G40: =IFERROR((SUMIFS('Data Cruda'!$P$2:$P$1801,'Data Cruda'!$D$2:$D$1801,"SOCIEDAD AGRICOLA 3P S.A.C.",'Data Cruda'!$A$2:$A$1801,2025)+SUMIFS('Data Cruda'!$P$2:$P$1801,'Data Cruda'!$D$2:$D$1801,"SOCIEDAD AGRICOLA 3P S.A.C.",'Data Cruda'!$A$2:$A$1801,2026))/(SUMIFS('Data Cruda'!$K$2:$K$1801,'Data Cruda'!$D$2:$D$1801,"SOCIEDAD AGRICOLA 3P S.A.C.",'Data Cruda'!$A$2:$A$1801,2025)+SUMIFS('Data Cruda'!$K$2:$K$1801,'Data Cruda'!$D$2:$D$1801,"SOCIEDAD AGRICOLA 3P S.A.C.",'Data Cruda'!$A$2:$A$1801,2026)),0) -> 0.16068063
A41: 38 | B41: AGRICOLA GANADERA LAS CANELAS SAC | C41: 256513.28 | D41: 0 | E41: 256513.28 | F41: 0.0040576642 | G41: =IFERROR((SUMIFS('Data Cruda'!$P$2:$P$1801,'Data Cruda'!$D$2:$D$1801,"AGRICOLA GANADERA LAS CANELAS SAC",'Data Cruda'!$A$2:$A$1801,2025)+SUMIFS('Data Cruda'!$P$2:$P$1801,'Data Cruda'!$D$2:$D$1801,"AGRICOLA GANADERA LAS CANELAS SAC",'Data Cruda'!$A$2:$A$1801,2026))/(SUMIFS('Data Cruda'!$K$2:$K$1801,'Data Cruda'!$D$2:$D$1801,"AGRICOLA GANADERA LAS CANELAS SAC",'Data Cruda'!$A$2:$A$1801,2025)+SUMIFS('Data Cruda'!$K$2:$K$1801,'Data Cruda'!$D$2:$D$1801,"AGRICOLA GANADERA LAS CANELAS SAC",'Data Cruda'!$A$2:$A$1801,2026)),0) -> 0.1458764
A42: 39 | B42: CONSORCIO AGRICOLA MOQUEGUA S.A.C. | C42: 224427.9 | D42: 8240 | E42: 232667.9 | F42: 0.0036804652 | G42: =IFERROR((SUMIFS('Data Cruda'!$P$2:$P$1801,'Data Cruda'!$D$2:$D$1801,"CONSORCIO AGRICOLA MOQUEGUA S.A.C.",'Data Cruda'!$A$2:$A$1801,2025)+SUMIFS('Data Cruda'!$P$2:$P$1801,'Data Cruda'!$D$2:$D$1801,"CONSORCIO AGRICOLA MOQUEGUA S.A.C.",'Data Cruda'!$A$2:$A$1801,2026))/(SUMIFS('Data Cruda'!$K$2:$K$1801,'Data Cruda'!$D$2:$D$1801,"CONSORCIO AGRICOLA MOQUEGUA S.A.C.",'Data Cruda'!$A$2:$A$1801,2025)+SUMIFS('Data Cruda'!$K$2:$K$1801,'Data Cruda'!$D$2:$D$1801,"CONSORCIO AGRICOLA MOQUEGUA S.A.C.",'Data Cruda'!$A$2:$A$1801,2026)),0) -> 0.15369864
A43: 40 | B43: T & T FRUITS S.A. | C43: 0 | D43: 227719.49 | E43: 227719.49 | F43: 0.0036021886 | G43: =IFERROR((SUMIFS('Data Cruda'!$P$2:$P$1801,'Data Cruda'!$D$2:$D$1801,"T & T FRUITS S.A.",'Data Cruda'!$A$2:$A$1801,2025)+SUMIFS('Data Cruda'!$P$2:$P$1801,'Data Cruda'!$D$2:$D$1801,"T & T FRUITS S.A.",'Data Cruda'!$A$2:$A$1801,2026))/(SUMIFS('Data Cruda'!$K$2:$K$1801,'Data Cruda'!$D$2:$D$1801,"T & T FRUITS S.A.",'Data Cruda'!$A$2:$A$1801,2025)+SUMIFS('Data Cruda'!$K$2:$K$1801,'Data Cruda'!$D$2:$D$1801,"T & T FRUITS S.A.",'Data Cruda'!$A$2:$A$1801,2026)),0) -> 0.13892171
A44: 41 | B44: SAN EFISIO S.A.C. | C44: 226880.03 | D44: 0 | E44: 226880.03 | F44: 0.0035889096 | G44: =IFERROR((SUMIFS('Data Cruda'!$P$2:$P$1801,'Data Cruda'!$D$2:$D$1801,"SAN EFISIO S.A.C.",'Data Cruda'!$A$2:$A$1801,2025)+SUMIFS('Data Cruda'!$P$2:$P$1801,'Data Cruda'!$D$2:$D$1801,"SAN EFISIO S.A.C.",'Data Cruda'!$A$2:$A$1801,2026))/(SUMIFS('Data Cruda'!$K$2:$K$1801,'Data Cruda'!$D$2:$D$1801,"SAN EFISIO S.A.C.",'Data Cruda'!$A$2:$A$1801,2025)+SUMIFS('Data Cruda'!$K$2:$K$1801,'Data Cruda'!$D$2:$D$1801,"SAN EFISIO S.A.C.",'Data Cruda'!$A$2:$A$1801,2026)),0) -> 0.19791984
A45: 42 | B45: UNIÓN DE CERVECERÍAS PERUANAS BACKUS Y JOHNSTON SAC | C45: 222254 | D45: 0 | E45: 222254 | F45: 0.0035157326 | G45: =IFERROR((SUMIFS('Data Cruda'!$P$2:$P$1801,'Data Cruda'!$D$2:$D$1801,"UNIÓN DE CERVECERÍAS PERUANAS BACKUS Y JOHNSTON SAC",'Data Cruda'!$A$2:$A$1801,2025)+SUMIFS('Data Cruda'!$P$2:$P$1801,'Data Cruda'!$D$2:$D$1801,"UNIÓN DE CERVECERÍAS PERUANAS BACKUS Y JOHNSTON SAC",'Data Cruda'!$A$2:$A$1801,2026))/(SUMIFS('Data Cruda'!$K$2:$K$1801,'Data Cruda'!$D$2:$D$1801,"UNIÓN DE CERVECERÍAS PERUANAS BACKUS Y JOHNSTON SAC",'Data Cruda'!$A$2:$A$1801,2025)+SUMIFS('Data Cruda'!$K$2:$K$1801,'Data Cruda'!$D$2:$D$1801,"UNIÓN DE CERVECERÍAS PERUANAS BACKUS Y JOHNSTON SAC",'Data Cruda'!$A$2:$A$1801,2026)),0) -> 0.12469998
A46: 43 | B46: VIVEROS EL TAMBO S.A.C. | C46: 0 | D46: 216754.9 | E46: 216754.9 | F46: 0.0034287449 | G46: =IFERROR((SUMIFS('Data Cruda'!$P$2:$P$1801,'Data Cruda'!$D$2:$D$1801,"VIVEROS EL TAMBO S.A.C.",'Data Cruda'!$A$2:$A$1801,2025)+SUMIFS('Data Cruda'!$P$2:$P$1801,'Data Cruda'!$D$2:$D$1801,"VIVEROS EL TAMBO S.A.C.",'Data Cruda'!$A$2:$A$1801,2026))/(SUMIFS('Data Cruda'!$K$2:$K$1801,'Data Cruda'!$D$2:$D$1801,"VIVEROS EL TAMBO S.A.C.",'Data Cruda'!$A$2:$A$1801,2025)+SUMIFS('Data Cruda'!$K$2:$K$1801,'Data Cruda'!$D$2:$D$1801,"VIVEROS EL TAMBO S.A.C.",'Data Cruda'!$A$2:$A$1801,2026)),0) -> 0.19515785
A47: 44 | B47: UNIVERSIDAD FEDERICO HENRIQUEZ Y CARVAJAL | C47: 0 | D47: 206089.67 | E47: 206089.67 | F47: 0.0032600365 | G47: =IFERROR((SUMIFS('Data Cruda'!$P$2:$P$1801,'Data Cruda'!$D$2:$D$1801,"UNIVERSIDAD FEDERICO HENRIQUEZ Y CARVAJAL",'Data Cruda'!$A$2:$A$1801,2025)+SUMIFS('Data Cruda'!$P$2:$P$1801,'Data Cruda'!$D$2:$D$1801,"UNIVERSIDAD FEDERICO HENRIQUEZ Y CARVAJAL",'Data Cruda'!$A$2:$A$1801,2026))/(SUMIFS('Data Cruda'!$K$2:$K$1801,'Data Cruda'!$D$2:$D$1801,"UNIVERSIDAD FEDERICO HENRIQUEZ Y CARVAJAL",'Data Cruda'!$A$2:$A$1801,2025)+SUMIFS('Data Cruda'!$K$2:$K$1801,'Data Cruda'!$D$2:$D$1801,"UNIVERSIDAD FEDERICO HENRIQUEZ Y CARVAJAL",'Data Cruda'!$A$2:$A$1801,2026)),0) -> 0.37198211
A48: 45 | B48: ARCA CONTINENTAL LINDLEY S.A. | C48: 0 | D48: 203678.39 | E48: 203678.39 | F48: 0.0032218936 | G48: =IFERROR((SUMIFS('Data Cruda'!$P$2:$P$1801,'Data Cruda'!$D$2:$D$1801,"ARCA CONTINENTAL LINDLEY S.A.",'Data Cruda'!$A$2:$A$1801,2025)+SUMIFS('Data Cruda'!$P$2:$P$1801,'Data Cruda'!$D$2:$D$1801,"ARCA CONTINENTAL LINDLEY S.A.",'Data Cruda'!$A$2:$A$1801,2026))/(SUMIFS('Data Cruda'!$K$2:$K$1801,'Data Cruda'!$D$2:$D$1801,"ARCA CONTINENTAL LINDLEY S.A.",'Data Cruda'!$A$2:$A$1801,2025)+SUMIFS('Data Cruda'!$K$2:$K$1801,'Data Cruda'!$D$2:$D$1801,"ARCA CONTINENTAL LINDLEY S.A.",'Data Cruda'!$A$2:$A$1801,2026)),0) -> 0.21300257
A49: 46 | B49: EMPRESA AGRICOLA SAN JUAN S.A | C49: 194358.88 | D49: 0 | E49: 194358.88 | F49: 0.0030744727 | G49: =IFERROR((SUMIFS('Data Cruda'!$P$2:$P$1801,'Data Cruda'!$D$2:$D$1801,"EMPRESA AGRICOLA SAN JUAN S.A",'Data Cruda'!$A$2:$A$1801,2025)+SUMIFS('Data Cruda'!$P$2:$P$1801,'Data Cruda'!$D$2:$D$1801,"EMPRESA AGRICOLA SAN JUAN S.A",'Data Cruda'!$A$2:$A$1801,2026))/(SUMIFS('Data Cruda'!$K$2:$K$1801,'Data Cruda'!$D$2:$D$1801,"EMPRESA AGRICOLA SAN JUAN S.A",'Data Cruda'!$A$2:$A$1801,2025)+SUMIFS('Data Cruda'!$K$2:$K$1801,'Data Cruda'!$D$2:$D$1801,"EMPRESA AGRICOLA SAN JUAN S.A",'Data Cruda'!$A$2:$A$1801,2026)),0) -> 0.18937787
A50: 47 | B50: DISTRIBUIDORA EXCLUSIVA DE PRODUCTOS DE CALIDAD SAC | C50: 189851.72 | D50: 0 | E50: 189851.72 | F50: 0.003003176 | G50: =IFERROR((SUMIFS('Data Cruda'!$P$2:$P$1801,'Data Cruda'!$D$2:$D$1801,"DISTRIBUIDORA EXCLUSIVA DE PRODUCTOS DE CALIDAD SAC",'Data Cruda'!$A$2:$A$1801,2025)+SUMIFS('Data Cruda'!$P$2:$P$1801,'Data Cruda'!$D$2:$D$1801,"DISTRIBUIDORA EXCLUSIVA DE PRODUCTOS DE CALIDAD SAC",'Data Cruda'!$A$2:$A$1801,2026))/(SUMIFS('Data Cruda'!$K$2:$K$1801,'Data Cruda'!$D$2:$D$1801,"DISTRIBUIDORA EXCLUSIVA DE PRODUCTOS DE CALIDAD SAC",'Data Cruda'!$A$2:$A$1801,2025)+SUMIFS('Data Cruda'!$K$2:$K$1801,'Data Cruda'!$D$2:$D$1801,"DISTRIBUIDORA EXCLUSIVA DE PRODUCTOS DE CALIDAD SAC",'Data Cruda'!$A$2:$A$1801,2026)),0) -> 0
A51: 48 | B51: FUSION FOODS S.A.C. | C51: 175587.99 | D51: 0 | E51: 175587.99 | F51: 0.0027775447 | G51: =IFERROR((SUMIFS('Data Cruda'!$P$2:$P$1801,'Data Cruda'!$D$2:$D$1801,"FUSION FOODS S.A.C.",'Data Cruda'!$A$2:$A$1801,2025)+SUMIFS('Data Cruda'!$P$2:$P$1801,'Data Cruda'!$D$2:$D$1801,"FUSION FOODS S.A.C.",'Data Cruda'!$A$2:$A$1801,2026))/(SUMIFS('Data Cruda'!$K$2:$K$1801,'Data Cruda'!$D$2:$D$1801,"FUSION FOODS S.A.C.",'Data Cruda'!$A$2:$A$1801,2025)+SUMIFS('Data Cruda'!$K$2:$K$1801,'Data Cruda'!$D$2:$D$1801,"FUSION FOODS S.A.C.",'Data Cruda'!$A$2:$A$1801,2026)),0) -> 0.094202286
A52: 49 | B52: AUSTRAL GROUP S.A.A. | C52: 117308 | D52: 0 | E52: 117308 | F52: 0.0018556406 | G52: =IFERROR((SUMIFS('Data Cruda'!$P$2:$P$1801,'Data Cruda'!$D$2:$D$1801,"AUSTRAL GROUP S.A.A.",'Data Cruda'!$A$2:$A$1801,2025)+SUMIFS('Data Cruda'!$P$2:$P$1801,'Data Cruda'!$D$2:$D$1801,"AUSTRAL GROUP S.A.A.",'Data Cruda'!$A$2:$A$1801,2026))/(SUMIFS('Data Cruda'!$K$2:$K$1801,'Data Cruda'!$D$2:$D$1801,"AUSTRAL GROUP S.A.A.",'Data Cruda'!$A$2:$A$1801,2025)+SUMIFS('Data Cruda'!$K$2:$K$1801,'Data Cruda'!$D$2:$D$1801,"AUSTRAL GROUP S.A.A.",'Data Cruda'!$A$2:$A$1801,2026)),0) -> 0
A53: 50 | B53: REITER PERUVIAN BERRY S.A. | C53: 0 | D53: 110710 | E53: 110710 | F53: 0.00175127 | G53: =IFERROR((SUMIFS('Data Cruda'!$P$2:$P$1801,'Data Cruda'!$D$2:$D$1801,"REITER PERUVIAN BERRY S.A.",'Data Cruda'!$A$2:$A$1801,2025)+SUMIFS('Data Cruda'!$P$2:$P$1801,'Data Cruda'!$D$2:$D$1801,"REITER PERUVIAN BERRY S.A.",'Data Cruda'!$A$2:$A$1801,2026))/(SUMIFS('Data Cruda'!$K$2:$K$1801,'Data Cruda'!$D$2:$D$1801,"REITER PERUVIAN BERRY S.A.",'Data Cruda'!$A$2:$A$1801,2025)+SUMIFS('Data Cruda'!$K$2:$K$1801,'Data Cruda'!$D$2:$D$1801,"REITER PERUVIAN BERRY S.A.",'Data Cruda'!$A$2:$A$1801,2026)),0) -> 0.14169352
A54: 51 | B54: AGRICOLA HUARMEY S.A.C. | C54: 0 | D54: 106047.18 | E54: 106047.18 | F54: 0.001677511 | G54: =IFERROR((SUMIFS('Data Cruda'!$P$2:$P$1801,'Data Cruda'!$D$2:$D$1801,"AGRICOLA HUARMEY S.A.C.",'Data Cruda'!$A$2:$A$1801,2025)+SUMIFS('Data Cruda'!$P$2:$P$1801,'Data Cruda'!$D$2:$D$1801,"AGRICOLA HUARMEY S.A.C.",'Data Cruda'!$A$2:$A$1801,2026))/(SUMIFS('Data Cruda'!$K$2:$K$1801,'Data Cruda'!$D$2:$D$1801,"AGRICOLA HUARMEY S.A.C.",'Data Cruda'!$A$2:$A$1801,2025)+SUMIFS('Data Cruda'!$K$2:$K$1801,'Data Cruda'!$D$2:$D$1801,"AGRICOLA HUARMEY S.A.C.",'Data Cruda'!$A$2:$A$1801,2026)),0) -> 0.17593716
A55: 52 | B55: INGENIERIA EN CARTONES Y PAPELES S.A.C | C55: 0 | D55: 101933.16 | E55: 101933.16 | F55: 0.0016124332 | G55: =IFERROR((SUMIFS('Data Cruda'!$P$2:$P$1801,'Data Cruda'!$D$2:$D$1801,"INGENIERIA EN CARTONES Y PAPELES S.A.C",'Data Cruda'!$A$2:$A$1801,2025)+SUMIFS('Data Cruda'!$P$2:$P$1801,'Data Cruda'!$D$2:$D$1801,"INGENIERIA EN CARTONES Y PAPELES S.A.C",'Data Cruda'!$A$2:$A$1801,2026))/(SUMIFS('Data Cruda'!$K$2:$K$1801,'Data Cruda'!$D$2:$D$1801,"INGENIERIA EN CARTONES Y PAPELES S.A.C",'Data Cruda'!$A$2:$A$1801,2025)+SUMIFS('Data Cruda'!$K$2:$K$1801,'Data Cruda'!$D$2:$D$1801,"INGENIERIA EN CARTONES Y PAPELES S.A.C",'Data Cruda'!$A$2:$A$1801,2026)),0) -> 0.20033363
A56: 53 | B56: IN VITRO LAB PERU S.A.C | C56: 99000 | D56: 0 | E56: 99000 | F56: 0.0015660349 | G56: =IFERROR((SUMIFS('Data Cruda'!$P$2:$P$1801,'Data Cruda'!$D$2:$D$1801,"IN VITRO LAB PERU S.A.C",'Data Cruda'!$A$2:$A$1801,2025)+SUMIFS('Data Cruda'!$P$2:$P$1801,'Data Cruda'!$D$2:$D$1801,"IN VITRO LAB PERU S.A.C",'Data Cruda'!$A$2:$A$1801,2026))/(SUMIFS('Data Cruda'!$K$2:$K$1801,'Data Cruda'!$D$2:$D$1801,"IN VITRO LAB PERU S.A.C",'Data Cruda'!$A$2:$A$1801,2025)+SUMIFS('Data Cruda'!$K$2:$K$1801,'Data Cruda'!$D$2:$D$1801,"IN VITRO LAB PERU S.A.C",'Data Cruda'!$A$2:$A$1801,2026)),0) -> 0.3
A57: 54 | B57: QBERRIES SAC | C57: 96847.02 | D57: 0 | E57: 96847.02 | F57: 0.0015319779 | G57: =IFERROR((SUMIFS('Data Cruda'!$P$2:$P$1801,'Data Cruda'!$D$2:$D$1801,"QBERRIES SAC",'Data Cruda'!$A$2:$A$1801,2025)+SUMIFS('Data Cruda'!$P$2:$P$1801,'Data Cruda'!$D$2:$D$1801,"QBERRIES SAC",'Data Cruda'!$A$2:$A$1801,2026))/(SUMIFS('Data Cruda'!$K$2:$K$1801,'Data Cruda'!$D$2:$D$1801,"QBERRIES SAC",'Data Cruda'!$A$2:$A$1801,2025)+SUMIFS('Data Cruda'!$K$2:$K$1801,'Data Cruda'!$D$2:$D$1801,"QBERRIES SAC",'Data Cruda'!$A$2:$A$1801,2026)),0) -> 0.3
A58: 55 | B58: SMART PACKING S.A.C. | C58: 0 | D58: 77696.99 | E58: 77696.99 | F58: 0.0012290525 | G58: =IFERROR((SUMIFS('Data Cruda'!$P$2:$P$1801,'Data Cruda'!$D$2:$D$1801,"SMART PACKING S.A.C.",'Data Cruda'!$A$2:$A$1801,2025)+SUMIFS('Data Cruda'!$P$2:$P$1801,'Data Cruda'!$D$2:$D$1801,"SMART PACKING S.A.C.",'Data Cruda'!$A$2:$A$1801,2026))/(SUMIFS('Data Cruda'!$K$2:$K$1801,'Data Cruda'!$D$2:$D$1801,"SMART PACKING S.A.C.",'Data Cruda'!$A$2:$A$1801,2025)+SUMIFS('Data Cruda'!$K$2:$K$1801,'Data Cruda'!$D$2:$D$1801,"SMART PACKING S.A.C.",'Data Cruda'!$A$2:$A$1801,2026)),0) -> 0.14254606
A59: 56 | B59: FLORISERT S.A.C. | C59: 0 | D59: 61715.57 | E59: 61715.57 | F59: 0.00097624987 | G59: =IFERROR((SUMIFS('Data Cruda'!$P$2:$P$1801,'Data Cruda'!$D$2:$D$1801,"FLORISERT S.A.C.",'Data Cruda'!$A$2:$A$1801,2025)+SUMIFS('Data Cruda'!$P$2:$P$1801,'Data Cruda'!$D$2:$D$1801,"FLORISERT S.A.C.",'Data Cruda'!$A$2:$A$1801,2026))/(SUMIFS('Data Cruda'!$K$2:$K$1801,'Data Cruda'!$D$2:$D$1801,"FLORISERT S.A.C.",'Data Cruda'!$A$2:$A$1801,2025)+SUMIFS('Data Cruda'!$K$2:$K$1801,'Data Cruda'!$D$2:$D$1801,"FLORISERT S.A.C.",'Data Cruda'!$A$2:$A$1801,2026)),0) -> 0.1684186
A60: 57 | B60: LOS OLIVOS DE VILLACURI S.A.C. | C60: 50827.6 | D60: 0 | E60: 50827.6 | F60: 0.00080401814 | G60: =IFERROR((SUMIFS('Data Cruda'!$P$2:$P$1801,'Data Cruda'!$D$2:$D$1801,"LOS OLIVOS DE VILLACURI S.A.C.",'Data Cruda'!$A$2:$A$1801,2025)+SUMIFS('Data Cruda'!$P$2:$P$1801,'Data Cruda'!$D$2:$D$1801,"LOS OLIVOS DE VILLACURI S.A.C.",'Data Cruda'!$A$2:$A$1801,2026))/(SUMIFS('Data Cruda'!$K$2:$K$1801,'Data Cruda'!$D$2:$D$1801,"LOS OLIVOS DE VILLACURI S.A.C.",'Data Cruda'!$A$2:$A$1801,2025)+SUMIFS('Data Cruda'!$K$2:$K$1801,'Data Cruda'!$D$2:$D$1801,"LOS OLIVOS DE VILLACURI S.A.C.",'Data Cruda'!$A$2:$A$1801,2026)),0) -> 0.24678482
A61: 58 | B61: FAMILY FARMS PERÚ S.R.L. | C61: 48530.23 | D61: 0 | E61: 48530.23 | F61: 0.00076767712 | G61: =IFERROR((SUMIFS('Data Cruda'!$P$2:$P$1801,'Data Cruda'!$D$2:$D$1801,"FAMILY FARMS PERÚ S.R.L.",'Data Cruda'!$A$2:$A$1801,2025)+SUMIFS('Data Cruda'!$P$2:$P$1801,'Data Cruda'!$D$2:$D$1801,"FAMILY FARMS PERÚ S.R.L.",'Data Cruda'!$A$2:$A$1801,2026))/(SUMIFS('Data Cruda'!$K$2:$K$1801,'Data Cruda'!$D$2:$D$1801,"FAMILY FARMS PERÚ S.R.L.",'Data Cruda'!$A$2:$A$1801,2025)+SUMIFS('Data Cruda'!$K$2:$K$1801,'Data Cruda'!$D$2:$D$1801,"FAMILY FARMS PERÚ S.R.L.",'Data Cruda'!$A$2:$A$1801,2026)),0) -> 0.13226354
A62: 59 | B62: ALZA PERU PACKING S.A.C. | C62: 43600.44 | D62: 0 | E62: 43600.44 | F62: 0.00068969506 | G62: =IFERROR((SUMIFS('Data Cruda'!$P$2:$P$1801,'Data Cruda'!$D$2:$D$1801,"ALZA PERU PACKING S.A.C.",'Data Cruda'!$A$2:$A$1801,2025)+SUMIFS('Data Cruda'!$P$2:$P$1801,'Data Cruda'!$D$2:$D$1801,"ALZA PERU PACKING S.A.C.",'Data Cruda'!$A$2:$A$1801,2026))/(SUMIFS('Data Cruda'!$K$2:$K$1801,'Data Cruda'!$D$2:$D$1801,"ALZA PERU PACKING S.A.C.",'Data Cruda'!$A$2:$A$1801,2025)+SUMIFS('Data Cruda'!$K$2:$K$1801,'Data Cruda'!$D$2:$D$1801,"ALZA PERU PACKING S.A.C.",'Data Cruda'!$A$2:$A$1801,2026)),0) -> 0.15
A63: 60 | B63: VITAFOODS PERU S.A.C. | C63: 0 | D63: 43470 | E63: 43470 | F63: 0.00068763169 | G63: =IFERROR((SUMIFS('Data Cruda'!$P$2:$P$1801,'Data Cruda'!$D$2:$D$1801,"VITAFOODS PERU S.A.C.",'Data Cruda'!$A$2:$A$1801,2025)+SUMIFS('Data Cruda'!$P$2:$P$1801,'Data Cruda'!$D$2:$D$1801,"VITAFOODS PERU S.A.C.",'Data Cruda'!$A$2:$A$1801,2026))/(SUMIFS('Data Cruda'!$K$2:$K$1801,'Data Cruda'!$D$2:$D$1801,"VITAFOODS PERU S.A.C.",'Data Cruda'!$A$2:$A$1801,2025)+SUMIFS('Data Cruda'!$K$2:$K$1801,'Data Cruda'!$D$2:$D$1801,"VITAFOODS PERU S.A.C.",'Data Cruda'!$A$2:$A$1801,2026)),0) -> 0.27075339
A64: 61 | B64: EL ROCIO S.A. | C64: 36681.15 | D64: 890 | E64: 37571.15 | F64: 0.00059432053 | G64: =IFERROR((SUMIFS('Data Cruda'!$P$2:$P$1801,'Data Cruda'!$D$2:$D$1801,"EL ROCIO S.A.",'Data Cruda'!$A$2:$A$1801,2025)+SUMIFS('Data Cruda'!$P$2:$P$1801,'Data Cruda'!$D$2:$D$1801,"EL ROCIO S.A.",'Data Cruda'!$A$2:$A$1801,2026))/(SUMIFS('Data Cruda'!$K$2:$K$1801,'Data Cruda'!$D$2:$D$1801,"EL ROCIO S.A.",'Data Cruda'!$A$2:$A$1801,2025)+SUMIFS('Data Cruda'!$K$2:$K$1801,'Data Cruda'!$D$2:$D$1801,"EL ROCIO S.A.",'Data Cruda'!$A$2:$A$1801,2026)),0) -> 0.056551144
A65: 62 | B65: PACKING DEL CARMEN S.A.C. | C65: 0 | D65: 36347.87 | E65: 36347.87 | F65: 0.00057497003 | G65: =IFERROR((SUMIFS('Data Cruda'!$P$2:$P$1801,'Data Cruda'!$D$2:$D$1801,"PACKING DEL CARMEN S.A.C.",'Data Cruda'!$A$2:$A$1801,2025)+SUMIFS('Data Cruda'!$P$2:$P$1801,'Data Cruda'!$D$2:$D$1801,"PACKING DEL CARMEN S.A.C.",'Data Cruda'!$A$2:$A$1801,2026))/(SUMIFS('Data Cruda'!$K$2:$K$1801,'Data Cruda'!$D$2:$D$1801,"PACKING DEL CARMEN S.A.C.",'Data Cruda'!$A$2:$A$1801,2025)+SUMIFS('Data Cruda'!$K$2:$K$1801,'Data Cruda'!$D$2:$D$1801,"PACKING DEL CARMEN S.A.C.",'Data Cruda'!$A$2:$A$1801,2026)),0) -> 0.17642327
A66: 63 | B66: ARA EXPORT S.A.C. | C66: 34403.05 | D66: 0 | E66: 34403.05 | F66: 0.00054420583 | G66: =IFERROR((SUMIFS('Data Cruda'!$P$2:$P$1801,'Data Cruda'!$D$2:$D$1801,"ARA EXPORT S.A.C.",'Data Cruda'!$A$2:$A$1801,2025)+SUMIFS('Data Cruda'!$P$2:$P$1801,'Data Cruda'!$D$2:$D$1801,"ARA EXPORT S.A.C.",'Data Cruda'!$A$2:$A$1801,2026))/(SUMIFS('Data Cruda'!$K$2:$K$1801,'Data Cruda'!$D$2:$D$1801,"ARA EXPORT S.A.C.",'Data Cruda'!$A$2:$A$1801,2025)+SUMIFS('Data Cruda'!$K$2:$K$1801,'Data Cruda'!$D$2:$D$1801,"ARA EXPORT S.A.C.",'Data Cruda'!$A$2:$A$1801,2026)),0) -> 0.15388607
A67: 64 | B67: UVICA S.A.C. | C67: 32800.01 | D67: 798 | E67: 33598.01 | F67: 0.00053147128 | G67: =IFERROR((SUMIFS('Data Cruda'!$P$2:$P$1801,'Data Cruda'!$D$2:$D$1801,"UVICA S.A.C.",'Data Cruda'!$A$2:$A$1801,2025)+SUMIFS('Data Cruda'!$P$2:$P$1801,'Data Cruda'!$D$2:$D$1801,"UVICA S.A.C.",'Data Cruda'!$A$2:$A$1801,2026))/(SUMIFS('Data Cruda'!$K$2:$K$1801,'Data Cruda'!$D$2:$D$1801,"UVICA S.A.C.",'Data Cruda'!$A$2:$A$1801,2025)+SUMIFS('Data Cruda'!$K$2:$K$1801,'Data Cruda'!$D$2:$D$1801,"UVICA S.A.C.",'Data Cruda'!$A$2:$A$1801,2026)),0) -> 0.1571471
A68: 65 | B68: QUELEN FRUIT PERU S.A.C. | C68: 25500 | D68: 0 | E68: 25500 | F68: 0.00040337263 | G68: =IFERROR((SUMIFS('Data Cruda'!$P$2:$P$1801,'Data Cruda'!$D$2:$D$1801,"QUELEN FRUIT PERU S.A.C.",'Data Cruda'!$A$2:$A$1801,2025)+SUMIFS('Data Cruda'!$P$2:$P$1801,'Data Cruda'!$D$2:$D$1801,"QUELEN FRUIT PERU S.A.C.",'Data Cruda'!$A$2:$A$1801,2026))/(SUMIFS('Data Cruda'!$K$2:$K$1801,'Data Cruda'!$D$2:$D$1801,"QUELEN FRUIT PERU S.A.C.",'Data Cruda'!$A$2:$A$1801,2025)+SUMIFS('Data Cruda'!$K$2:$K$1801,'Data Cruda'!$D$2:$D$1801,"QUELEN FRUIT PERU S.A.C.",'Data Cruda'!$A$2:$A$1801,2026)),0) -> 0.15
A69: 66 | B69: TAL S A | C69: 0 | D69: 17671.66 | E69: 17671.66 | F69: 0.00027953976 | G69: =IFERROR((SUMIFS('Data Cruda'!$P$2:$P$1801,'Data Cruda'!$D$2:$D$1801,"TAL S A",'Data Cruda'!$A$2:$A$1801,2025)+SUMIFS('Data Cruda'!$P$2:$P$1801,'Data Cruda'!$D$2:$D$1801,"TAL S A",'Data Cruda'!$A$2:$A$1801,2026))/(SUMIFS('Data Cruda'!$K$2:$K$1801,'Data Cruda'!$D$2:$D$1801,"TAL S A",'Data Cruda'!$A$2:$A$1801,2025)+SUMIFS('Data Cruda'!$K$2:$K$1801,'Data Cruda'!$D$2:$D$1801,"TAL S A",'Data Cruda'!$A$2:$A$1801,2026)),0) -> 0.24999972
A70: 67 | B70: EL PARQUE ALAYA PACKING S.A.C. | C70: 0 | D70: 15941.32 | E70: 15941.32 | F70: 0.00025216832 | G70: =IFERROR((SUMIFS('Data Cruda'!$P$2:$P$1801,'Data Cruda'!$D$2:$D$1801,"EL PARQUE ALAYA PACKING S.A.C.",'Data Cruda'!$A$2:$A$1801,2025)+SUMIFS('Data Cruda'!$P$2:$P$1801,'Data Cruda'!$D$2:$D$1801,"EL PARQUE ALAYA PACKING S.A.C.",'Data Cruda'!$A$2:$A$1801,2026))/(SUMIFS('Data Cruda'!$K$2:$K$1801,'Data Cruda'!$D$2:$D$1801,"EL PARQUE ALAYA PACKING S.A.C.",'Data Cruda'!$A$2:$A$1801,2025)+SUMIFS('Data Cruda'!$K$2:$K$1801,'Data Cruda'!$D$2:$D$1801,"EL PARQUE ALAYA PACKING S.A.C.",'Data Cruda'!$A$2:$A$1801,2026)),0) -> 0.13555465
A71: 68 | B71: WESTFALIA FRUIT PERU S.A.C. | C71: 10000 | D71: 0 | E71: 10000 | F71: 0.00015818534 | G71: =IFERROR((SUMIFS('Data Cruda'!$P$2:$P$1801,'Data Cruda'!$D$2:$D$1801,"WESTFALIA FRUIT PERU S.A.C.",'Data Cruda'!$A$2:$A$1801,2025)+SUMIFS('Data Cruda'!$P$2:$P$1801,'Data Cruda'!$D$2:$D$1801,"WESTFALIA FRUIT PERU S.A.C.",'Data Cruda'!$A$2:$A$1801,2026))/(SUMIFS('Data Cruda'!$K$2:$K$1801,'Data Cruda'!$D$2:$D$1801,"WESTFALIA FRUIT PERU S.A.C.",'Data Cruda'!$A$2:$A$1801,2025)+SUMIFS('Data Cruda'!$K$2:$K$1801,'Data Cruda'!$D$2:$D$1801,"WESTFALIA FRUIT PERU S.A.C.",'Data Cruda'!$A$2:$A$1801,2026)),0) -> 0.3
A72: 69 | B72: CIA.DE EXP.Y NEGOCIOS GNRLES.S.A.(COEXA) | C72: 0 | D72: 6840.69 | E72: 6840.69 | F72: 0.00010820969 | G72: =IFERROR((SUMIFS('Data Cruda'!$P$2:$P$1801,'Data Cruda'!$D$2:$D$1801,"CIA.DE EXP.Y NEGOCIOS GNRLES.S.A.(COEXA)",'Data Cruda'!$A$2:$A$1801,2025)+SUMIFS('Data Cruda'!$P$2:$P$1801,'Data Cruda'!$D$2:$D$1801,"CIA.DE EXP.Y NEGOCIOS GNRLES.S.A.(COEXA)",'Data Cruda'!$A$2:$A$1801,2026))/(SUMIFS('Data Cruda'!$K$2:$K$1801,'Data Cruda'!$D$2:$D$1801,"CIA.DE EXP.Y NEGOCIOS GNRLES.S.A.(COEXA)",'Data Cruda'!$A$2:$A$1801,2025)+SUMIFS('Data Cruda'!$K$2:$K$1801,'Data Cruda'!$D$2:$D$1801,"CIA.DE EXP.Y NEGOCIOS GNRLES.S.A.(COEXA)",'Data Cruda'!$A$2:$A$1801,2026)),0) -> 0.080648297
A73: 70 | B73: AVOCADO PACKING COMPANY S.A.C. | C73: 4392.39 | D73: 0 | E73: 4392.39 | F73: 6.9481173e-05 | G73: =IFERROR((SUMIFS('Data Cruda'!$P$2:$P$1801,'Data Cruda'!$D$2:$D$1801,"AVOCADO PACKING COMPANY S.A.C.",'Data Cruda'!$A$2:$A$1801,2025)+SUMIFS('Data Cruda'!$P$2:$P$1801,'Data Cruda'!$D$2:$D$1801,"AVOCADO PACKING COMPANY S.A.C.",'Data Cruda'!$A$2:$A$1801,2026))/(SUMIFS('Data Cruda'!$K$2:$K$1801,'Data Cruda'!$D$2:$D$1801,"AVOCADO PACKING COMPANY S.A.C.",'Data Cruda'!$A$2:$A$1801,2025)+SUMIFS('Data Cruda'!$K$2:$K$1801,'Data Cruda'!$D$2:$D$1801,"AVOCADO PACKING COMPANY S.A.C.",'Data Cruda'!$A$2:$A$1801,2026)),0) -> 0.19856843
A74: 71 | B74: AGRICOLA BLUE GOLD S.A.C. | C74: 4265.26 | D74: 0 | E74: 4265.26 | F74: 6.7470162e-05 | G74: =IFERROR((SUMIFS('Data Cruda'!$P$2:$P$1801,'Data Cruda'!$D$2:$D$1801,"AGRICOLA BLUE GOLD S.A.C.",'Data Cruda'!$A$2:$A$1801,2025)+SUMIFS('Data Cruda'!$P$2:$P$1801,'Data Cruda'!$D$2:$D$1801,"AGRICOLA BLUE GOLD S.A.C.",'Data Cruda'!$A$2:$A$1801,2026))/(SUMIFS('Data Cruda'!$K$2:$K$1801,'Data Cruda'!$D$2:$D$1801,"AGRICOLA BLUE GOLD S.A.C.",'Data Cruda'!$A$2:$A$1801,2025)+SUMIFS('Data Cruda'!$K$2:$K$1801,'Data Cruda'!$D$2:$D$1801,"AGRICOLA BLUE GOLD S.A.C.",'Data Cruda'!$A$2:$A$1801,2026)),0) -> 0.25209718
A75: 72 | B75: AUSTRAL GROUP S.A.A | C75: 0 | D75: 2310 | E75: 2310 | F75: 3.6540815e-05 | G75: =IFERROR((SUMIFS('Data Cruda'!$P$2:$P$1801,'Data Cruda'!$D$2:$D$1801,"AUSTRAL GROUP S.A.A",'Data Cruda'!$A$2:$A$1801,2025)+SUMIFS('Data Cruda'!$P$2:$P$1801,'Data Cruda'!$D$2:$D$1801,"AUSTRAL GROUP S.A.A",'Data Cruda'!$A$2:$A$1801,2026))/(SUMIFS('Data Cruda'!$K$2:$K$1801,'Data Cruda'!$D$2:$D$1801,"AUSTRAL GROUP S.A.A",'Data Cruda'!$A$2:$A$1801,2025)+SUMIFS('Data Cruda'!$K$2:$K$1801,'Data Cruda'!$D$2:$D$1801,"AUSTRAL GROUP S.A.A",'Data Cruda'!$A$2:$A$1801,2026)),0) -> 0.12941991
A76: 73 | B76: STEELSER S.A.C. | C76: 2200 | D76: 0 | E76: 2200 | F76: 3.4800776e-05 | G76: =IFERROR((SUMIFS('Data Cruda'!$P$2:$P$1801,'Data Cruda'!$D$2:$D$1801,"STEELSER S.A.C.",'Data Cruda'!$A$2:$A$1801,2025)+SUMIFS('Data Cruda'!$P$2:$P$1801,'Data Cruda'!$D$2:$D$1801,"STEELSER S.A.C.",'Data Cruda'!$A$2:$A$1801,2026))/(SUMIFS('Data Cruda'!$K$2:$K$1801,'Data Cruda'!$D$2:$D$1801,"STEELSER S.A.C.",'Data Cruda'!$A$2:$A$1801,2025)+SUMIFS('Data Cruda'!$K$2:$K$1801,'Data Cruda'!$D$2:$D$1801,"STEELSER S.A.C.",'Data Cruda'!$A$2:$A$1801,2026)),0) -> 0.19003182
B77: TOTAL | C77: 34956324 | D77: 28260657 | E77: 63216981 | F77: 1 | G77: =IFERROR((SUMIFS('Data Cruda'!$P$2:$P$1801,'Data Cruda'!$A$2:$A$1801,2025)+SUMIFS('Data Cruda'!$P$2:$P$1801,'Data Cruda'!$A$2:$A$1801,2026))/(SUMIFS('Data Cruda'!$K$2:$K$1801,'Data Cruda'!$A$2:$A$1801,2025)+SUMIFS('Data Cruda'!$K$2:$K$1801,'Data Cruda'!$A$2:$A$1801,2026)),0) -> 0.15750372
A80: TABLA 2 – CLIENTES NUEVOS 2025-2026 (PRIMERA VEZ EN CARTERA)
A82: # | B82: Cliente | C82: Año Ingreso | D82: Monto | E82: Zona | F82: Sector
A83: 1 | B83: AGROBERRIES PERU S.A.C. | C83: 2026 | D83: 10141560 | E83: NORTE | F83: ARANDANOS
A84: 2 | B84: PROSEMBRA SOCIEDAD ANONIMA CERRADA | C84: 2025 | D84: 3632242.2 | E84: SUR | F84: ARANDANOS
A85: 3 | B85: Q PACK S.A.C. | C85: 2025 | D85: 2949135.6 | E85: NORTE | F85: ARANDANOS
A86: 4 | B86: PROCESOS AGROINDUSTRIALES SOCIEDAD ANONIMA | C86: 2026 | D86: 2034100.6 | E86: SUR | F86: UVA
A87: 5 | B87: TA EXPORT S.A.C. | C87: 2026 | D87: 1460000 | E87: SUR | F87: ARANDANOS
A88: 6 | B88: ARA FOODS INDUSTRY S.A.C. | C88: 2025 | D88: 905597.47 | E88: NORTE | F88: PALTA
A89: 7 | B89: IMBAREX S.A. | C89: 2025 | D89: 853450 | E89: SUR | F89: ARANDANOS
A90: 8 | B90: AGROINDUSTRIA FRUTOS DE ORO S.A.C. | C90: 2025 | D90: 508072.36 | E90: NORTE | F90: MANGO
A91: 9 | B91: ESTANTERIAS METALICAS J.R.M. S.A.C | C91: 2026 | D91: 455000 | E91: SUR | F91: OTROS
A92: 10 | B92: DELICE S.A.C | C92: 2025 | D92: 427469.32 | E92: CENTRO | F92: QUESO
A93: 11 | B93: BERRY HARVEST S.A. | C93: 2025 | D93: 402750.72 | E93: NORTE | F93: OTROS
A94: 12 | B94: DIAMOND BRIDGE SAC | C94: 2025 | D94: 321860.28 | E94: SUR | F94: ARANDANOS
... A116: 34 | B116: STEELSER S.A.C. | C116: 2025 | D116: 2200 | E116: NORTE | F116: OTROS
B117: Total Nuevos (34) | D117: 26751801 | F117: 0.42317429

Sheet 4. Top Clientes
A1: TABLA 1 – CLIENTES ÚNICOS TOTALES
A3: Total Clientes Únicos (2014-2026): | B3: 255
A5: Año | B5: Clientes Activos | C5: Monto Total | D5: Ticket Promedio
A6: 2014 | B6: 87 | C6: 14220367 | D6: 163452.49
A7: 2015 | B7: 42 | C7: 10355990 | D7: 246571.2
A8: 2016 | B8: 42 | C8: 13090132 | D8: 311669.81
A9: 2017 | B9: 53 | C9: 12892019 | D9: 243245.64
A10: 2018 | B10: 47 | C10: 22696033 | D10: 482894.32
A11: 2019 | B11: 43 | C11: 13980477 | D11: 325127.37
A12: 2020 | B12: 53 | C12: 20124783 | D12: 379712.88
A13: 2021 | B13: 55 | C13: 20310541 | D13: 369282.57
A14: 2022 | B14: 51 | C14: 33199765 | D14: 650975.78
A15: 2023 | B15: 41 | C15: 15289375 | D15: 372911.58
A16: 2024 | B16: 46 | C16: 15451149 | D16: 335894.55
A17: 2025 | B17: 49 | C17: 34956324 | D17: 713394.38
A18: 2026 | B18: 46 | C18: 28260657 | D18: 614362.11
A19: TOTAL | B19: 255 | C19: 2.5482761e+08 | D19: 999323.97
A22: TABLA 2 – TOP 20 CLIENTES HISTÓRICO (2014-2026)
A24: Ranking | B24: Cliente | C24: Monto Histórico | D24: % Total General | E24: Años Activo | F24: Último Año
A25: 1 | B25: CORPORACION AGROLATINA S.A.C. | C25: 14074374 | D25: 0.055230961 | E25: 10 | F25: 2026
A26: 2 | B26: AGROVISION PERU S.A.C. | C26: 12027997 | D26: 0.047200526 | E26: 9 | F26: 2025
A27: 3 | B27: DANPER TRUJILLO S.A.C. | C27: 11318013 | D27: 0.04441439 | E27: 12 | F27: 2026
A28: 4 | B28: VIRU S.A. | C28: 10204953 | D28: 0.040046496 | E28: 10 | F28: 2025
A29: 5 | B29: AGROBERRIES PERU S.A.C. | C29: 10141560 | D29: 0.039797728 | E29: 1 | F29: 2026
A30: 6 | B30: SOCIEDAD AGRICOLA DROKASA S.A. | C30: 10047517 | D30: 0.039428682 | E30: 12 | F30: 2026
A31: 7 | B31: TAL S.A. | C31: 7592460.4 | D31: 0.029794496 | E31: 10 | F31: 2026
A32: 8 | B32: AQU ANQA S.A.C. | C32: 7494665.7 | D32: 0.029410729 | E32: 5 | F32: 2026
A33: 9 | B33: LOS OLIVOS DE VILLACURI S.A.C. | C33: 6191500.6 | D33: 0.02429682 | E33: 8 | F33: 2025
A34: 10 | B34: AGRICOLA ALAYA SOCIEDAD ANONIMA CERRADA | C34: 5993440.9 | D34: 0.02351959 | E34: 4 | F34: 2025
A35: 11 | B35: BOMAREA S.R.L. | C35: 5621736.4 | D35: 0.022060939 | E35: 2 | F35: 2026
A36: 12 | B36: AGROCASAGRANDE S.A.C. | C36: 5187381.9 | D36: 0.020356436 | E36: 6 | F36: 2025
... A44: 20 | B44: PROSEMBRA SOCIEDAD ANONIMA CERRADA | C44: 3632242.2 | D44: 0.014253723 | E44: 2 | F44: 2026
B45: Total Top 20 | C45: 1.3981291e+08 | D45: 0.54865682
A48: TABLA 3 – TOP 20 CLIENTES 2025-2026
A50: Ranking | B50: Cliente | C50: Monto 25-26 | D50: % Total 25-26 | E50: Zona | F50: ¿Nuevo?
A51: 1 | B51: AGROBERRIES PERU S.A.C. | C51: 10141560 | D51: 0.16042462 | E51: NORTE | F51: SÍ
A52: 2 | B52: DANPER TRUJILLO S.A.C. | C52: 4485901 | D52: 0.07096038 | E52: NORTE | F52: NO
A53: 3 | B53: CORPORACION AGROLATINA S.A.C. | C53: 4450000 | D53: 0.070392478 | E53: SUR | F53: NO
A54: 4 | B54: AGRICOLA HUARMEY S.A. | C54: 4008997 | D54: 0.063416458 | E54: NORTE | F54: NO
A55: 5 | B55: PROSEMBRA SOCIEDAD ANONIMA CERRADA | C55: 3632242.2 | D55: 0.057456749 | E55: SUR | F55: SÍ
A56: 6 | B56: AQU ANQA S.A.C. | C56: 3356000.7 | D56: 0.053087013 | E56: NORTE | F56: NO
A57: 7 | B57: BOMAREA S.R.L. | C57: 3162368.8 | D57: 0.050024039 | E57: NORTE | F57: NO
A58: 8 | B58: Q PACK S.A.C. | C58: 2949135.6 | D58: 0.046651004 | E58: NORTE | F58: SÍ
A59: 9 | B59: TAL S.A. | C59: 2072732.8 | D59: 0.032787595 | E59: NORTE | F59: NO
A60: 10 | B60: PROCESOS AGROINDUSTRIALES SOCIEDAD ANONIMA | C60: 2034100.6 | D60: 0.03217649 | E60: SUR | F60: SÍ
A61: 11 | B61: SOCIEDAD AGRICOLA DROKASA S.A. | C61: 1629602.3 | D61: 0.025777921 | E61: SUR | F61: NO
A62: 12 | B62: AGRICOLA ALAYA SOCIEDAD ANONIMA CERRADA | C62: 1490360.7 | D62: 0.023575322 | E62: NORTE | F62: NO
... A70: 20 | B70: AGROVISION PERU S.A.C. | C70: 817031.34 | D70: 0.012924238 | E70: NORTE | F70: NO
B71: Total Top 20 | C71: 51627658 | D71: 0.81667389

Sheet 5. Categorías Monto
A1: CATEGORÍAS POR MONTO FACTURADO 2025-2026
A3: Categoría | B3: # Clientes | C3: Monto Total | D3: % Particip. | E3: Margen Pond.
A4: Platinum | B4: 15 | C4: 47185945 | D4: 0.7464125 | E4: =IFERROR(SUMPRODUCT(C11:C25,E11:E25)/SUM(C11:C25),0) -> 0.15474939
A5: Gold | B5: 23 | C5: 12746466 | D5: 0.20163041 | E5: =IFERROR(SUMPRODUCT(C30:C52,E30:E52)/SUM(C30:C52),0) -> 0.16171615
A6: Classic | B6: 35 | C6: 3284570.6 | D6: 0.051957093 | E6: =IFERROR(SUMPRODUCT(C57:C91,E57:E91)/SUM(C57:C91),0) -> 0.17162128
A7: TOTAL | B7: 73 | C7: 63216981 | D7: 1 | E7: =IFERROR((SUMPRODUCT(C11:C25,E11:E25)+SUMPRODUCT(C30:C52,E30:E52)+SUMPRODUCT(C57:C91,E57:E91))/(SUM(C11:C25)+SUM(C30:C52)+SUM(C57:C91)),0) -> 0.15703071
A9: DETALLE PLATINUM
A10: # | B10: Cliente | C10: Monto Total | D10: % del Total | E10: Margen % | F10: # Reg
A11: 1 | B11: AGROBERRIES PERU S.A.C. | C11: 10141560 | D11: 0.16042462 | E11: =IFERROR((SUMIFS('Data Cruda'!$P$2:$P$1801,'Data Cruda'!$D$2:$D$1801,"AGROBERRIES PERU S.A.C.",'Data Cruda'!$A$2:$A$1801,2025)+SUMIFS('Data Cruda'!$P$2:$P$1801,'Data Cruda'!$D$2:$D$1801,"AGROBERRIES PERU S.A.C.",'Data Cruda'!$A$2:$A$1801,2026))/(SUMIFS('Data Cruda'!$K$2:$K$1801,'Data Cruda'!$D$2:$D$1801,"AGROBERRIES PERU S.A.C.",'Data Cruda'!$A$2:$A$1801,2025)+SUMIFS('Data Cruda'!$K$2:$K$1801,'Data Cruda'!$D$2:$D$1801,"AGROBERRIES PERU S.A.C.",'Data Cruda'!$A$2:$A$1801,2026)),0) -> 0.1393832 | F11: 4
A12: 2 | B12: DANPER TRUJILLO S.A.C. | C12: 4485901 | D12: 0.07096038 | E12: =IFERROR((SUMIFS('Data Cruda'!$P$2:$P$1801,'Data Cruda'!$D$2:$D$1801,"DANPER TRUJILLO S.A.C.",'Data Cruda'!$A$2:$A$1801,2025)+SUMIFS('Data Cruda'!$P$2:$P$1801,'Data Cruda'!$D$2:$D$1801,"DANPER TRUJILLO S.A.C.",'Data Cruda'!$A$2:$A$1801,2026))/(SUMIFS('Data Cruda'!$K$2:$K$1801,'Data Cruda'!$D$2:$D$1801,"DANPER TRUJILLO S.A.C.",'Data Cruda'!$A$2:$A$1801,2025)+SUMIFS('Data Cruda'!$K$2:$K$1801,'Data Cruda'!$D$2:$D$1801,"DANPER TRUJILLO S.A.C.",'Data Cruda'!$A$2:$A$1801,2026)),0) -> 0.15082002 | F12: 4
A13: 3 | B13: CORPORACION AGROLATINA S.A.C. | C13: 4450000 | D13: 0.070392478 | E13: =IFERROR((SUMIFS('Data Cruda'!$P$2:$P$1801,'Data Cruda'!$D$2:$D$1801,"CORPORACION AGROLATINA S.A.C.",'Data Cruda'!$A$2:$A$1801,2025)+SUMIFS('Data Cruda'!$P$2:$P$1801,'Data Cruda'!$D$2:$D$1801,"CORPORACION AGROLATINA S.A.C.",'Data Cruda'!$A$2:$A$1801,2026))/(SUMIFS('Data Cruda'!$K$2:$K$1801,'Data Cruda'!$D$2:$D$1801,"CORPORACION AGROLATINA S.A.C.",'Data Cruda'!$A$2:$A$1801,2025)+SUMIFS('Data Cruda'!$K$2:$K$1801,'Data Cruda'!$D$2:$D$1801,"CORPORACION AGROLATINA S.A.C.",'Data Cruda'!$A$2:$A$1801,2026)),0) -> 0.14905433 | F13: 2
A14: 4 | B14: AGRICOLA HUARMEY S.A. | C14: 4008997 | D14: 0.063416458 | E14: =IFERROR((SUMIFS('Data Cruda'!$P$2:$P$1801,'Data Cruda'!$D$2:$D$1801,"AGRICOLA HUARMEY S.A.",'Data Cruda'!$A$2:$A$1801,2025)+SUMIFS('Data Cruda'!$P$2:$P$1801,'Data Cruda'!$D$2:$D$1801,"AGRICOLA HUARMEY S.A.",'Data Cruda'!$A$2:$A$1801,2026))/(SUMIFS('Data Cruda'!$K$2:$K$1801,'Data Cruda'!$D$2:$D$1801,"AGRICOLA HUARMEY S.A.",'Data Cruda'!$A$2:$A$1801,2025)+SUMIFS('Data Cruda'!$K$2:$K$1801,'Data Cruda'!$D$2:$D$1801,"AGRICOLA HUARMEY S.A.",'Data Cruda'!$A$2:$A$1801,2026)),0) -> 0.16069571 | F14: 2
A15: 5 | B15: PROSEMBRA SOCIEDAD ANONIMA CERRADA | C15: 3632242.2 | D15: 0.057456749 | E15: =IFERROR((SUMIFS('Data Cruda'!$P$2:$P$1801,'Data Cruda'!$D$2:$D$1801,"PROSEMBRA SOCIEDAD ANONIMA CERRADA",'Data Cruda'!$A$2:$A$1801,2025)+SUMIFS('Data Cruda'!$P$2:$P$1801,'Data Cruda'!$D$2:$D$1801,"PROSEMBRA SOCIEDAD ANONIMA CERRADA",'Data Cruda'!$A$2:$A$1801,2026))/(SUMIFS('Data Cruda'!$K$2:$K$1801,'Data Cruda'!$D$2:$D$1801,"PROSEMBRA SOCIEDAD ANONIMA CERRADA",'Data Cruda'!$A$2:$A$1801,2025)+SUMIFS('Data Cruda'!$K$2:$K$1801,'Data Cruda'!$D$2:$D$1801,"PROSEMBRA SOCIEDAD ANONIMA CERRADA",'Data Cruda'!$A$2:$A$1801,2026)),0) -> 0.17386194 | F15: 7
A16: 6 | B16: AQU ANQA S.A.C. | C16: 3356000.7 | D16: 0.053087013 | E16: =IFERROR((SUMIFS('Data Cruda'!$P$2:$P$1801,'Data Cruda'!$D$2:$D$1801,"AQU ANQA S.A.C.",'Data Cruda'!$A$2:$A$1801,2025)+SUMIFS('Data Cruda'!$P$2:$P$1801,'Data Cruda'!$D$2:$D$1801,"AQU ANQA S.A.C.",'Data Cruda'!$A$2:$A$1801,2026))/(SUMIFS('Data Cruda'!$K$2:$K$1801,'Data Cruda'!$D$2:$D$1801,"AQU ANQA S.A.C.",'Data Cruda'!$A$2:$A$1801,2025)+SUMIFS('Data Cruda'!$K$2:$K$1801,'Data Cruda'!$D$2:$D$1801,"AQU ANQA S.A.C.",'Data Cruda'!$A$2:$A$1801,2026)),0) -> 0.18232047 | F16: 15
A17: 7 | B17: BOMAREA S.R.L. | C17: 3162368.8 | D17: 0.050024039 | E17: =IFERROR((SUMIFS('Data Cruda'!$P$2:$P$1801,'Data Cruda'!$D$2:$D$1801,"BOMAREA S.R.L.",'Data Cruda'!$A$2:$A$1801,2025)+SUMIFS('Data Cruda'!$P$2:$P$1801,'Data Cruda'!$D$2:$D$1801,"BOMAREA S.R.L.",'Data Cruda'!$A$2:$A$1801,2026))/(SUMIFS('Data Cruda'!$K$2:$K$1801,'Data Cruda'!$D$2:$D$1801,"BOMAREA S.R.L.",'Data Cruda'!$A$2:$A$1801,2025)+SUMIFS('Data Cruda'!$K$2:$K$1801,'Data Cruda'!$D$2:$D$1801,"BOMAREA S.R.L.",'Data Cruda'!$A$2:$A$1801,2026)),0) -> 0.14773245 | F17: 4
A18: 8 | B18: Q PACK S.A.C. | C18: 2949135.6 | D18: 0.046651004 | E18: =IFERROR((SUMIFS('Data Cruda'!$P$2:$P$1801,'Data Cruda'!$D$2:$D$1801,"Q PACK S.A.C.",'Data Cruda'!$A$2:$A$1801,2025)+SUMIFS('Data Cruda'!$P$2:$P$1801,'Data Cruda'!$D$2:$D$1801,"Q PACK S.A.C.",'Data Cruda'!$A$2:$A$1801,2026))/(SUMIFS('Data Cruda'!$K$2:$K$1801,'Data Cruda'!$D$2:$D$1801,"Q PACK S.A.C.",'Data Cruda'!$A$2:$A$1801,2025)+SUMIFS('Data Cruda'!$K$2:$K$1801,'Data Cruda'!$D$2:$D$1801,"Q PACK S.A.C.",'Data Cruda'!$A$2:$A$1801,2026)),0) -> 0.17957819 | F18: 8
A19: 9 | B19: TAL S.A. | C19: 2072732.8 | D19: 0.032787595 | E19: =IFERROR((SUMIFS('Data Cruda'!$P$2:$P$1801,'Data Cruda'!$D$2:$D$1801,"TAL S.A.",'Data Cruda'!$A$2:$A$1801,2025)+SUMIFS('Data Cruda'!$P$2:$P$1801,'Data Cruda'!$D$2:$D$1801,"TAL S.A.",'Data Cruda'!$A$2:$A$1801,2026))/(SUMIFS('Data Cruda'!$K$2:$K$1801,'Data Cruda'!$D$2:$D$1801,"TAL S.A.",'Data Cruda'!$A$2:$A$1801,2025)+SUMIFS('Data Cruda'!$K$2:$K$1801,'Data Cruda'!$D$2:$D$1801,"TAL S.A.",'Data Cruda'!$A$2:$A$1801,2026)),0) -> 0.13883549 | F19: 3
A20: 10 | B20: PROCESOS AGROINDUSTRIALES SOCIEDAD ANONIMA | C20: 2034100.6 | D20: 0.03217649 | E20: =IFERROR((SUMIFS('Data Cruda'!$P$2:$P$1801,'Data Cruda'!$D$2:$D$1801,"PROCESOS AGROINDUSTRIALES SOCIEDAD ANONIMA",'Data Cruda'!$A$2:$A$1801,2025)+SUMIFS('Data Cruda'!$P$2:$P$1801,'Data Cruda'!$D$2:$D$1801,"PROCESOS AGROINDUSTRIALES SOCIEDAD ANONIMA",'Data Cruda'!$A$2:$A$1801,2026))/(SUMIFS('Data Cruda'!$K$2:$K$1801,'Data Cruda'!$D$2:$D$1801,"PROCESOS AGROINDUSTRIALES SOCIEDAD ANONIMA",'Data Cruda'!$A$2:$A$1801,2025)+SUMIFS('Data Cruda'!$K$2:$K$1801,'Data Cruda'!$D$2:$D$1801,"PROCESOS AGROINDUSTRIALES SOCIEDAD ANONIMA",'Data Cruda'!$A$2:$A$1801,2026)),0) -> 0.14012856 | F20: 1
A21: 11 | B21: SOCIEDAD AGRICOLA DROKASA S.A. | C21: 1629602.3 | D21: 0.025777921 | E21: =IFERROR((SUMIFS('Data Cruda'!$P$2:$P$1801,'Data Cruda'!$D$2:$D$1801,"SOCIEDAD AGRICOLA DROKASA S.A.",'Data Cruda'!$A$2:$A$1801,2025)+SUMIFS('Data Cruda'!$P$2:$P$1801,'Data Cruda'!$D$2:$D$1801,"SOCIEDAD AGRICOLA DROKASA S.A.",'Data Cruda'!$A$2:$A$1801,2026))/(SUMIFS('Data Cruda'!$K$2:$K$1801,'Data Cruda'!$D$2:$D$1801,"SOCIEDAD AGRICOLA DROKASA S.A.",'Data Cruda'!$A$2:$A$1801,2025)+SUMIFS('Data Cruda'!$K$2:$K$1801,'Data Cruda'!$D$2:$D$1801,"SOCIEDAD AGRICOLA DROKASA S.A.",'Data Cruda'!$A$2:$A$1801,2026)),0) -> 0.14932792 | F21: 6
A22: 12 | B22: AGRICOLA ALAYA SOCIEDAD ANONIMA CERRADA | C22: 1490360.7 | D22: 0.023575322 | E22: =IFERROR((SUMIFS('Data Cruda'!$P$2:$P$1801,'Data Cruda'!$D$2:$D$1801,"AGRICOLA ALAYA SOCIEDAD ANONIMA CERRADA",'Data Cruda'!$A$2:$A$1801,2025)+SUMIFS('Data Cruda'!$P$2:$P$1801,'Data Cruda'!$D$2:$D$1801,"AGRICOLA ALAYA SOCIEDAD ANONIMA CERRADA",'Data Cruda'!$A$2:$A$1801,2026))/(SUMIFS('Data Cruda'!$K$2:$K$1801,'Data Cruda'!$D$2:$D$1801,"AGRICOLA ALAYA SOCIEDAD ANONIMA CERRADA",'Data Cruda'!$A$2:$A$1801,2025)+SUMIFS('Data Cruda'!$K$2:$K$1801,'Data Cruda'!$D$2:$D$1801,"AGRICOLA ALAYA SOCIEDAD ANONIMA CERRADA",'Data Cruda'!$A$2:$A$1801,2026)),0) -> 0.17062136 | F22: 1
A23: 13 | B23: TA EXPORT S.A.C. | C23: 1460000 | D23: 0.02309506 | E23: =IFERROR((SUMIFS('Data Cruda'!$P$2:$P$1801,'Data Cruda'!$D$2:$D$1801,"TA EXPORT S.A.C.",'Data Cruda'!$A$2:$A$1801,2025)+SUMIFS('Data Cruda'!$P$2:$P$1801,'Data Cruda'!$D$2:$D$1801,"TA EXPORT S.A.C.",'Data Cruda'!$A$2:$A$1801,2026))/(SUMIFS('Data Cruda'!$K$2:$K$1801,'Data Cruda'!$D$2:$D$1801,"TA EXPORT S.A.C.",'Data Cruda'!$A$2:$A$1801,2025)+SUMIFS('Data Cruda'!$K$2:$K$1801,'Data Cruda'!$D$2:$D$1801,"TA EXPORT S.A.C.",'Data Cruda'!$A$2:$A$1801,2026)),0) -> 0.1634769 | F23: 1
A24: 14 | B24: AGRICOLA PAMPA BAJA S.A.C. | C24: 1224885.8 | D24: 0.019375898 | E24: =IFERROR((SUMIFS('Data Cruda'!$P$2:$P$1801,'Data Cruda'!$D$2:$D$1801,"AGRICOLA PAMPA BAJA S.A.C.",'Data Cruda'!$A$2:$A$1801,2025)+SUMIFS('Data Cruda'!$P$2:$P$1801,'Data Cruda'!$D$2:$D$1801,"AGRICOLA PAMPA BAJA S.A.C.",'Data Cruda'!$A$2:$A$1801,2026))/(SUMIFS('Data Cruda'!$K$2:$K$1801,'Data Cruda'!$D$2:$D$1801,"AGRICOLA PAMPA BAJA S.A.C.",'Data Cruda'!$A$2:$A$1801,2025)+SUMIFS('Data Cruda'!$K$2:$K$1801,'Data Cruda'!$D$2:$D$1801,"AGRICOLA PAMPA BAJA S.A.C.",'Data Cruda'!$A$2:$A$1801,2026)),0) -> 0.15406422 | F24: 5
A25: 15 | B25: AGROINDUSTRIAS AIB S.A | C25: 1088057.2 | D25: 0.01721147 | E25: =IFERROR((SUMIFS('Data Cruda'!$P$2:$P$1801,'Data Cruda'!$D$2:$D$1801,"AGROINDUSTRIAS AIB S.A",'Data Cruda'!$A$2:$A$1801,2025)+SUMIFS('Data Cruda'!$P$2:$P$1801,'Data Cruda'!$D$2:$D$1801,"AGROINDUSTRIAS AIB S.A",'Data Cruda'!$A$2:$A$1801,2026))/(SUMIFS('Data Cruda'!$K$2:$K$1801,'Data Cruda'!$D$2:$D$1801,"AGROINDUSTRIAS AIB S.A",'Data Cruda'!$A$2:$A$1801,2025)+SUMIFS('Data Cruda'!$K$2:$K$1801,'Data Cruda'!$D$2:$D$1801,"AGROINDUSTRIAS AIB S.A",'Data Cruda'!$A$2:$A$1801,2026)),0) -> 0.15289941 | F25: 3
B26: Subtotal Platinum | C26: 47185945 | D26: 0.7464125
A28: DETALLE GOLD
A29: # | B29: Cliente | C29: Monto Total | D29: % del Total | E29: Margen % | F29: # Reg
A30: 1 | B30: EL PEDREGAL S.A. | C30: 954731.07 | D30: 0.015102446 | E30: =IFERROR((SUMIFS('Data Cruda'!$P$2:$P$1801,'Data Cruda'!$D$2:$D$1801,"EL PEDREGAL S.A.",'Data Cruda'!$A$2:$A$1801,2025)+SUMIFS('Data Cruda'!$P$2:$P$1801,'Data Cruda'!$D$2:$D$1801,"EL PEDREGAL S.A.",'Data Cruda'!$A$2:$A$1801,2026))/(SUMIFS('Data Cruda'!$K$2:$K$1801,'Data Cruda'!$D$2:$D$1801,"EL PEDREGAL S.A.",'Data Cruda'!$A$2:$A$1801,2025)+SUMIFS('Data Cruda'!$K$2:$K$1801,'Data Cruda'!$D$2:$D$1801,"EL PEDREGAL S.A.",'Data Cruda'!$A$2:$A$1801,2026)),0) -> 0.14383219 | F30: 5
A31: 2 | B31: PROCESADORA LARAN SAC | C31: 910903.47 | D31: 0.014409158 | E31: =IFERROR((SUMIFS('Data Cruda'!$P$2:$P$1801,'Data Cruda'!$D$2:$D$1801,"PROCESADORA LARAN SAC",'Data Cruda'!$A$2:$A$1801,2025)+SUMIFS('Data Cruda'!$P$2:$P$1801,'Data Cruda'!$D$2:$D$1801,"PROCESADORA LARAN SAC",'Data Cruda'!$A$2:$A$1801,2026))/(SUMIFS('Data Cruda'!$K$2:$K$1801,'Data Cruda'!$D$2:$D$1801,"PROCESADORA LARAN SAC",'Data Cruda'!$A$2:$A$1801,2025)+SUMIFS('Data Cruda'!$K$2:$K$1801,'Data Cruda'!$D$2:$D$1801,"PROCESADORA LARAN SAC",'Data Cruda'!$A$2:$A$1801,2026)),0) -> 0.13679221 | F31: 3
A32: 3 | B32: ARA FOODS INDUSTRY S.A.C. | C32: 905597.47 | D32: 0.014325225 | E32: =IFERROR((SUMIFS('Data Cruda'!$P$2:$P$1801,'Data Cruda'!$D$2:$D$1801,"ARA FOODS INDUSTRY S.A.C.",'Data Cruda'!$A$2:$A$1801,2025)+SUMIFS('Data Cruda'!$P$2:$P$1801,'Data Cruda'!$D$2:$D$1801,"ARA FOODS INDUSTRY S.A.C.",'Data Cruda'!$A$2:$A$1801,2026))/(SUMIFS('Data Cruda'!$K$2:$K$1801,'Data Cruda'!$D$2:$D$1801,"ARA FOODS INDUSTRY S.A.C.",'Data Cruda'!$A$2:$A$1801,2025)+SUMIFS('Data Cruda'!$K$2:$K$1801,'Data Cruda'!$D$2:$D$1801,"ARA FOODS INDUSTRY S.A.C.",'Data Cruda'!$A$2:$A$1801,2026)),0) -> 0.17152947 | F32: 5
A33: 4 | B33: IMBAREX S.A. | C33: 853450 | D33: 0.013500328 | E33: =IFERROR((SUMIFS('Data Cruda'!$P$2:$P$1801,'Data Cruda'!$D$2:$D$1801,"IMBAREX S.A.",'Data Cruda'!$A$2:$A$1801,2025)+SUMIFS('Data Cruda'!$P$2:$P$1801,'Data Cruda'!$D$2:$D$1801,"IMBAREX S.A.",'Data Cruda'!$A$2:$A$1801,2026))/(SUMIFS('Data Cruda'!$K$2:$K$1801,'Data Cruda'!$D$2:$D$1801,"IMBAREX S.A.",'Data Cruda'!$A$2:$A$1801,2025)+SUMIFS('Data Cruda'!$K$2:$K$1801,'Data Cruda'!$D$2:$D$1801,"IMBAREX S.A.",'Data Cruda'!$A$2:$A$1801,2026)),0) -> 0.16949982 | F33: 3
A34: 5 | B34: AGROVISION PERU S.A.C. | C34: 817031.34 | D34: 0.012924238 | E34: =IFERROR((SUMIFS('Data Cruda'!$P$2:$P$1801,'Data Cruda'!$D$2:$D$1801,"AGROVISION PERU S.A.C.",'Data Cruda'!$A$2:$A$1801,2025)+SUMIFS('Data Cruda'!$P$2:$P$1801,'Data Cruda'!$D$2:$D$1801,"AGROVISION PERU S.A.C.",'Data Cruda'!$A$2:$A$1801,2026))/(SUMIFS('Data Cruda'!$K$2:$K$1801,'Data Cruda'!$D$2:$D$1801,"AGROVISION PERU S.A.C.",'Data Cruda'!$A$2:$A$1801,2025)+SUMIFS('Data Cruda'!$K$2:$K$1801,'Data Cruda'!$D$2:$D$1801,"AGROVISION PERU S.A.C.",'Data Cruda'!$A$2:$A$1801,2026)),0) -> 0.14029453 | F34: 2
A35: 6 | B35: AGROCASAGRANDE S.A.C. | C35: 785287.51 | D35: 0.012422098 | E35: =IFERROR((SUMIFS('Data Cruda'!$P$2:$P$1801,'Data Cruda'!$D$2:$D$1801,"AGROCASAGRANDE S.A.C.",'Data Cruda'!$A$2:$A$1801,2025)+SUMIFS('Data Cruda'!$P$2:$P$1801,'Data Cruda'!$D$2:$D$1801,"AGROCASAGRANDE S.A.C.",'Data Cruda'!$A$2:$A$1801,2026))/(SUMIFS('Data Cruda'!$K$2:$K$1801,'Data Cruda'!$D$2:$D$1801,"AGROCASAGRANDE S.A.C.",'Data Cruda'!$A$2:$A$1801,2025)+SUMIFS('Data Cruda'!$K$2:$K$1801,'Data Cruda'!$D$2:$D$1801,"AGROCASAGRANDE S.A.C.",'Data Cruda'!$A$2:$A$1801,2026)),0) -> 0.18165273 | F35: 8
A36: 7 | B36: PROCESADORA TORRE BLANCA S.A.C | C36: 721156.89 | D36: 0.011407645 | E36: =IFERROR((SUMIFS('Data Cruda'!$P$2:$P$1801,'Data Cruda'!$D$2:$D$1801,"PROCESADORA TORRE BLANCA S.A.C",'Data Cruda'!$A$2:$A$1801,2025)+SUMIFS('Data Cruda'!$P$2:$P$1801,'Data Cruda'!$D$2:$D$1801,"PROCESADORA TORRE BLANCA S.A.C",'Data Cruda'!$A$2:$A$1801,2026))/(SUMIFS('Data Cruda'!$K$2:$K$1801,'Data Cruda'!$D$2:$D$1801,"PROCESADORA TORRE BLANCA S.A.C",'Data Cruda'!$A$2:$A$1801,2025)+SUMIFS('Data Cruda'!$K$2:$K$1801,'Data Cruda'!$D$2:$D$1801,"PROCESADORA TORRE BLANCA S.A.C",'Data Cruda'!$A$2:$A$1801,2026)),0) -> 0.19493805 | F36: 2
A37: 8 | B37: AGROBUSINESS INTERNATIONAL PERU S.A.C. | C37: 602333.49 | D37: 0.0095280331 | E37: =IFERROR((SUMIFS('Data Cruda'!$P$2:$P$1801,'Data Cruda'!$D$2:$D$1801,"AGROBUSINESS INTERNATIONAL PERU S.A.C.",'Data Cruda'!$A$2:$A$1801,2025)+SUMIFS('Data Cruda'!$P$2:$P$1801,'Data Cruda'!$D$2:$D$1801,"AGROBUSINESS INTERNATIONAL PERU S.A.C.",'Data Cruda'!$A$2:$A$1801,2026))/(SUMIFS('Data Cruda'!$K$2:$K$1801,'Data Cruda'!$D$2:$D$1801,"AGROBUSINESS INTERNATIONAL PERU S.A.C.",'Data Cruda'!$A$2:$A$1801,2025)+SUMIFS('Data Cruda'!$K$2:$K$1801,'Data Cruda'!$D$2:$D$1801,"AGROBUSINESS INTERNATIONAL PERU S.A.C.",'Data Cruda'!$A$2:$A$1801,2026)),0) -> 0.17460278 | F37: 3
A38: 9 | B38: SANTA SOFIA DEL SUR S.A.C. | C38: 550187.52 | D38: 0.0087031602 | E38: =IFERROR((SUMIFS('Data Cruda'!$P$2:$P$1801,'Data Cruda'!$D$2:$D$1801,"SANTA SOFIA DEL SUR S.A.C.",'Data Cruda'!$A$2:$A$1801,2025)+SUMIFS('Data Cruda'!$P$2:$P$1801,'Data Cruda'!$D$2:$D$1801,"SANTA SOFIA DEL SUR S.A.C.",'Data Cruda'!$A$2:$A$1801,2026))/(SUMIFS('Data Cruda'!$K$2:$K$1801,'Data Cruda'!$D$2:$D$1801,"SANTA SOFIA DEL SUR S.A.C.",'Data Cruda'!$A$2:$A$1801,2025)+SUMIFS('Data Cruda'!$K$2:$K$1801,'Data Cruda'!$D$2:$D$1801,"SANTA SOFIA DEL SUR S.A.C.",'Data Cruda'!$A$2:$A$1801,2026)),0) -> 0.13309998 | F38: 2
A39: 10 | B39: AGRO FLORAL PERU S.A.C. | C39: 538929.42 | D39: 0.0085250736 | E39: =IFERROR((SUMIFS('Data Cruda'!$P$2:$P$1801,'Data Cruda'!$D$2:$D$1801,"AGRO FLORAL PERU S.A.C.",'Data Cruda'!$A$2:$A$1801,2025)+SUMIFS('Data Cruda'!$P$2:$P$1801,'Data Cruda'!$D$2:$D$1801,"AGRO FLORAL PERU S.A.C.",'Data Cruda'!$A$2:$A$1801,2026))/(SUMIFS('Data Cruda'!$K$2:$K$1801,'Data Cruda'!$D$2:$D$1801,"AGRO FLORAL PERU S.A.C.",'Data Cruda'!$A$2:$A$1801,2025)+SUMIFS('Data Cruda'!$K$2:$K$1801,'Data Cruda'!$D$2:$D$1801,"AGRO FLORAL PERU S.A.C.",'Data Cruda'!$A$2:$A$1801,2026)),0) -> 0.17036528 | F39: 6
A40: 11 | B40: AGROINDUSTRIA FRUTOS DE ORO S.A.C. | C40: 508072.36 | D40: 0.0080369601 | E40: =IFERROR((SUMIFS('Data Cruda'!$P$2:$P$1801,'Data Cruda'!$D$2:$D$1801,"AGROINDUSTRIA FRUTOS DE ORO S.A.C.",'Data Cruda'!$A$2:$A$1801,2025)+SUMIFS('Data Cruda'!$P$2:$P$1801,'Data Cruda'!$D$2:$D$1801,"AGROINDUSTRIA FRUTOS DE ORO S.A.C.",'Data Cruda'!$A$2:$A$1801,2026))/(SUMIFS('Data Cruda'!$K$2:$K$1801,'Data Cruda'!$D$2:$D$1801,"AGROINDUSTRIA FRUTOS DE ORO S.A.C.",'Data Cruda'!$A$2:$A$1801,2025)+SUMIFS('Data Cruda'!$K$2:$K$1801,'Data Cruda'!$D$2:$D$1801,"AGROINDUSTRIA FRUTOS DE ORO S.A.C.",'Data Cruda'!$A$2:$A$1801,2026)),0) -> 0.16892888 | F40: 3
A41: 12 | B41: CAMPOSOL S.A. | C41: 497385.27 | D41: 0.007867906 | E41: =IFERROR((SUMIFS('Data Cruda'!$P$2:$P$1801,'Data Cruda'!$D$2:$D$1801,"CAMPOSOL S.A.",'Data Cruda'!$A$2:$A$1801,2025)+SUMIFS('Data Cruda'!$P$2:$P$1801,'Data Cruda'!$D$2:$D$1801,"CAMPOSOL S.A.",'Data Cruda'!$A$2:$A$1801,2026))/(SUMIFS('Data Cruda'!$K$2:$K$1801,'Data Cruda'!$D$2:$D$1801,"CAMPOSOL S.A.",'Data Cruda'!$A$2:$A$1801,2025)+SUMIFS('Data Cruda'!$K$2:$K$1801,'Data Cruda'!$D$2:$D$1801,"CAMPOSOL S.A.",'Data Cruda'!$A$2:$A$1801,2026)),0) -> 0.1509673 | F41: 1
A42: 13 | B42: SUN FRUITS EXPORTS S.A. | C42: 460117.04 | D42: 0.0072783773 | E42: =IFERROR((SUMIFS('Data Cruda'!$P$2:$P$1801,'Data Cruda'!$D$2:$D$1801,"SUN FRUITS EXPORTS S.A.",'Data Cruda'!$A$2:$A$1801,2025)+SUMIFS('Data Cruda'!$P$2:$P$1801,'Data Cruda'!$D$2:$D$1801,"SUN FRUITS EXPORTS S.A.",'Data Cruda'!$A$2:$A$1801,2026))/(SUMIFS('Data Cruda'!$K$2:$K$1801,'Data Cruda'!$D$2:$D$1801,"SUN FRUITS EXPORTS S.A.",'Data Cruda'!$A$2:$A$1801,2025)+SUMIFS('Data Cruda'!$K$2:$K$1801,'Data Cruda'!$D$2:$D$1801,"SUN FRUITS EXPORTS S.A.",'Data Cruda'!$A$2:$A$1801,2026)),0) -> 0.20032218 | F42: 3
A43: 14 | B43: ESTANTERIAS METALICAS J.R.M. S.A.C | C43: 455000 | D43: 0.0071974332 | E43: =IFERROR((SUMIFS('Data Cruda'!$P$2:$P$1801,'Data Cruda'!$D$2:$D$1801,"ESTANTERIAS METALICAS J.R.M. S.A.C",'Data Cruda'!$A$2:$A$1801,2025)+SUMIFS('Data Cruda'!$P$2:$P$1801,'Data Cruda'!$D$2:$D$1801,"ESTANTERIAS METALICAS J.R.M. S.A.C",'Data Cruda'!$A$2:$A$1801,2026))/(SUMIFS('Data Cruda'!$K$2:$K$1801,'Data Cruda'!$D$2:$D$1801,"ESTANTERIAS METALICAS J.R.M. S.A.C",'Data Cruda'!$A$2:$A$1801,2025)+SUMIFS('Data Cruda'!$K$2:$K$1801,'Data Cruda'!$D$2:$D$1801,"ESTANTERIAS METALICAS J.R.M. S.A.C",'Data Cruda'!$A$2:$A$1801,2026)),0) -> 0.14243422 | F43: 1
A44: 15 | B44: DELICE S.A.C | C44: 427469.32 | D44: 0.0067619382 | E44: =IFERROR((SUMIFS('Data Cruda'!$P$2:$P$1801,'Data Cruda'!$D$2:$D$1801,"DELICE S.A.C",'Data Cruda'!$A$2:$A$1801,2025)+SUMIFS('Data Cruda'!$P$2:$P$1801,'Data Cruda'!$D$2:$D$1801,"DELICE S.A.C",'Data Cruda'!$A$2:$A$1801,2026))/(SUMIFS('Data Cruda'!$K$2:$K$1801,'Data Cruda'!$D$2:$D$1801,"DELICE S.A.C",'Data Cruda'!$A$2:$A$1801,2025)+SUMIFS('Data Cruda'!$K$2:$K$1801,'Data Cruda'!$D$2:$D$1801,"DELICE S.A.C",'Data Cruda'!$A$2:$A$1801,2026)),0) -> 0.14045859 | F44: 4
A45: 16 | B45: VIRU S.A. | C45: 407039.67 | D45: 0.006438771 | E45: =IFERROR((SUMIFS('Data Cruda'!$P$2:$P$1801,'Data Cruda'!$D$2:$D$1801,"VIRU S.A.",'Data Cruda'!$A$2:$A$1801,2025)+SUMIFS('Data Cruda'!$P$2:$P$1801,'Data Cruda'!$D$2:$D$1801,"VIRU S.A.",'Data Cruda'!$A$2:$A$1801,2026))/(SUMIFS('Data Cruda'!$K$2:$K$1801,'Data Cruda'!$D$2:$D$1801,"VIRU S.A.",'Data Cruda'!$A$2:$A$1801,2025)+SUMIFS('Data Cruda'!$K$2:$K$1801,'Data Cruda'!$D$2:$D$1801,"VIRU S.A.",'Data Cruda'!$A$2:$A$1801,2026)),0) -> 0.16478352 | F45: 2
A46: 17 | B46: BERRY HARVEST S.A. | C46: 402750.72 | D46: 0.0063709261 | E46: =IFERROR((SUMIFS('Data Cruda'!$P$2:$P$1801,'Data Cruda'!$D$2:$D$1801,"BERRY HARVEST S.A.",'Data Cruda'!$A$2:$A$1801,2025)+SUMIFS('Data Cruda'!$P$2:$P$1801,'Data Cruda'!$D$2:$D$1801,"BERRY HARVEST S.A.",'Data Cruda'!$A$2:$A$1801,2026))/(SUMIFS('Data Cruda'!$K$2:$K$1801,'Data Cruda'!$D$2:$D$1801,"BERRY HARVEST S.A.",'Data Cruda'!$A$2:$A$1801,2025)+SUMIFS('Data Cruda'!$K$2:$K$1801,'Data Cruda'!$D$2:$D$1801,"BERRY HARVEST S.A.",'Data Cruda'!$A$2:$A$1801,2026)),0) -> 0.18555774 | F46: 6
A47: 18 | B47: AGRICOLA 2M S.A.C. | C47: 390950.55 | D47: 0.0061842648 | E47: =IFERROR((SUMIFS('Data Cruda'!$P$2:$P$1801,'Data Cruda'!$D$2:$D$1801,"AGRICOLA 2M S.A.C.",'Data Cruda'!$A$2:$A$1801,2025)+SUMIFS('Data Cruda'!$P$2:$P$1801,'Data Cruda'!$D$2:$D$1801,"AGRICOLA 2M S.A.C.",'Data Cruda'!$A$2:$A$1801,2026))/(SUMIFS('Data Cruda'!$K$2:$K$1801,'Data Cruda'!$D$2:$D$1801,"AGRICOLA 2M S.A.C.",'Data Cruda'!$A$2:$A$1801,2025)+SUMIFS('Data Cruda'!$K$2:$K$1801,'Data Cruda'!$D$2:$D$1801,"AGRICOLA 2M S.A.C.",'Data Cruda'!$A$2:$A$1801,2026)),0) -> 0.16107096 | F47: 4
A48: 19 | B48: QALI FRUITS S.A.C. | C48: 379901.83 | D48: 0.0060094902 | E48: =IFERROR((SUMIFS('Data Cruda'!$P$2:$P$1801,'Data Cruda'!$D$2:$D$1801,"QALI FRUITS S.A.C.",'Data Cruda'!$A$2:$A$1801,2025)+SUMIFS('Data Cruda'!$P$2:$P$1801,'Data Cruda'!$D$2:$D$1801,"QALI FRUITS S.A.C.",'Data Cruda'!$A$2:$A$1801,2026))/(SUMIFS('Data Cruda'!$K$2:$K$1801,'Data Cruda'!$D$2:$D$1801,"QALI FRUITS S.A.C.",'Data Cruda'!$A$2:$A$1801,2025)+SUMIFS('Data Cruda'!$K$2:$K$1801,'Data Cruda'!$D$2:$D$1801,"QALI FRUITS S.A.C.",'Data Cruda'!$A$2:$A$1801,2026)),0) -> 0.15382442 | F48: 1
A49: 20 | B49: DIAMOND BRIDGE SAC | C49: 321860.28 | D49: 0.0050913579 | E49: =IFERROR((SUMIFS('Data Cruda'!$P$2:$P$1801,'Data Cruda'!$D$2:$D$1801,"DIAMOND BRIDGE SAC",'Data Cruda'!$A$2:$A$1801,2025)+SUMIFS('Data Cruda'!$P$2:$P$1801,'Data Cruda'!$D$2:$D$1801,"DIAMOND BRIDGE SAC",'Data Cruda'!$A$2:$A$1801,2026))/(SUMIFS('Data Cruda'!$K$2:$K$1801,'Data Cruda'!$D$2:$D$1801,"DIAMOND BRIDGE SAC",'Data Cruda'!$A$2:$A$1801,2025)+SUMIFS('Data Cruda'!$K$2:$K$1801,'Data Cruda'!$D$2:$D$1801,"DIAMOND BRIDGE SAC",'Data Cruda'!$A$2:$A$1801,2026)),0) -> 0.16518315 | F49: 5
A50: 21 | B50: LIMONES PIURANOS SOCIEDAD ANONIMA CERRADA | C50: 317796.61 | D50: 0.0050270766 | E50: =IFERROR((SUMIFS('Data Cruda'!$P$2:$P$1801,'Data Cruda'!$D$2:$D$1801,"LIMONES PIURANOS SOCIEDAD ANONIMA CERRADA",'Data Cruda'!$A$2:$A$1801,2025)+SUMIFS('Data Cruda'!$P$2:$P$1801,'Data Cruda'!$D$2:$D$1801,"LIMONES PIURANOS SOCIEDAD ANONIMA CERRADA",'Data Cruda'!$A$2:$A$1801,2026))/(SUMIFS('Data Cruda'!$K$2:$K$1801,'Data Cruda'!$D$2:$D$1801,"LIMONES PIURANOS SOCIEDAD ANONIMA CERRADA",'Data Cruda'!$A$2:$A$1801,2025)+SUMIFS('Data Cruda'!$K$2:$K$1801,'Data Cruda'!$D$2:$D$1801,"LIMONES PIURANOS SOCIEDAD ANONIMA CERRADA",'Data Cruda'!$A$2:$A$1801,2026)),0) -> 0.17076041 | F50: 1
A51: 22 | B51: SOCIEDAD AGRICOLA 3P S.A.C. | C51: 282000.85 | D51: 0.0044608402 | E51: =IFERROR((SUMIFS('Data Cruda'!$P$2:$P$1801,'Data Cruda'!$D$2:$D$1801,"SOCIEDAD AGRICOLA 3P S.A.C.",'Data Cruda'!$A$2:$A$1801,2025)+SUMIFS('Data Cruda'!$P$2:$P$1801,'Data Cruda'!$D$2:$D$1801,"SOCIEDAD AGRICOLA 3P S.A.C.",'Data Cruda'!$A$2:$A$1801,2026))/(SUMIFS('Data Cruda'!$K$2:$K$1801,'Data Cruda'!$D$2:$D$1801,"SOCIEDAD AGRICOLA 3P S.A.C.",'Data Cruda'!$A$2:$A$1801,2025)+SUMIFS('Data Cruda'!$K$2:$K$1801,'Data Cruda'!$D$2:$D$1801,"SOCIEDAD AGRICOLA 3P S.A.C.",'Data Cruda'!$A$2:$A$1801,2026)),0) -> 0.16068063 | F51: 5
A52: 23 | B52: AGRICOLA GANADERA LAS CANELAS SAC | C52: 256513.28 | D52: 0.0040576642 | E52: =IFERROR((SUMIFS('Data Cruda'!$P$2:$P$1801,'Data Cruda'!$D$2:$D$1801,"AGRICOLA GANADERA LAS CANELAS SAC",'Data Cruda'!$A$2:$A$1801,2025)+SUMIFS('Data Cruda'!$P$2:$P$1801,'Data Cruda'!$D$2:$D$1801,"AGRICOLA GANADERA LAS CANELAS SAC",'Data Cruda'!$A$2:$A$1801,2026))/(SUMIFS('Data Cruda'!$K$2:$K$1801,'Data Cruda'!$D$2:$D$1801,"AGRICOLA GANADERA LAS CANELAS SAC",'Data Cruda'!$A$2:$A$1801,2025)+SUMIFS('Data Cruda'!$K$2:$K$1801,'Data Cruda'!$D$2:$D$1801,"AGRICOLA GANADERA LAS CANELAS SAC",'Data Cruda'!$A$2:$A$1801,2026)),0) -> 0.1458764 | F52: 4
B53: Subtotal Gold | C53: 12746466 | D53: 0.20163041
A55: DETALLE CLASSIC
A56: # | B56: Cliente | C56: Monto Total | D56: % del Total | E56: Margen % | F56: # Reg
A57: 1 | B57: CONSORCIO AGRICOLA MOQUEGUA S.A.C. | C57: 232667.9 | D57: 0.0036804652 | E57: =IFERROR((SUMIFS('Data Cruda'!$P$2:$P$1801,'Data Cruda'!$D$2:$D$1801,"CONSORCIO AGRICOLA MOQUEGUA S.A.C.",'Data Cruda'!$A$2:$A$1801,2025)+SUMIFS('Data Cruda'!$P$2:$P$1801,'Data Cruda'!$D$2:$D$1801,"CONSORCIO AGRICOLA MOQUEGUA S.A.C.",'Data Cruda'!$A$2:$A$1801,2026))/(SUMIFS('Data Cruda'!$K$2:$K$1801,'Data Cruda'!$D$2:$D$1801,"CONSORCIO AGRICOLA MOQUEGUA S.A.C.",'Data Cruda'!$A$2:$A$1801,2025)+SUMIFS('Data Cruda'!$K$2:$K$1801,'Data Cruda'!$D$2:$D$1801,"CONSORCIO AGRICOLA MOQUEGUA S.A.C.",'Data Cruda'!$A$2:$A$1801,2026)),0) -> 0.15369864 | F57: 2
A58: 2 | B58: T & T FRUITS S.A. | C58: 227719.49 | D58: 0.0036021886 | E58: =IFERROR((SUMIFS('Data Cruda'!$P$2:$P$1801,'Data Cruda'!$D$2:$D$1801,"T & T FRUITS S.A.",'Data Cruda'!$A$2:$A$1801,2025)+SUMIFS('Data Cruda'!$P$2:$P$1801,'Data Cruda'!$D$2:$D$1801,"T & T FRUITS S.A.",'Data Cruda'!$A$2:$A$1801,2026))/(SUMIFS('Data Cruda'!$K$2:$K$1801,'Data Cruda'!$D$2:$D$1801,"T & T FRUITS S.A.",'Data Cruda'!$A$2:$A$1801,2025)+SUMIFS('Data Cruda'!$K$2:$K$1801,'Data Cruda'!$D$2:$D$1801,"T & T FRUITS S.A.",'Data Cruda'!$A$2:$A$1801,2026)),0) -> 0.13892171 | F58: 1
A59: 3 | B59: SAN EFISIO S.A.C. | C59: 226880.03 | D59: 0.0035889096 | E59: =IFERROR((SUMIFS('Data Cruda'!$P$2:$P$1801,'Data Cruda'!$D$2:$D$1801,"SAN EFISIO S.A.C.",'Data Cruda'!$A$2:$A$1801,2025)+SUMIFS('Data Cruda'!$P$2:$P$1801,'Data Cruda'!$D$2:$D$1801,"SAN EFISIO S.A.C.",'Data Cruda'!$A$2:$A$1801,2026))/(SUMIFS('Data Cruda'!$K$2:$K$1801,'Data Cruda'!$D$2:$D$1801,"SAN EFISIO S.A.C.",'Data Cruda'!$A$2:$A$1801,2025)+SUMIFS('Data Cruda'!$K$2:$K$1801,'Data Cruda'!$D$2:$D$1801,"SAN EFISIO S.A.C.",'Data Cruda'!$A$2:$A$1801,2026)),0) -> 0.19791984 | F59: 1
A60: 4 | B60: UNIÓN DE CERVECERÍAS PERUANAS BACKUS Y JOHNSTON SAC | C60: 222254 | D60: 0.0035157326 | E60: =IFERROR((SUMIFS('Data Cruda'!$P$2:$P$1801,'Data Cruda'!$D$2:$D$1801,"UNIÓN DE CERVECERÍAS PERUANAS BACKUS Y JOHNSTON SAC",'Data Cruda'!$A$2:$A$1801,2025)+SUMIFS('Data Cruda'!$P$2:$P$1801,'Data Cruda'!$D$2:$D$1801,"UNIÓN DE CERVECERÍAS PERUANAS BACKUS Y JOHNSTON SAC",'Data Cruda'!$A$2:$A$1801,2026))/(SUMIFS('Data Cruda'!$K$2:$K$1801,'Data Cruda'!$D$2:$D$1801,"UNIÓN DE CERVECERÍAS PERUANAS BACKUS Y JOHNSTON SAC",'Data Cruda'!$A$2:$A$1801,2025)+SUMIFS('Data Cruda'!$K$2:$K$1801,'Data Cruda'!$D$2:$D$1801,"UNIÓN DE CERVECERÍAS PERUANAS BACKUS Y JOHNSTON SAC",'Data Cruda'!$A$2:$A$1801,2026)),0) -> 0.12469998 | F60: 1
A61: 5 | B61: VIVEROS EL TAMBO S.A.C. | C61: 216754.9 | D61: 0.0034287449 | E61: =IFERROR((SUMIFS('Data Cruda'!$P$2:$P$1801,'Data Cruda'!$D$2:$D$1801,"VIVEROS EL TAMBO S.A.C.",'Data Cruda'!$A$2:$A$1801,2025)+SUMIFS('Data Cruda'!$P$2:$P$1801,'Data Cruda'!$D$2:$D$1801,"VIVEROS EL TAMBO S.A.C.",'Data Cruda'!$A$2:$A$1801,2026))/(SUMIFS('Data Cruda'!$K$2:$K$1801,'Data Cruda'!$D$2:$D$1801,"VIVEROS EL TAMBO S.A.C.",'Data Cruda'!$A$2:$A$1801,2025)+SUMIFS('Data Cruda'!$K$2:$K$1801,'Data Cruda'!$D$2:$D$1801,"VIVEROS EL TAMBO S.A.C.",'Data Cruda'!$A$2:$A$1801,2026)),0) -> 0.19515785 | F61: 1
A62: 6 | B62: UNIVERSIDAD FEDERICO HENRIQUEZ Y CARVAJAL | C62: 206089.67 | D62: 0.0032600365 | E62: =IFERROR((SUMIFS('Data Cruda'!$P$2:$P$1801,'Data Cruda'!$D$2:$D$1801,"UNIVERSIDAD FEDERICO HENRIQUEZ Y CARVAJAL",'Data Cruda'!$A$2:$A$1801,2025)+SUMIFS('Data Cruda'!$P$2:$P$1801,'Data Cruda'!$D$2:$D$1801,"UNIVERSIDAD FEDERICO HENRIQUEZ Y CARVAJAL",'Data Cruda'!$A$2:$A$1801,2026))/(SUMIFS('Data Cruda'!$K$2:$K$1801,'Data Cruda'!$D$2:$D$1801,"UNIVERSIDAD FEDERICO HENRIQUEZ Y CARVAJAL",'Data Cruda'!$A$2:$A$1801,2025)+SUMIFS('Data Cruda'!$K$2:$K$1801,'Data Cruda'!$D$2:$D$1801,"UNIVERSIDAD FEDERICO HENRIQUEZ Y CARVAJAL",'Data Cruda'!$A$2:$A$1801,2026)),0) -> 0.37198211 | F62: 1
A63: 7 | B63: ARCA CONTINENTAL LINDLEY S.A. | C63: 203678.39 | D63: 0.0032218936 | E63: =IFERROR((SUMIFS('Data Cruda'!$P$2:$P$1801,'Data Cruda'!$D$2:$D$1801,"ARCA CONTINENTAL LINDLEY S.A.",'Data Cruda'!$A$2:$A$1801,2025)+SUMIFS('Data Cruda'!$P$2:$P$1801,'Data Cruda'!$D$2:$D$1801,"ARCA CONTINENTAL LINDLEY S.A.",'Data Cruda'!$A$2:$A$1801,2026))/(SUMIFS('Data Cruda'!$K$2:$K$1801,'Data Cruda'!$D$2:$D$1801,"ARCA CONTINENTAL LINDLEY S.A.",'Data Cruda'!$A$2:$A$1801,2025)+SUMIFS('Data Cruda'!$K$2:$K$1801,'Data Cruda'!$D$2:$D$1801,"ARCA CONTINENTAL LINDLEY S.A.",'Data Cruda'!$A$2:$A$1801,2026)),0) -> 0.21300257 | F63: 1
A64: 8 | B64: EMPRESA AGRICOLA SAN JUAN S.A | C64: 194358.88 | D64: 0.0030744727 | E64: =IFERROR((SUMIFS('Data Cruda'!$P$2:$P$1801,'Data Cruda'!$D$2:$D$1801,"EMPRESA AGRICOLA SAN JUAN S.A",'Data Cruda'!$A$2:$A$1801,2025)+SUMIFS('Data Cruda'!$P$2:$P$1801,'Data Cruda'!$D$2:$D$1801,"EMPRESA AGRICOLA SAN JUAN S.A",'Data Cruda'!$A$2:$A$1801,2026))/(SUMIFS('Data Cruda'!$K$2:$K$1801,'Data Cruda'!$D$2:$D$1801,"EMPRESA AGRICOLA SAN JUAN S.A",'Data Cruda'!$A$2:$A$1801,2025)+SUMIFS('Data Cruda'!$K$2:$K$1801,'Data Cruda'!$D$2:$D$1801,"EMPRESA AGRICOLA SAN JUAN S.A",'Data Cruda'!$A$2:$A$1801,2026)),0) -> 0.18937787 | F64: 1
A65: 9 | B65: DISTRIBUIDORA EXCLUSIVA DE PRODUCTOS DE CALIDAD SAC | C65: 189851.72 | D65: 0.003003176 | E65: =IFERROR((SUMIFS('Data Cruda'!$P$2:$P$1801,'Data Cruda'!$D$2:$D$1801,"DISTRIBUIDORA EXCLUSIVA DE PRODUCTOS DE CALIDAD SAC",'Data Cruda'!$A$2:$A$1801,2025)+SUMIFS('Data Cruda'!$P$2:$P$1801,'Data Cruda'!$D$2:$D$1801,"DISTRIBUIDORA EXCLUSIVA DE PRODUCTOS DE CALIDAD SAC",'Data Cruda'!$A$2:$A$1801,2026))/(SUMIFS('Data Cruda'!$K$2:$K$1801,'Data Cruda'!$D$2:$D$1801,"DISTRIBUIDORA EXCLUSIVA DE PRODUCTOS DE CALIDAD SAC",'Data Cruda'!$A$2:$A$1801,2025)+SUMIFS('Data Cruda'!$K$2:$K$1801,'Data Cruda'!$D$2:$D$1801,"DISTRIBUIDORA EXCLUSIVA DE PRODUCTOS DE CALIDAD SAC",'Data Cruda'!$A$2:$A$1801,2026)),0) -> 0 | F65: 1
A66: 10 | B66: FUSION FOODS S.A.C. | C66: 175587.99 | D66: 0.0027775447 | E66: =IFERROR((SUMIFS('Data Cruda'!$P$2:$P$1801,'Data Cruda'!$D$2:$D$1801,"FUSION FOODS S.A.C.",'Data Cruda'!$A$2:$A$1801,2025)+SUMIFS('Data Cruda'!$P$2:$P$1801,'Data Cruda'!$D$2:$D$1801,"FUSION FOODS S.A.C.",'Data Cruda'!$A$2:$A$1801,2026))/(SUMIFS('Data Cruda'!$K$2:$K$1801,'Data Cruda'!$D$2:$D$1801,"FUSION FOODS S.A.C.",'Data Cruda'!$A$2:$A$1801,2025)+SUMIFS('Data Cruda'!$K$2:$K$1801,'Data Cruda'!$D$2:$D$1801,"FUSION FOODS S.A.C.",'Data Cruda'!$A$2:$A$1801,2026)),0) -> 0.094202286 | F66: 3
A67: 11 | B67: AUSTRAL GROUP S.A.A. | C67: 117308 | D67: 0.0018556406 | E67: =IFERROR((SUMIFS('Data Cruda'!$P$2:$P$1801,'Data Cruda'!$D$2:$D$1801,"AUSTRAL GROUP S.A.A.",'Data Cruda'!$A$2:$A$1801,2025)+SUMIFS('Data Cruda'!$P$2:$P$1801,'Data Cruda'!$D$2:$D$1801,"AUSTRAL GROUP S.A.A.",'Data Cruda'!$A$2:$A$1801,2026))/(SUMIFS('Data Cruda'!$K$2:$K$1801,'Data Cruda'!$D$2:$D$1801,"AUSTRAL GROUP S.A.A.",'Data Cruda'!$A$2:$A$1801,2025)+SUMIFS('Data Cruda'!$K$2:$K$1801,'Data Cruda'!$D$2:$D$1801,"AUSTRAL GROUP S.A.A.",'Data Cruda'!$A$2:$A$1801,2026)),0) -> 0 | F67: 1
A68: 12 | B68: REITER PERUVIAN BERRY S.A. | C68: 110710 | D68: 0.00175127 | E68: =IFERROR((SUMIFS('Data Cruda'!$P$2:$P$1801,'Data Cruda'!$D$2:$D$1801,"REITER PERUVIAN BERRY S.A.",'Data Cruda'!$A$2:$A$1801,2025)+SUMIFS('Data Cruda'!$P$2:$P$1801,'Data Cruda'!$D$2:$D$1801,"REITER PERUVIAN BERRY S.A.",'Data Cruda'!$A$2:$A$1801,2026))/(SUMIFS('Data Cruda'!$K$2:$K$1801,'Data Cruda'!$D$2:$D$1801,"REITER PERUVIAN BERRY S.A.",'Data Cruda'!$A$2:$A$1801,2025)+SUMIFS('Data Cruda'!$K$2:$K$1801,'Data Cruda'!$D$2:$D$1801,"REITER PERUVIAN BERRY S.A.",'Data Cruda'!$A$2:$A$1801,2026)),0) -> 0.14169352 | F68: 1
A69: 13 | B69: AGRICOLA HUARMEY S.A.C. | C69: 106047.18 | D69: 0.001677511 | E69: =IFERROR((SUMIFS('Data Cruda'!$P$2:$P$1801,'Data Cruda'!$D$2:$D$1801,"AGRICOLA HUARMEY S.A.C.",'Data Cruda'!$A$2:$A$1801,2025)+SUMIFS('Data Cruda'!$P$2:$P$1801,'Data Cruda'!$D$2:$D$1801,"AGRICOLA HUARMEY S.A.C.",'Data Cruda'!$A$2:$A$1801,2026))/(SUMIFS('Data Cruda'!$K$2:$K$1801,'Data Cruda'!$D$2:$D$1801,"AGRICOLA HUARMEY S.A.C.",'Data Cruda'!$A$2:$A$1801,2025)+SUMIFS('Data Cruda'!$K$2:$K$1801,'Data Cruda'!$D$2:$D$1801,"AGRICOLA HUARMEY S.A.C.",'Data Cruda'!$A$2:$A$1801,2026)),0) -> 0.17593716 | F69: 2
A70: 14 | B70: INGENIERIA EN CARTONES Y PAPELES S.A.C | C70: 101933.16 | D70: 0.0016124332 | E70: =IFERROR((SUMIFS('Data Cruda'!$P$2:$P$1801,'Data Cruda'!$D$2:$D$1801,"INGENIERIA EN CARTONES Y PAPELES S.A.C",'Data Cruda'!$A$2:$A$1801,2025)+SUMIFS('Data Cruda'!$P$2:$P$1801,'Data Cruda'!$D$2:$D$1801,"INGENIERIA EN CARTONES Y PAPELES S.A.C",'Data Cruda'!$A$2:$A$1801,2026))/(SUMIFS('Data Cruda'!$K$2:$K$1801,'Data Cruda'!$D$2:$D$1801,"INGENIERIA EN CARTONES Y PAPELES S.A.C",'Data Cruda'!$A$2:$A$1801,2025)+SUMIFS('Data Cruda'!$K$2:$K$1801,'Data Cruda'!$D$2:$D$1801,"INGENIERIA EN CARTONES Y PAPELES S.A.C",'Data Cruda'!$A$2:$A$1801,2026)),0) -> 0.20033363 | F70: 1
A71: 15 | B71: IN VITRO LAB PERU S.A.C | C71: 99000 | D71: 0.0015660349 | E71: =IFERROR((SUMIFS('Data Cruda'!$P$2:$P$1801,'Data Cruda'!$D$2:$D$1801,"IN VITRO LAB PERU S.A.C",'Data Cruda'!$A$2:$A$1801,2025)+SUMIFS('Data Cruda'!$P$2:$P$1801,'Data Cruda'!$D$2:$D$1801,"IN VITRO LAB PERU S.A.C",'Data Cruda'!$A$2:$A$1801,2026))/(SUMIFS('Data Cruda'!$K$2:$K$1801,'Data Cruda'!$D$2:$D$1801,"IN VITRO LAB PERU S.A.C",'Data Cruda'!$A$2:$A$1801,2025)+SUMIFS('Data Cruda'!$K$2:$K$1801,'Data Cruda'!$D$2:$D$1801,"IN VITRO LAB PERU S.A.C",'Data Cruda'!$A$2:$A$1801,2026)),0) -> 0.3 | F71: 1
A72: 16 | B72: QBERRIES SAC | C72: 96847.02 | D72: 0.0015319779 | E72: =IFERROR((SUMIFS('Data Cruda'!$P$2:$P$1801,'Data Cruda'!$D$2:$D$1801,"QBERRIES SAC",'Data Cruda'!$A$2:$A$1801,2025)+SUMIFS('Data Cruda'!$P$2:$P$1801,'Data Cruda'!$D$2:$D$1801,"QBERRIES SAC",'Data Cruda'!$A$2:$A$1801,2026))/(SUMIFS('Data Cruda'!$K$2:$K$1801,'Data Cruda'!$D$2:$D$1801,"QBERRIES SAC",'Data Cruda'!$A$2:$A$1801,2025)+SUMIFS('Data Cruda'!$K$2:$K$1801,'Data Cruda'!$D$2:$D$1801,"QBERRIES SAC",'Data Cruda'!$A$2:$A$1801,2026)),0) -> 0.3 | F72: 2
A73: 17 | B73: SMART PACKING S.A.C. | C73: 77696.99 | D73: 0.0012290525 | E73: =IFERROR((SUMIFS('Data Cruda'!$P$2:$P$1801,'Data Cruda'!$D$2:$D$1801,"SMART PACKING S.A.C.",'Data Cruda'!$A$2:$A$1801,2025)+SUMIFS('Data Cruda'!$P$2:$P$1801,'Data Cruda'!$D$2:$D$1801,"SMART PACKING S.A.C.",'Data Cruda'!$A$2:$A$1801,2026))/(SUMIFS('Data Cruda'!$K$2:$K$1801,'Data Cruda'!$D$2:$D$1801,"SMART PACKING S.A.C.",'Data Cruda'!$A$2:$A$1801,2025)+SUMIFS('Data Cruda'!$K$2:$K$1801,'Data Cruda'!$D$2:$D$1801,"SMART PACKING S.A.C.",'Data Cruda'!$A$2:$A$1801,2026)),0) -> 0.14254606 | F73: 3
A74: 18 | B74: FLORISERT S.A.C. | C74: 61715.57 | D74: 0.00097624987 | E74: =IFERROR((SUMIFS('Data Cruda'!$P$2:$P$1801,'Data Cruda'!$D$2:$D$1801,"FLORISERT S.A.C.",'Data Cruda'!$A$2:$A$1801,2025)+SUMIFS('Data Cruda'!$P$2:$P$1801,'Data Cruda'!$D$2:$D$1801,"FLORISERT S.A.C.",'Data Cruda'!$A$2:$A$1801,2026))/(SUMIFS('Data Cruda'!$K$2:$K$1801,'Data Cruda'!$D$2:$D$1801,"FLORISERT S.A.C.",'Data Cruda'!$A$2:$A$1801,2025)+SUMIFS('Data Cruda'!$K$2:$K$1801,'Data Cruda'!$D$2:$D$1801,"FLORISERT S.A.C.",'Data Cruda'!$A$2:$A$1801,2026)),0) -> 0.1684186 | F74: 1
A75: 19 | B75: LOS OLIVOS DE VILLACURI S.A.C. | C75: 50827.6 | D75: 0.00080401814 | E75: =IFERROR((SUMIFS('Data Cruda'!$P$2:$P$1801,'Data Cruda'!$D$2:$D$1801,"LOS OLIVOS DE VILLACURI S.A.C.",'Data Cruda'!$A$2:$A$1801,2025)+SUMIFS('Data Cruda'!$P$2:$P$1801,'Data Cruda'!$D$2:$D$1801,"LOS OLIVOS DE VILLACURI S.A.C.",'Data Cruda'!$A$2:$A$1801,2026))/(SUMIFS('Data Cruda'!$K$2:$K$1801,'Data Cruda'!$D$2:$D$1801,"LOS OLIVOS DE VILLACURI S.A.C.",'Data Cruda'!$A$2:$A$1801,2025)+SUMIFS('Data Cruda'!$K$2:$K$1801,'Data Cruda'!$D$2:$D$1801,"LOS OLIVOS DE VILLACURI S.A.C.",'Data Cruda'!$A$2:$A$1801,2026)),0) -> 0.24678482 | F75: 4
A76: 20 | B76: FAMILY FARMS PERÚ S.R.L. | C76: 48530.23 | D76: 0.00076767712 | E76: =IFERROR((SUMIFS('Data Cruda'!$P$2:$P$1801,'Data Cruda'!$D$2:$D$1801,"FAMILY FARMS PERÚ S.R.L.",'Data Cruda'!$A$2:$A$1801,2025)+SUMIFS('Data Cruda'!$P$2:$P$1801,'Data Cruda'!$D$2:$D$1801,"FAMILY FARMS PERÚ S.R.L.",'Data Cruda'!$A$2:$A$1801,2026))/(SUMIFS('Data Cruda'!$K$2:$K$1801,'Data Cruda'!$D$2:$D$1801,"FAMILY FARMS PERÚ S.R.L.",'Data Cruda'!$A$2:$A$1801,2025)+SUMIFS('Data Cruda'!$K$2:$K$1801,'Data Cruda'!$D$2:$D$1801,"FAMILY FARMS PERÚ S.R.L.",'Data Cruda'!$A$2:$A$1801,2026)),0) -> 0.13226354 | F76: 1
A77: 21 | B77: ALZA PERU PACKING S.A.C. | C77: 43600.44 | D77: 0.00068969506 | E77: =IFERROR((SUMIFS('Data Cruda'!$P$2:$P$1801,'Data Cruda'!$D$2:$D$1801,"ALZA PERU PACKING S.A.C.",'Data Cruda'!$A$2:$A$1801,2025)+SUMIFS('Data Cruda'!$P$2:$P$1801,'Data Cruda'!$D$2:$D$1801,"ALZA PERU PACKING S.A.C.",'Data Cruda'!$A$2:$A$1801,2026))/(SUMIFS('Data Cruda'!$K$2:$K$1801,'Data Cruda'!$D$2:$D$1801,"ALZA PERU PACKING S.A.C.",'Data Cruda'!$A$2:$A$1801,2025)+SUMIFS('Data Cruda'!$K$2:$K$1801,'Data Cruda'!$D$2:$D$1801,"ALZA PERU PACKING S.A.C.",'Data Cruda'!$A$2:$A$1801,2026)),0) -> 0.15 | F77: 5
A78: 22 | B78: VITAFOODS PERU S.A.C. | C78: 43470 | D78: 0.00068763169 | E78: =IFERROR((SUMIFS('Data Cruda'!$P$2:$P$1801,'Data Cruda'!$D$2:$D$1801,"VITAFOODS PERU S.A.C.",'Data Cruda'!$A$2:$A$1801,2025)+SUMIFS('Data Cruda'!$P$2:$P$1801,'Data Cruda'!$D$2:$D$1801,"VITAFOODS PERU S.A.C.",'Data Cruda'!$A$2:$A$1801,2026))/(SUMIFS('Data Cruda'!$K$2:$K$1801,'Data Cruda'!$D$2:$D$1801,"VITAFOODS PERU S.A.C.",'Data Cruda'!$A$2:$A$1801,2025)+SUMIFS('Data Cruda'!$K$2:$K$1801,'Data Cruda'!$D$2:$D$1801,"VITAFOODS PERU S.A.C.",'Data Cruda'!$A$2:$A$1801,2026)),0) -> 0.27075339 | F78: 2
A79: 23 | B79: EL ROCIO S.A. | C79: 37571.15 | D79: 0.00059432053 | E79: =IFERROR((SUMIFS('Data Cruda'!$P$2:$P$1801,'Data Cruda'!$D$2:$D$1801,"EL ROCIO S.A.",'Data Cruda'!$A$2:$A$1801,2025)+SUMIFS('Data Cruda'!$P$2:$P$1801,'Data Cruda'!$D$2:$D$1801,"EL ROCIO S.A.",'Data Cruda'!$A$2:$A$1801,2026))/(SUMIFS('Data Cruda'!$K$2:$K$1801,'Data Cruda'!$D$2:$D$1801,"EL ROCIO S.A.",'Data Cruda'!$A$2:$A$1801,2025)+SUMIFS('Data Cruda'!$K$2:$K$1801,'Data Cruda'!$D$2:$D$1801,"EL ROCIO S.A.",'Data Cruda'!$A$2:$A$1801,2026)),0) -> 0.056551144 | F79: 4
A80: 24 | B80: PACKING DEL CARMEN S.A.C. | C80: 36347.87 | D80: 0.00057497003 | E80: =IFERROR((SUMIFS('Data Cruda'!$P$2:$P$1801,'Data Cruda'!$D$2:$D$1801,"PACKING DEL CARMEN S.A.C.",'Data Cruda'!$A$2:$A$1801,2025)+SUMIFS('Data Cruda'!$P$2:$P$1801,'Data Cruda'!$D$2:$D$1801,"PACKING DEL CARMEN S.A.C.",'Data Cruda'!$A$2:$A$1801,2026))/(SUMIFS('Data Cruda'!$K$2:$K$1801,'Data Cruda'!$D$2:$D$1801,"PACKING DEL CARMEN S.A.C.",'Data Cruda'!$A$2:$A$1801,2025)+SUMIFS('Data Cruda'!$K$2:$K$1801,'Data Cruda'!$D$2:$D$1801,"PACKING DEL CARMEN S.A.C.",'Data Cruda'!$A$2:$A$1801,2026)),0) -> 0.17642327 | F80: 1
A81: 25 | B81: ARA EXPORT S.A.C. | C81: 34403.05 | D81: 0.00054420583 | E81: =IFERROR((SUMIFS('Data Cruda'!$P$2:$P$1801,'Data Cruda'!$D$2:$D$1801,"ARA EXPORT S.A.C.",'Data Cruda'!$A$2:$A$1801,2025)+SUMIFS('Data Cruda'!$P$2:$P$1801,'Data Cruda'!$D$2:$D$1801,"ARA EXPORT S.A.C.",'Data Cruda'!$A$2:$A$1801,2026))/(SUMIFS('Data Cruda'!$K$2:$K$1801,'Data Cruda'!$D$2:$D$1801,"ARA EXPORT S.A.C.",'Data Cruda'!$A$2:$A$1801,2025)+SUMIFS('Data Cruda'!$K$2:$K$1801,'Data Cruda'!$D$2:$D$1801,"ARA EXPORT S.A.C.",'Data Cruda'!$A$2:$A$1801,2026)),0) -> 0.15388607 | F81: 1
A82: 26 | B82: UVICA S.A.C. | C82: 33598.01 | D82: 0.00053147128 | E82: =IFERROR((SUMIFS('Data Cruda'!$P$2:$P$1801,'Data Cruda'!$D$2:$D$1801,"UVICA S.A.C.",'Data Cruda'!$A$2:$A$1801,2025)+SUMIFS('Data Cruda'!$P$2:$P$1801,'Data Cruda'!$D$2:$D$1801,"UVICA S.A.C.",'Data Cruda'!$A$2:$A$1801,2026))/(SUMIFS('Data Cruda'!$K$2:$K$1801,'Data Cruda'!$D$2:$D$1801,"UVICA S.A.C.",'Data Cruda'!$A$2:$A$1801,2025)+SUMIFS('Data Cruda'!$K$2:$K$1801,'Data Cruda'!$D$2:$D$1801,"UVICA S.A.C.",'Data Cruda'!$A$2:$A$1801,2026)),0) -> 0.1571471 | F82: 3
A83: 27 | B83: QUELEN FRUIT PERU S.A.C. | C83: 25500 | D83: 0.00040337263 | E83: =IFERROR((SUMIFS('Data Cruda'!$P$2:$P$1801,'Data Cruda'!$D$2:$D$1801,"QUELEN FRUIT PERU S.A.C.",'Data Cruda'!$A$2:$A$1801,2025)+SUMIFS('Data Cruda'!$P$2:$P$1801,'Data Cruda'!$D$2:$D$1801,"QUELEN FRUIT PERU S.A.C.",'Data Cruda'!$A$2:$A$1801,2026))/(SUMIFS('Data Cruda'!$K$2:$K$1801,'Data Cruda'!$D$2:$D$1801,"QUELEN FRUIT PERU S.A.C.",'Data Cruda'!$A$2:$A$1801,2025)+SUMIFS('Data Cruda'!$K$2:$K$1801,'Data Cruda'!$D$2:$D$1801,"QUELEN FRUIT PERU S.A.C.",'Data Cruda'!$A$2:$A$1801,2026)),0) -> 0.15 | F83: 1
A84: 28 | B84: TAL S A | C84: 17671.66 | D84: 0.00027953976 | E84: =IFERROR((SUMIFS('Data Cruda'!$P$2:$P$1801,'Data Cruda'!$D$2:$D$1801,"TAL S A",'Data Cruda'!$A$2:$A$1801,2025)+SUMIFS('Data Cruda'!$P$2:$P$1801,'Data Cruda'!$D$2:$D$1801,"TAL S A",'Data Cruda'!$A$2:$A$1801,2026))/(SUMIFS('Data Cruda'!$K$2:$K$1801,'Data Cruda'!$D$2:$D$1801,"TAL S A",'Data Cruda'!$A$2:$A$1801,2025)+SUMIFS('Data Cruda'!$K$2:$K$1801,'Data Cruda'!$D$2:$D$1801,"TAL S A",'Data Cruda'!$A$2:$A$1801,2026)),0) -> 0.24999972 | F84: 1
A85: 29 | B85: EL PARQUE ALAYA PACKING S.A.C. | C85: 15941.32 | D85: 0.00025216832 | E85: =IFERROR((SUMIFS('Data Cruda'!$P$2:$P$1801,'Data Cruda'!$D$2:$D$1801,"EL PARQUE ALAYA PACKING S.A.C.",'Data Cruda'!$A$2:$A$1801,2025)+SUMIFS('Data Cruda'!$P$2:$P$1801,'Data Cruda'!$D$2:$D$1801,"EL PARQUE ALAYA PACKING S.A.C.",'Data Cruda'!$A$2:$A$1801,2026))/(SUMIFS('Data Cruda'!$K$2:$K$1801,'Data Cruda'!$D$2:$D$1801,"EL PARQUE ALAYA PACKING S.A.C.",'Data Cruda'!$A$2:$A$1801,2025)+SUMIFS('Data Cruda'!$K$2:$K$1801,'Data Cruda'!$D$2:$D$1801,"EL PARQUE ALAYA PACKING S.A.C.",'Data Cruda'!$A$2:$A$1801,2026)),0) -> 0.13555465 | F85: 2
A86: 30 | B86: WESTFALIA FRUIT PERU S.A.C. | C86: 10000 | D86: 0.00015818534 | E86: =IFERROR((SUMIFS('Data Cruda'!$P$2:$P$1801,'Data Cruda'!$D$2:$D$1801,"WESTFALIA FRUIT PERU S.A.C.",'Data Cruda'!$A$2:$A$1801,2025)+SUMIFS('Data Cruda'!$P$2:$P$1801,'Data Cruda'!$D$2:$D$1801,"WESTFALIA FRUIT PERU S.A.C.",'Data Cruda'!$A$2:$A$1801,2026))/(SUMIFS('Data Cruda'!$K$2:$K$1801,'Data Cruda'!$D$2:$D$1801,"WESTFALIA FRUIT PERU S.A.C.",'Data Cruda'!$A$2:$A$1801,2025)+SUMIFS('Data Cruda'!$K$2:$K$1801,'Data Cruda'!$D$2:$D$1801,"WESTFALIA FRUIT PERU S.A.C.",'Data Cruda'!$A$2:$A$1801,2026)),0) -> 0.3 | F86: 1
A87: 31 | B87: CIA.DE EXP.Y NEGOCIOS GNRLES.S.A.(COEXA) | C87: 6840.69 | D87: 0.00010820969 | E87: =IFERROR((SUMIFS('Data Cruda'!$P$2:$P$1801,'Data Cruda'!$D$2:$D$1801,"CIA.DE EXP.Y NEGOCIOS GNRLES.S.A.(COEXA)",'Data Cruda'!$A$2:$A$1801,2025)+SUMIFS('Data Cruda'!$P$2:$P$1801,'Data Cruda'!$D$2:$D$1801,"CIA.DE EXP.Y NEGOCIOS GNRLES.S.A.(COEXA)",'Data Cruda'!$A$2:$A$1801,2026))/(SUMIFS('Data Cruda'!$K$2:$K$1801,'Data Cruda'!$D$2:$D$1801,"CIA.DE EXP.Y NEGOCIOS GNRLES.S.A.(COEXA)",'Data Cruda'!$A$2:$A$1801,2025)+SUMIFS('Data Cruda'!$K$2:$K$1801,'Data Cruda'!$D$2:$D$1801,"CIA.DE EXP.Y NEGOCIOS GNRLES.S.A.(COEXA)",'Data Cruda'!$A$2:$A$1801,2026)),0) -> 0.080648297 | F87: 1
A88: 32 | B88: AVOCADO PACKING COMPANY S.A.C. | C88: 4392.39 | D88: 6.9481173e-05 | E88: =IFERROR((SUMIFS('Data Cruda'!$P$2:$P$1801,'Data Cruda'!$D$2:$D$1801,"AVOCADO PACKING COMPANY S.A.C.",'Data Cruda'!$A$2:$A$1801,2025)+SUMIFS('Data Cruda'!$P$2:$P$1801,'Data Cruda'!$D$2:$D$1801,"AVOCADO PACKING COMPANY S.A.C.",'Data Cruda'!$A$2:$A$1801,2026))/(SUMIFS('Data Cruda'!$K$2:$K$1801,'Data Cruda'!$D$2:$D$1801,"AVOCADO PACKING COMPANY S.A.C.",'Data Cruda'!$A$2:$A$1801,2025)+SUMIFS('Data Cruda'!$K$2:$K$1801,'Data Cruda'!$D$2:$D$1801,"AVOCADO PACKING COMPANY S.A.C.",'Data Cruda'!$A$2:$A$1801,2026)),0) -> 0.19856843 | F88: 3
A89: 33 | B89: AGRICOLA BLUE GOLD S.A.C. | C89: 4265.26 | D89: 6.7470162e-05 | E89: =IFERROR((SUMIFS('Data Cruda'!$P$2:$P$1801,'Data Cruda'!$D$2:$D$1801,"AGRICOLA BLUE GOLD S.A.C.",'Data Cruda'!$A$2:$A$1801,2025)+SUMIFS('Data Cruda'!$P$2:$P$1801,'Data Cruda'!$D$2:$D$1801,"AGRICOLA BLUE GOLD S.A.C.",'Data Cruda'!$A$2:$A$1801,2026))/(SUMIFS('Data Cruda'!$K$2:$K$1801,'Data Cruda'!$D$2:$D$1801,"AGRICOLA BLUE GOLD S.A.C.",'Data Cruda'!$A$2:$A$1801,2025)+SUMIFS('Data Cruda'!$K$2:$K$1801,'Data Cruda'!$D$2:$D$1801,"AGRICOLA BLUE GOLD S.A.C.",'Data Cruda'!$A$2:$A$1801,2026)),0) -> 0.25209718 | F89: 1
A90: 34 | B90: AUSTRAL GROUP S.A.A | C90: 2310 | D90: 3.6540815e-05 | E90: =IFERROR((SUMIFS('Data Cruda'!$P$2:$P$1801,'Data Cruda'!$D$2:$D$1801,"AUSTRAL GROUP S.A.A",'Data Cruda'!$A$2:$A$1801,2025)+SUMIFS('Data Cruda'!$P$2:$P$1801,'Data Cruda'!$D$2:$D$1801,"AUSTRAL GROUP S.A.A",'Data Cruda'!$A$2:$A$1801,2026))/(SUMIFS('Data Cruda'!$K$2:$K$1801,'Data Cruda'!$D$2:$D$1801,"AUSTRAL GROUP S.A.A",'Data Cruda'!$A$2:$A$1801,2025)+SUMIFS('Data Cruda'!$K$2:$K$1801,'Data Cruda'!$D$2:$D$1801,"AUSTRAL GROUP S.A.A",'Data Cruda'!$A$2:$A$1801,2026)),0) -> 0.12941991 | F90: 1
A91: 35 | B91: STEELSER S.A.C. | C91: 2200 | D91: 3.4800776e-05 | E91: =IFERROR((SUMIFS('Data Cruda'!$P$2:$P$1801,'Data Cruda'!$D$2:$D$1801,"STEELSER S.A.C.",'Data Cruda'!$A$2:$A$1801,2025)+SUMIFS('Data Cruda'!$P$2:$P$1801,'Data Cruda'!$D$2:$D$1801,"STEELSER S.A.C.",'Data Cruda'!$A$2:$A$1801,2026))/(SUMIFS('Data Cruda'!$K$2:$K$1801,'Data Cruda'!$D$2:$D$1801,"STEELSER S.A.C.",'Data Cruda'!$A$2:$A$1801,2025)+SUMIFS('Data Cruda'!$K$2:$K$1801,'Data Cruda'!$D$2:$D$1801,"STEELSER S.A.C.",'Data Cruda'!$A$2:$A$1801,2026)),0) -> 0.19003182 | F91: 1
B92: Subtotal Classic | C92: 3284570.6 | D92: 0.051957093
A94: CATEGORÍAS POR MONTO FACTURADO HISTÓRICO 2014-2026
A96: Categoría | B96: # Clientes | C96: Monto Total | D96: % Particip.
A97: Platinum | B97: 60 | C97: 2.1604141e+08 | D97: 0.84779435
A98: Gold | B98: 55 | C98: 30087479 | D98: 0.11806993
A99: Classic | B99: 140 | C99: 8698724.7 | D99: 0.034135723
A100: TOTAL | B100: 255 | C100: 2.5482761e+08 | D100: 1
A102: DETALLE HISTÓRICO PLATINUM
A103: # | B103: Cliente | C103: Monto Total | D103: % del Total | E103: Años Activo | F103: # Reg
A104: 1 | B104: CORPORACION AGROLATINA S.A.C. | C104: 14074374 | D104: 0.055230961 | E104: 10 | F104: 30
A105: 2 | B105: AGROVISION PERU S.A.C. | C105: 12027997 | D105: 0.047200526 | E105: 9 | F105: 61
A106: 3 | B106: DANPER TRUJILLO S.A.C. | C106: 11318013 | D106: 0.04441439 | E106: 12 | F106: 53
A107: 4 | B107: VIRU S.A. | C107: 10204953 | D107: 0.040046496 | E107: 10 | F107: 79
...

Sheet 6. Segmentación Cartera
A1: SEGMENTACIÓN DE CARTERA 2025-2026
A2: Retenidos=activos 23-24 y 25-26 · Reactivados=activos antes de 2023, regresan en 25-26 · Nuevos=primera vez · Sin Actividad=activos 23-24 ausentes en 25-26
A4: Segmento | B4: # Clientes | C4: Monto | D4: % Particip. | E4: Margen Pond.
A5: Retenidos | B5: 29 | C5: 24540104 | D5: 0.38818848 | E5: =IFERROR(SUMPRODUCT(ISNUMBER(MATCH('Data Cruda'!$D$2:$D$1801,$B$13:$B$41,0))*(('Data Cruda'!$A$2:$A$1801=2025)+('Data Cruda'!$A$2:$A$1801=2026))*'Data Cruda'!$P$2:$P$1801)/SUMPRODUCT(ISNUMBER(MATCH('Data Cruda'!$D$2:$D$1801,$B$13:$B$41,0))*(('Data Cruda'!$A$2:$A$1801=2025)+('Data Cruda'!$A$2:$A$1801=2026))*'Data Cruda'!$K$2:$K$1801),0) -> 0.15972932
A6: Reactivados | B6: 10 | C6: 11925076 | D6: 0.18863723 | E6: =IFERROR(SUMPRODUCT(ISNUMBER(MATCH('Data Cruda'!$D$2:$D$1801,$B$46:$B$55,0))*(('Data Cruda'!$A$2:$A$1801=2025)+('Data Cruda'!$A$2:$A$1801=2026))*'Data Cruda'!$P$2:$P$1801)/SUMPRODUCT(ISNUMBER(MATCH('Data Cruda'!$D$2:$D$1801,$B$46:$B$55,0))*(('Data Cruda'!$A$2:$A$1801=2025)+('Data Cruda'!$A$2:$A$1801=2026))*'Data Cruda'!$K$2:$K$1801),0) -> 0.15202601
A7: Nuevos | B7: 34 | C7: 26751801 | D7: 0.42317429 | E7: =IFERROR(SUMPRODUCT(ISNUMBER(MATCH('Data Cruda'!$D$2:$D$1801,$B$60:$B$93,0))*(('Data Cruda'!$A$2:$A$1801=2025)+('Data Cruda'!$A$2:$A$1801=2026))*'Data Cruda'!$P$2:$P$1801)/SUMPRODUCT(ISNUMBER(MATCH('Data Cruda'!$D$2:$D$1801,$B$60:$B$93,0))*(('Data Cruda'!$A$2:$A$1801=2025)+('Data Cruda'!$A$2:$A$1801=2026))*'Data Cruda'!$K$2:$K$1801),0) -> 0.15790678
A8: Sin Actividad | B8: 33 | C8: 9568845.3 | D8: 0.15136511 | E8: =IFERROR(SUMPRODUCT(ISNUMBER(MATCH('Data Cruda'!$D$2:$D$1801,$B$98:$B$130,0))*(('Data Cruda'!$A$2:$A$1801=2023)+('Data Cruda'!$A$2:$A$1801=2024))*'Data Cruda'!$P$2:$P$1801)/SUMPRODUCT(ISNUMBER(MATCH('Data Cruda'!$D$2:$D$1801,$B$98:$B$130,0))*(('Data Cruda'!$A$2:$A$1801=2023)+('Data Cruda'!$A$2:$A$1801=2024))*'Data Cruda'!$K$2:$K$1801),0) -> 0.15692621
A9: TOTAL | B9: 106 | C9: 72785827 | D9: 1
A11: DETALLE: RETENIDOS
A12: # | B12: Cliente | C12: Monto 25-26 | D12: Zona | E12: Sector Principal
A13: 1 | B13: DANPER TRUJILLO S.A.C. | C13: 4485901 | D13: NORTE | E13: ARANDANOS
A14: 2 | B14: CORPORACION AGROLATINA S.A.C. | C14: 4450000 | D14: SUR | E14: UVA
A15: 3 | B15: AQU ANQA S.A.C. | C15: 3356000.7 | D15: NORTE | E15: ARANDANOS
A16: 4 | B16: SOCIEDAD AGRICOLA DROKASA S.A. | C16: 1629602.3 | D16: SUR | E16: OTROS
A17: 5 | B17: AGRICOLA ALAYA SOCIEDAD ANONIMA CERRADA | C17: 1490360.7 | D17: NORTE | E17: ARANDANOS
A18: 6 | B18: AGROINDUSTRIAS AIB S.A | C18: 1088057.2 | D18: SUR | E18: OTROS
A19: 7 | B19: EL PEDREGAL S.A. | C19: 954731.07 | D19: NORTE | E19: ARANDANOS
A20: 8 | B20: PROCESADORA LARAN SAC | C20: 910903.47 | D20: SUR | E20: ARANDANOS
A21: 9 | B21: AGROVISION PERU S.A.C. | C21: 817031.34 | D21: NORTE | E21: ARANDANOS
A22: 10 | B22: AGROCASAGRANDE S.A.C. | C22: 785287.51 | D22: NORTE | E22: ARANDANOS
A23: 11 | B23: PROCESADORA TORRE BLANCA S.A.C | C23: 721156.89 | D23: CENTRO | E23: CITRICOS
A24: 12 | B24: AGROBUSINESS INTERNATIONAL PERU S.A.C. | C24: 602333.49 | D24: NORTE | E24: ARANDANOS
... A41: 29 | B41: AGRICOLA BLUE GOLD S.A.C. | C41: 4265.26 | D41: NORTE | E41: OTROS
B42: Subtotal Retenidos | C42: 24540104
A44: DETALLE: REACTIVADOS
A45: # | B45: Cliente | C45: Monto 25-26 | D45: Zona | E45: Sector Principal
A46: 1 | B46: AGRICOLA HUARMEY S.A. | C46: 4008997 | D46: NORTE | E46: ARANDANOS
A47: 2 | B47: BOMAREA S.R.L. | C47: 3162368.8 | D47: NORTE | E47: ARANDANOS
A48: 3 | B48: TAL S.A. | C48: 2072732.8 | D48: NORTE | E48: ARANDANOS
A49: 4 | B49: AGRICOLA PAMPA BAJA S.A.C. | C49: 1224885.8 | D49: SUR | E49: OTROS
A50: 5 | B50: SANTA SOFIA DEL SUR S.A.C. | C50: 550187.52 | D50: SUR | E50: CITRICOS
A51: 6 | B51: CONSORCIO AGRICOLA MOQUEGUA S.A.C. | C51: 232667.9 | D51: SUR | E51: ARANDANOS
A52: 7 | B52: T & T FRUITS S.A. | C52: 227719.49 | D52: CENTRO | E52: CITRICOS
A53: 8 | B53: VIVEROS EL TAMBO S.A.C. | C53: 216754.9 | D53: NORTE | E53: OTROS
A54: 9 | B54: EMPRESA AGRICOLA SAN JUAN S.A | C54: 194358.88 | D54: NORTE | E54: PALTA
A55: 10 | B55: ARA EXPORT S.A.C. | C55: 34403.05 | D55: NORTE | E55: OTROS
B56: Subtotal Reactivados | C56: 11925076
A58: DETALLE: NUEVOS
A59: # | B59: Cliente | C59: Monto 25-26 | D59: Zona | E59: Sector Principal
A60: 1 | B60: AGROBERRIES PERU S.A.C. | C60: 10141560 | D60: NORTE | E60: ARANDANOS
A61: 2 | B61: PROSEMBRA SOCIEDAD ANONIMA CERRADA | C61: 3632242.2 | D61: SUR | E61: ARANDANOS
A62: 3 | B62: Q PACK S.A.C. | C62: 2949135.6 | D62: NORTE | E62: ARANDANOS
A63: 4 | B63: PROCESOS AGROINDUSTRIALES SOCIEDAD ANONIMA | C63: 2034100.6 | D63: SUR | E63: UVA
A64: 5 | B64: TA EXPORT S.A.C. | C64: 1460000 | D64: SUR | E64: ARANDANOS
A65: 6 | B65: ARA FOODS INDUSTRY S.A.C. | C65: 905597.47 | D65: NORTE | E65: PALTA
A66: 7 | B66: IMBAREX S.A. | C66: 853450 | D66: SUR | E66: ARANDANOS
A67: 8 | B67: AGROINDUSTRIA FRUTOS DE ORO S.A.C. | C67: 508072.36 | D67: NORTE | E67: MANGO
A68: 9 | B68: ESTANTERIAS METALICAS J.R.M. S.A.C | C68: 455000 | D68: SUR | E68: OTROS
A69: 10 | B69: DELICE S.A.C | C69: 427469.32 | D69: CENTRO | E69: QUESO
A70: 11 | B70: BERRY HARVEST S.A. | C70: 402750.72 | D70: NORTE | E70: OTROS
A71: 12 | B71: DIAMOND BRIDGE SAC | C71: 321860.28 | D71: SUR | E71: ARANDANOS
... A93: 34 | B93: STEELSER S.A.C. | C93: 2200 | D93: NORTE | E93: OTROS
B94: Subtotal Nuevos | C94: 26751801
A96: DETALLE: SIN ACTIVIDAD
A97: # | B97: Cliente | C97: Monto 23-24 | D97: Último Año | E97: Zona
A98: 1 | B98: AGRICOLA DON RICARDO S.A.C. | C98: 2018854.2 | D98: 2024 | E98: SUR
A99: 2 | B99: SUNSHINE EXPORT S.A.C. | C99: 1786003.5 | D99: 2024 | E99: NORTE
A100: 3 | B100: AGROFUTURA COMPANY S.A.C. | C100: 1307823.4 | D100: 2024 | E100: NORTE
A101: 4 | B101: AGROINDUSTRIAL ESTANISLAO DEL CHIMU S.A.C. | C101: 1136822.7 | D101: 2024 | E101: NORTE
A102: 5 | B102: MEGACENTRO LURIN S.A.C. | C102: 576750.25 | D102: 2024 | E102: CENTRO
A103: 6 | B103: AGRICOLA CHAPI SA | C103: 538363.61 | D103: 2024 | E103: SUR
A104: 7 | B104: AXIONLOG PERU S.A.C. | C104: 517370 | D104: 2023 | E104: CENTRO
A105: 8 | B105: AGROINDUSTRIAS HUARAL SOCIEDAD ANONIMA CERRADA | C105: 399766.95 | D105: 2024 | E105: CENTRO
A106: 9 | B106: PACIFIC OCEAN BERRIES S.A.C. | C106: 294669.9 | D106: 2024 | E106: SUR
A107: 10 | B107: MANUELITA FYH S.A.C. | C107: 219792 | D107: 2024 | E107: SUR
A108: 11 | B108: MEDLOG PIURA SAC | C108: 209899.57 | D108: 2024 | E108: NORTE
A109: 12 | B109: SEED FOOD SOCIEDAD ANONIMA CERRADA | C109: 205000 | D109: 2024 | E109: CENTRO
... A130: 33 | B130: FRIOTEAM S.A.C. | C130: 440 | D130: 2024 | E130: SUR
B131: Subtotal Sin Actividad | C131: 9568845.3

Sheet 7. Análisis por Zona
A1: TABLA 1 – VENTAS ANUALES POR ZONA (RESUMEN)
A3: Año | B3: Zona | C3: Monto Total | D3: Margen % | E3: % Particip. Año
A4: 2021 | B4: Centro | C4: 4489914.4 | D4: =IFERROR(SUMIFS('Data Cruda'!$P$2:$P$1801,'Data Cruda'!$A$2:$A$1801,2021,'Data Cruda'!$G$2:$G$1801,"CENTRO")/SUMIFS('Data Cruda'!$K$2:$K$1801,'Data Cruda'!$A$2:$A$1801,2021,'Data Cruda'!$G$2:$G$1801,"CENTRO"),0) -> 0.15006527 | E4: 0.22106326
A5: 2021 | B5: Norte | C5: 9124292.2 | D5: =IFERROR(SUMIFS('Data Cruda'!$P$2:$P$1801,'Data Cruda'!$A$2:$A$1801,2021,'Data Cruda'!$G$2:$G$1801,"NORTE")/SUMIFS('Data Cruda'!$K$2:$K$1801,'Data Cruda'!$A$2:$A$1801,2021,'Data Cruda'!$G$2:$G$1801,"NORTE"),0) -> 0.11767554 | E5: 0.44923925
A6: 2021 | B6: Sur | C6: 6696334.6 | D6: =IFERROR(SUMIFS('Data Cruda'!$P$2:$P$1801,'Data Cruda'!$A$2:$A$1801,2021,'Data Cruda'!$G$2:$G$1801,"SUR")/SUMIFS('Data Cruda'!$K$2:$K$1801,'Data Cruda'!$A$2:$A$1801,2021,'Data Cruda'!$G$2:$G$1801,"SUR"),0) -> 0.14644849 | E6: 0.3296975
A7: Total 2021 | C7: 20310541 | D7: =IFERROR(SUMIFS('Data Cruda'!$P$2:$P$1801,'Data Cruda'!$A$2:$A$1801,2021)/SUMIFS('Data Cruda'!$K$2:$K$1801,'Data Cruda'!$A$2:$A$1801,2021),0) -> 0.13432209 | E7: 1
A8: 2022 | B8: Centro | C8: 6626687.1 | D8: =IFERROR(SUMIFS('Data Cruda'!$P$2:$P$1801,'Data Cruda'!$A$2:$A$1801,2022,'Data Cruda'!$G$2:$G$1801,"CENTRO")/SUMIFS('Data Cruda'!$K$2:$K$1801,'Data Cruda'!$A$2:$A$1801,2022,'Data Cruda'!$G$2:$G$1801,"CENTRO"),0) -> 0.12114727 | E8: 0.19960043
A9: 2022 | B9: Norte | C9: 13676856 | D9: =IFERROR(SUMIFS('Data Cruda'!$P$2:$P$1801,'Data Cruda'!$A$2:$A$1801,2022,'Data Cruda'!$G$2:$G$1801,"NORTE")/SUMIFS('Data Cruda'!$K$2:$K$1801,'Data Cruda'!$A$2:$A$1801,2022,'Data Cruda'!$G$2:$G$1801,"NORTE"),0) -> 0.15834046 | E9: 0.41195641
A10: 2022 | B10: Sur | C10: 12896222 | D10: =IFERROR(SUMIFS('Data Cruda'!$P$2:$P$1801,'Data Cruda'!$A$2:$A$1801,2022,'Data Cruda'!$G$2:$G$1801,"SUR")/SUMIFS('Data Cruda'!$K$2:$K$1801,'Data Cruda'!$A$2:$A$1801,2022,'Data Cruda'!$G$2:$G$1801,"SUR"),0) -> 0.132868 | E10: 0.38844316
A11: Total 2022 | C11: 33199765 | D11: =IFERROR(SUMIFS('Data Cruda'!$P$2:$P$1801,'Data Cruda'!$A$2:$A$1801,2022)/SUMIFS('Data Cruda'!$K$2:$K$1801,'Data Cruda'!$A$2:$A$1801,2022),0) -> 0.14102208 | E11: 1
A12: 2023 | B12: Centro | C12: 1686953.1 | D12: =IFERROR(SUMIFS('Data Cruda'!$P$2:$P$1801,'Data Cruda'!$A$2:$A$1801,2023,'Data Cruda'!$G$2:$G$1801,"CENTRO")/SUMIFS('Data Cruda'!$K$2:$K$1801,'Data Cruda'!$A$2:$A$1801,2023,'Data Cruda'!$G$2:$G$1801,"CENTRO"),0) -> 0.1796244 | E12: 0.11033499
A13: 2023 | B13: Norte | C13: 6966480.7 | D13: =IFERROR(SUMIFS('Data Cruda'!$P$2:$P$1801,'Data Cruda'!$A$2:$A$1801,2023,'Data Cruda'!$G$2:$G$1801,"NORTE")/SUMIFS('Data Cruda'!$K$2:$K$1801,'Data Cruda'!$A$2:$A$1801,2023,'Data Cruda'!$G$2:$G$1801,"NORTE"),0) -> 0.1715229 | E13: 0.45564196
A14: 2023 | B14: Sur | C14: 6635941.1 | D14: =IFERROR(SUMIFS('Data Cruda'!$P$2:$P$1801,'Data Cruda'!$A$2:$A$1801,2023,'Data Cruda'!$G$2:$G$1801,"SUR")/SUMIFS('Data Cruda'!$K$2:$K$1801,'Data Cruda'!$A$2:$A$1801,2023,'Data Cruda'!$G$2:$G$1801,"SUR"),0) -> 0.16806805 | E14: 0.43402305
A15: Total 2023 | C15: 15289375 | D15: =IFERROR(SUMIFS('Data Cruda'!$P$2:$P$1801,'Data Cruda'!$A$2:$A$1801,2023)/SUMIFS('Data Cruda'!$K$2:$K$1801,'Data Cruda'!$A$2:$A$1801,2023),0) -> 0.17091729 | E15: 1
A16: 2024 | B16: Centro | C16: 2668843 | D16: =IFERROR(SUMIFS('Data Cruda'!$P$2:$P$1801,'Data Cruda'!$A$2:$A$1801,2024,'Data Cruda'!$G$2:$G$1801,"CENTRO")/SUMIFS('Data Cruda'!$K$2:$K$1801,'Data Cruda'!$A$2:$A$1801,2024,'Data Cruda'!$G$2:$G$1801,"CENTRO"),0) -> 0.16365262 | E16: 0.1727278
A17: 2024 | B17: Norte | C17: 6253794.6 | D17: =IFERROR(SUMIFS('Data Cruda'!$P$2:$P$1801,'Data Cruda'!$A$2:$A$1801,2024,'Data Cruda'!$G$2:$G$1801,"NORTE")/SUMIFS('Data Cruda'!$K$2:$K$1801,'Data Cruda'!$A$2:$A$1801,2024,'Data Cruda'!$G$2:$G$1801,"NORTE"),0) -> 0.14167196 | E17: 0.40474624
A18: 2024 | B18: Sur | C18: 6528511.7 | D18: =IFERROR(SUMIFS('Data Cruda'!$P$2:$P$1801,'Data Cruda'!$A$2:$A$1801,2024,'Data Cruda'!$G$2:$G$1801,"SUR")/SUMIFS('Data Cruda'!$K$2:$K$1801,'Data Cruda'!$A$2:$A$1801,2024,'Data Cruda'!$G$2:$G$1801,"SUR"),0) -> 0.15949725 | E18: 0.42252596
A19: Total 2024 | C19: 15451149 | D19: =IFERROR(SUMIFS('Data Cruda'!$P$2:$P$1801,'Data Cruda'!$A$2:$A$1801,2024)/SUMIFS('Data Cruda'!$K$2:$K$1801,'Data Cruda'!$A$2:$A$1801,2024),0) -> 0.15300028 | E19: 1
A20: 2025 | B20: Centro | C20: 1710978.1 | D20: =IFERROR(SUMIFS('Data Cruda'!$P$2:$P$1801,'Data Cruda'!$A$2:$A$1801,2025,'Data Cruda'!$G$2:$G$1801,"CENTRO")/SUMIFS('Data Cruda'!$K$2:$K$1801,'Data Cruda'!$A$2:$A$1801,2025,'Data Cruda'!$G$2:$G$1801,"CENTRO"),0) -> 0.14790441 | E20: 0.048946166
A21: 2025 | B21: Norte | C21: 22237407 | D21: =IFERROR(SUMIFS('Data Cruda'!$P$2:$P$1801,'Data Cruda'!$A$2:$A$1801,2025,'Data Cruda'!$G$2:$G$1801,"NORTE")/SUMIFS('Data Cruda'!$K$2:$K$1801,'Data Cruda'!$A$2:$A$1801,2025,'Data Cruda'!$G$2:$G$1801,"NORTE"),0) -> 0.1672791 | E21: 0.63614831
A22: 2025 | B22: Sur | C22: 11007940 | D22: =IFERROR(SUMIFS('Data Cruda'!$P$2:$P$1801,'Data Cruda'!$A$2:$A$1801,2025,'Data Cruda'!$G$2:$G$1801,"SUR")/SUMIFS('Data Cruda'!$K$2:$K$1801,'Data Cruda'!$A$2:$A$1801,2025,'Data Cruda'!$G$2:$G$1801,"SUR"),0) -> 0.15024434 | E22: 0.31490553
A23: Total 2025 | C23: 34956324 | D23: =IFERROR(SUMIFS('Data Cruda'!$P$2:$P$1801,'Data Cruda'!$A$2:$A$1801,2025)/SUMIFS('Data Cruda'!$K$2:$K$1801,'Data Cruda'!$A$2:$A$1801,2025),0) -> 0.16103777 | E23: 1
A24: 2026 | B24: Centro | C24: 1525584.6 | D24: =IFERROR(SUMIFS('Data Cruda'!$P$2:$P$1801,'Data Cruda'!$A$2:$A$1801,2026,'Data Cruda'!$G$2:$G$1801,"CENTRO")/SUMIFS('Data Cruda'!$K$2:$K$1801,'Data Cruda'!$A$2:$A$1801,2026,'Data Cruda'!$G$2:$G$1801,"CENTRO"),0) -> 0.17838477 | E24: 0.053982629
A25: 2026 | B25: Norte | C25: 17071546 | D25: =IFERROR(SUMIFS('Data Cruda'!$P$2:$P$1801,'Data Cruda'!$A$2:$A$1801,2026,'Data Cruda'!$G$2:$G$1801,"NORTE")/SUMIFS('Data Cruda'!$K$2:$K$1801,'Data Cruda'!$A$2:$A$1801,2026,'Data Cruda'!$G$2:$G$1801,"NORTE"),0) -> 0.14395747 | E25: 0.60407462
A26: 2026 | B26: Sur | C26: 9663526.7 | D26: =IFERROR(SUMIFS('Data Cruda'!$P$2:$P$1801,'Data Cruda'!$A$2:$A$1801,2026,'Data Cruda'!$G$2:$G$1801,"SUR")/SUMIFS('Data Cruda'!$K$2:$K$1801,'Data Cruda'!$A$2:$A$1801,2026,'Data Cruda'!$G$2:$G$1801,"SUR"),0) -> 0.16542355 | E26: 0.34194275
A27: Total 2026 | C27: 28260657 | D27: =IFERROR(SUMIFS('Data Cruda'!$P$2:$P$1801,'Data Cruda'!$A$2:$A$1801,2026)/SUMIFS('Data Cruda'!$K$2:$K$1801,'Data Cruda'!$A$2:$A$1801,2026),0) -> 0.15315612 | E27: 1
A30: TABLA 2 – DESGLOSE MENSUAL POR ZONA
A32: Año | B32: Zona | C32: Ene | D32: Feb | E32: Mar | F32: Abr | G32: May | H32: Jun | I32: Jul | J32: Ago | K32: Sep | L32: Oct | M32: Nov | N32: Dic | O32: Total Año
A33: 2021 | B33: Centro | C33: 385222.91 | D33: 706847.04 | E33: 133807 | F33: 2826.3795 | G33: 791516.35 | H33: 1851.08 | I33: 259401.74 | J33: 0 | K33: 974211.47 | L33: 100 | M33: 569506.15 | N33: 664624.24 | O33: =SUM(C33:N33) -> 4489914.4
A34: 2021 | B34: Norte | C34: 1073934.3 | D34: 257020.01 | E34: 379433.29 | F34: 2041743.6 | G34: 1559151.7 | H34: 482826.98 | I34: 1024067.2 | J34: 488536.26 | K34: 150223.53 | L34: 20342.96 | M34: 312581.36 | N34: 1334431 | O34: =SUM(C34:N34) -> 9124292.2
A35: 2021 | B35: Sur | C35: 351235.81 | D35: 125364.75 | E35: 603630.03 | F35: 23923.4 | G35: 154473.32 | H35: 3104705.9 | I35: 633758.92 | J35: 651704.71 | K35: 151579.59 | L35: 13555.44 | M35: 266117.77 | N35: 616285.02 | O35: =SUM(C35:N35) -> 6696334.6
A36: Total 2021 | C36: =SUM(C33:C35) -> 1810393 | D36: =SUM(D33:D35) -> 1089231.8 | E36: =SUM(E33:E35) -> 1116870.3 | F36: =SUM(F33:F35) -> 2068493.4 | G36: =SUM(G33:G35) -> 2505141.4 | H36: =SUM(H33:H35) -> 3589383.9 | I36: =SUM(I33:I35) -> 1917227.9 | J36: =SUM(J33:J35) -> 1140241 | ... N36: =SUM(N33:N35) -> 2615340.2 | O36: =SUM(C36:N36) -> 20310541
A37: Acum. | C37: =C36 -> 1810393 | D37: =C37+D36 -> 2899624.8 | E37: =D37+E36 -> 4016495.1 | F37: =E37+F36 -> 6084988.5 | G37: =F37+G36 -> 8590129.9 | H37: =G37+H36 -> 12179514 | I37: =H37+I36 -> 14096742 | J37: =I37+J36 -> 15236983 | K37: =J37+K36 -> 16512997 | ... N37: =M37+N36 -> 20310541 | O37: =N37 -> 20310541
A38: 2022 | B38: Centro | C38: 124425.02 | D38: 107516.64 | E38: 16979.1 | F38: 1084628.6 | G38: 19072.36 | H38: 340751.56 | I38: 146621.1 | J38: 20754.29 | K38: 50056.05 | L38: 0 | M38: 292200 | N38: 4423682.4 | O38: =SUM(C38:N38) -> 6626687.1
A39: 2022 | B39: Norte | C39: 57346.68 | D39: 3433230.4 | E39: 215659.97 | F39: 2585749.8 | G39: 4144791.5 | H39: 100194.41 | I39: 141924.43 | J39: 1721570.6 | K39: 1123247.1 | L39: 17429.07 | M39: 133299.09 | N39: 2412.86 | O39: =SUM(C39:N39) -> 13676856
A40: 2022 | B40: Sur | C40: 47985 | D40: 331088.52 | E40: 3369477 | F40: 2560179.9 | G40: 1059071 | H40: 986843.92 | I40: 3187916 | J40: 127888.56 | K40: 39315.67 | L40: 124870.59 | M40: 879990.48 | N40: 181594.89 | O40: =SUM(C40:N40) -> 12896222
A41: Total 2022 | C41: =SUM(C38:C40) -> 229756.7 | D41: =SUM(D38:D40) -> 3871835.6 | E41: =SUM(E38:E40) -> 3602116.1 | F41: =SUM(F38:F40) -> 6230558.3 | G41: =SUM(G38:G40) -> 5222934.9 | H41: =SUM(H38:H40) -> 1427789.9 | I41: =SUM(I38:I40) -> 3476461.5 | J41: =SUM(J38:J40) -> 1870213.4 | ... N41: =SUM(N38:N40) -> 4607690.2 | O41: =SUM(C41:N41) -> 33199765
A42: Acum. | C42: =C41 -> 229756.7 | D42: =C42+D41 -> 4101592.3 | E42: =D42+E41 -> 7703708.4 | F42: =E42+F41 -> 13934267 | G42: =F42+G41 -> 19157202 | H42: =G42+H41 -> 20584991 | I42: =H42+I41 -> 24061453 | J42: =I42+J41 -> 25931666 | K42: =J42+K41 -> 27144285 | ... N42: =M42+N41 -> 33199765 | O42: =N42 -> 33199765
A43: 2023 | B43: Centro | C43: 0 | D43: 256150.88 | E43: 36754.65 | F43: 13716.67 | G43: 522197.54 | H43: 121000 | I43: 550208.11 | J43: 63970.28 | K43: 7551.43 | L43: 4745.08 | M43: 88658.44 | N43: 22000 | O43: =SUM(C43:N43) -> 1686953.1
A44: 2023 | B44: Norte | C44: 388659.04 | D44: 11673.66 | E44: 2147024.5 | F44: 1699793.7 | G44: 343574.61 | H44: 132426.36 | I44: 2925 | J44: 640312.52 | K44: 6250.8 | L44: 3357.14 | M44: 31020.94 | N44: 1559462.4 | O44: =SUM(C44:N44) -> 6966480.7
A45: 2023 | B45: Sur | C45: 284435.87 | D45: 248691.98 | E45: 226787.04 | F45: 15878.41 | G45: 1905290.6 | H45: 739661.05 | I45: 950600.04 | J45: 335505.07 | K45: 13975.541 | L45: 586374.87 | M45: 1293462.1 | N45: 35278.508 | O45: =SUM(C45:N45) -> 6635941.1
A46: Total 2023 | C46: =SUM(C43:C45) -> 673094.91 | D46: =SUM(D43:D45) -> 516516.52 | E46: =SUM(E43:E45) -> 2410566.1 | F46: =SUM(F43:F45) -> 1729388.8 | G46: =SUM(G43:G45) -> 2771062.7 | H46: =SUM(H43:H45) -> 993087.41 | I46: =SUM(I43:I45) -> 1503733.1 | J46: =SUM(J43:J45) -> 1039787.9 | ... N46: =SUM(N43:N45) -> 1616740.9 | O46: =SUM(C46:N46) -> 15289375
A47: Acum. | C47: =C46 -> 673094.91 | D47: =C47+D46 -> 1189611.4 | E47: =D47+E46 -> 3600177.6 | F47: =E47+F46 -> 5329566.4 | G47: =F47+G46 -> 8100629.1 | H47: =G47+H46 -> 9093716.5 | I47: =H47+I46 -> 10597450 | J47: =I47+J46 -> 11637238 | K47: =J47+K46 -> 11665015 | ... N47: =M47+N46 -> 15289375 | O47: =N47 -> 15289375
A48: 2024 | B48: Centro | C48: 3046.68 | D48: 505513.81 | E48: 6656.84 | F48: 5052 | G48: 1404340.3 | H48: 55024.88 | I48: 0 | J48: 205000 | K48: 79941.09 | L48: 0 | M48: 404267.45 | N48: 0 | O48: =SUM(C48:N48) -> 2668843
A49: 2024 | B49: Norte | C49: 18480 | D49: 371628.54 | E49: 2331664.8 | F49: 1599787.6 | G49: 192552.85 | H49: 6405 | I49: 1238260.9 | J49: 65145.301 | K49: 222055.79 | L49: 135702.37 | M49: 60850.59 | N49: 11260.89 | O49: =SUM(C49:N49) -> 6253794.6
A50: 2024 | B50: Sur | C50: 55493.04 | D50: 291469.9 | E50: 1252435 | F50: 22029.18 | G50: 1518894.6 | H50: 1095399.6 | I50: 324255 | J50: 308440.42 | K50: 32652 | L50: 1536495.4 | M50: 5646.34 | N50: 85301.18 | O50: =SUM(C50:N50) -> 6528511.7
A51: Total 2024 | C51: =SUM(C48:C50) -> 77019.72 | D51: =SUM(D48:D50) -> 1168612.2 | E51: =SUM(E48:E50) -> 3590756.6 | F51: =SUM(F48:F50) -> 1626868.8 | G51: =SUM(G48:G50) -> 3115787.7 | H51: =SUM(H48:H50) -> 1156829.5 | I51: =SUM(I48:I50) -> 1562515.9 | J51: =SUM(J48:J50) -> 578585.72 | ... N51: =SUM(N48:N50) -> 96562.07 | O51: =SUM(C51:N51) -> 15451149
A52: Acum. | C52: =C51 -> 77019.72 | D52: =C52+D51 -> 1245632 | E52: =D52+E51 -> 4836388.6 | F52: =E52+F51 -> 6463257.4 | G52: =F52+G51 -> 9579045.1 | H52: =G52+H51 -> 10735875 | I52: =H52+I51 -> 12298390 | J52: =I52+J51 -> 12876976 | K52: =J52+K51 -> 13211625 | ... N52: =M52+N51 -> 15451149 | O52: =N52 -> 15451149
A53: 2025 | B53: Centro | C53: 0 | D53: 3092.21 | E53: 38670.36 | F53: 117308 | G53: 417229.33 | H53: 0 | I53: 159825.42 | J53: 99000 | K53: 0 | L53: 514966.62 | M53: 0 | N53: 360886.11 | O53: =SUM(C53:N53) -> 1710978
A54: 2025 | B54: Norte | C54: 3882.39 | D54: 1081788.6 | E54: 4713414.8 | F54: 3672248.7 | G54: 1407723.8 | H54: 2139803.6 | I54: 412648.39 | J54: 1136674 | K54: 4050638.3 | L54: 1446018.5 | M54: 2162000 | N54: 10565.61 | O54: =SUM(C54:N54) -> 22237407
A55: 2025 | B55: Sur | C55: 193369.01 | D55: 11340 | E55: 1863332.9 | F55: 818126.67 | G55: 598481.58 | H55: 2134822 | I55: 315785.25 | J55: 4117456.5 | K55: 21201.56 | L55: 31474.11 | M55: 270240.99 | N55: 632309.11 | O55: =SUM(C55:N55) -> 11007940
A56: Total 2025 | C56: =SUM(C53:C55) -> 197251.4 | D56: =SUM(D53:D55) -> 1096220.8 | E56: =SUM(E53:E55) -> 6615418.1 | F56: =SUM(F53:F55) -> 4607683.4 | G56: =SUM(G53:G55) -> 2423434.7 | H56: =SUM(H53:H55) -> 4274625.6 | I56: =SUM(I53:I55) -> 888259.06 | J56: =SUM(J53:J55) -> 5353130.5 | ... N56: =SUM(N53:N55) -> 1003760.8 | O56: =SUM(C56:N56) -> 34956324
A57: Acum. | C57: =C56 -> 197251.4 | D57: =C57+D56 -> 1293472.2 | E57: =D57+E56 -> 7908890.3 | F57: =E57+F56 -> 12516574 | G57: =F57+G56 -> 14940008 | H57: =G57+H56 -> 19214634 | I57: =H57+I56 -> 20102893 | J57: =I57+J56 -> 25456024 | K57: =J57+K56 -> 29527863 | ... N57: =M57+N56 -> 34956324 | O57: =N57 -> 34956324
A58: 2026 | B58: Centro | C58: 946217.79 | D58: 41690 | E58: 0 | F58: 144516.37 | G58: 382560.42 | H58: 10600 | I58: 0 | J58: 0 | K58: 0 | L58: 0 | M58: 0 | N58: 0 | O58: =SUM(C58:N58) -> 1525584.6
A59: 2026 | B59: Norte | C59: 3200000 | D59: 1837981.8 | E59: 292455.06 | F59: 187218.78 | G59: 11543568 | H59: 10321.66 | I59: 0 | J59: 0 | K59: 0 | L59: 0 | M59: 0 | N59: 0 | O59: =SUM(C59:N59) -> 17071546
A60: 2026 | B60: Sur | C60: 215798 | D60: 1698898.1 | E60: 189083.49 | F60: 3935327 | G60: 1118762.6 | H60: 2505657.6 | I60: 0 | J60: 0 | K60: 0 | L60: 0 | M60: 0 | N60: 0 | O60: =SUM(C60:N60) -> 9663526.7
A61: Total 2026 | C61: =SUM(C58:C60) -> 4362015.8 | D61: =SUM(D58:D60) -> 3578569.9 | E61: =SUM(E58:E60) -> 481538.55 | F61: =SUM(F58:F60) -> 4267062.1 | G61: =SUM(G58:G60) -> 13044891 | H61: =SUM(H58:H60) -> 2526579.3 | I61: =SUM(I58:I60) -> 0 | J61: =SUM(J58:J60) -> 0 | ... N61: =SUM(N58:N60) -> 0 | O61: =SUM(C61:N61) -> 28260657
A62: Acum. | C62: =C61 -> 4362015.8 | D62: =C62+D61 -> 7940585.7 | E62: =D62+E61 -> 8422124.2 | F62: =E62+F61 -> 12689186 | G62: =F62+G61 -> 25734078 | H62: =G62+H61 -> 28260657 | I62: =H62+I61 -> 28260657 | J62: =I62+J61 -> 28260657 | K62: =J62+K61 -> 28260657 | ... N62: =M62+N61 -> 28260657 | O62: =N62 -> 28260657

Sheet 8. Estacionalidad
A1: TABLA 1 – EVOLUCIÓN % MENSUAL POR AÑO
A3: Año | B3: Ene | C3: Feb | D3: Mar | E3: Abr | F3: May | G3: Jun | H3: Jul | I3: Ago | J3: Sep | K3: Oct | L3: Nov | M3: Dic | N3: Total
A4: 2021 | B4: 0.089135635 | C4: 0.053628891 | D4: 0.054989688 | E4: 0.10184334 | F4: 0.12334193 | G4: 0.17672517 | H4: 0.094395706 | I4: 0.056140354 | J4: 0.062825238 | K4: 0.0016739288 | L4: 0.056532481 | M4: 0.12876763 | N4: 1
A5: 2022 | B5: 0.0069204316 | C5: 0.11662238 | D5: 0.10849824 | E5: 0.18766875 | F5: 0.15731843 | G5: 0.043006025 | H5: 0.10471344 | I5: 0.056332128 | J5: 0.036524921 | K5: 0.0042861649 | L5: 0.039322254 | M5: 0.13878683 | N5: 1
A6: 2023 | B6: 0.044023704 | C6: 0.03378271 | D6: 0.15766283 | E6: 0.1131105 | F6: 0.18124107 | G6: 0.064952781 | H6: 0.098351513 | I6: 0.06800722 | J6: 0.0018168022 | K6: 0.038881714 | L6: 0.092426375 | M6: 0.10574278 | N6: 1
A7: 2024 | B7: 0.0049847243 | C7: 0.075632707 | D7: 0.23239414 | E7: 0.10529112 | F7: 0.20165411 | G7: 0.074870125 | H7: 0.10112619 | I7: 0.037446128 | J7: 0.021658511 | K7: 0.10822482 | L7: 0.03046792 | M7: 0.0062495073 | N7: 1
A8: 2025 | B8: 0.0056427957 | C8: 0.031359727 | D8: 0.1892481 | E8: 0.13181258 | F8: 0.069327504 | G8: 0.12228476 | H8: 0.025410539 | I8: 0.15313768 | J8: 0.11648364 | K8: 0.056998534 | L8: 0.069579426 | M8: 0.028714713 | N8: 1
A9: 2026 | B9: 0.15434941 | C9: 0.12662727 | D9: 0.017039185 | E9: 0.15098949 | F9: 0.46159194 | G9: 0.089402708 | H9: 0 | I9: 0 | J9: 0 | K9: 0 | L9: 0 | M9: 0 | N9: 1
A10: Promedio | B10: =AVERAGE(B4:B9) -> 0.050842784 | C10: =AVERAGE(C4:C9) -> 0.072942281 | D10: =AVERAGE(D4:D9) -> 0.1266387 | E10: =AVERAGE(E4:E9) -> 0.13178596 | F10: =AVERAGE(F4:F9) -> 0.19907916 | G10: =AVERAGE(G4:G9) -> 0.095206928 | H10: =AVERAGE(H4:H9) -> 0.070666231 | I10: =AVERAGE(I4:I9) -> 0.061843919 | ... M10: =AVERAGE(M4:M9) -> 0.068043577 | N10: 1
A13: TABLA 2 – ESTACIONALIDAD PROMEDIO HISTÓRICA (2021-2026)
A15: Métrica | B15: Ene | C15: Feb | D15: Mar | E15: Abr | F15: May | G15: Jun | H15: Jul | I15: Ago | J15: Sep | K15: Oct | L15: Nov | M15: Dic
A16: Promedio Mensual ($) | B16: 1224921.9 | C16: 1886831.1 | D16: 2969544.3 | E16: 3421675.8 | F16: 4847208.8 | G16: 2328049.3 | H16: 1558032.9 | I16: 1663659.8 | J16: 1153816.6 | K16: 739238.7 | L16: 1128307 | M16: 1656682.4
